Workbook

Sheet Academic Signing Day
A1: ACADEMIC SIGNING DAY | B1: 2025 | S1: ACADEMIC SIGNING DAY | T1: 2024
A2: Total Sponsorship Amount Sold | B2: =SUM(D9:D27) -> 17500 | K2: OUTSTANDING | S2: Total Sponsorship Amount Sold | T2: =SUM(U9:U17) -> 15000
A3: Budget Goal | B3: 10000 | K3: =MIN(K23-B2) -> -1000 | S3: Budget Goal | T3: 9000
A4: Remaining Balance | B4: =MIN(B2-B3) -> 7500 | K4: =K23/B2 -> 0.94285714 | S4: Remaining Balance | T4: =MIN(T2-T3) -> 6000
A5: Stretch Goal | B5: 20000 | S5: Stretch Goal | T5: 11000
A6: Remaining Balance | B6: =MIN(B2-B5) -> -2500 | S6: Remaining Balance | T6: =MIN(T2-T5) -> 4000
A8: SPONSOR NAME | B8: SPONSORSHIP | C8: COST | D8: PRICE PLEDGED | E8: SOLD BY | F8: DATE SOLD | G8: NOTES | H8: SPECIAL BILLING | I8: INVOICED | J8: DATE PAID | K8: PAID AMOUNT | L8: CONTACT | M8: PHONE | N8: EMAIL | P8: SOLD BY | Q8: PLEDGED | S8: SPONSOR NAME | T8: SPONSORSHIP | U8: PRICE PLEDGED | V8: SOLD BY
A9: State Farm Jay Bernard | B9: Title | C9: 5000 | D9: 5000 | E9: BL | F9: 2.28.25 | G9: Will provide a $1000 scholarship | H9: YES | J9: 3.19.25 | K9: 5000 | L9: Jay Bernard | N9: jay.bernard.l8if@statefarm.com | P9: BL | Q9: 13500 | S9: Acxiom | T9: Presenting | U9: 3500 | V9: BL
A10: Acxiom | B10: Presenting | C10: 3500 | D10: 3500 | E10: BL | F10: 1.8.25 | J10: 5.1.25 | K10: 3500 | L10: Crystal Floyd, Alison Cowles | N10: Crystal.Floyd@acxiom.com; Alison.Cowles@acxiom.com | P10: BL-N | Q10: 4000 | S10: Conway Corporation | T10: Gold | U10: 1500 | V10: BL
A11: Turbare | B11: Awards | C11: 2500 | D11: 2500 | E11: BL-N | F11: 1.3.25 | G11: Turbare rep. will participate in awards presentation but no speaking role. | H11: YES | J11: 7.7.25 | K11: 2500 | L11: Laura Martin, Andria White | N11: ceo@turbare.org; awhite@turbare.org | P11: BL-O | S11: Conway Regional | T11: Gold | U11: 500 | V11: BL
B12: Media | C12: 2500 | P12: CP | S12: Crafton Tull | T12: Gold | U12: 1000 | V12: BL
A13: Virco | B13: Gold | C13: 1000 | D13: 1000 | E13: BL | F13: 12.2.24 | H13: YES | J13: 45902 | K13: 1000 | L13: Scotty Bell, Steve Presley | N13: scottybell@virco.com; stevepresley@virco.com | P13: CP-N | S13: Green Bay Packaging | T13: Gold | U13: 1000 | V13: BL
A14: Green Bay Packaging | B14: Gold | C14: 1000 | D14: 1000 | E14: BL | F14: 12.3.24 | H14: YES | J14: 6.5.25 | K14: 1000 | L14: Brad Harville, Christy Prater | N14: bharville@gbp.com, cprater@gbp.com | P14: CP-O | S14: Klaasmeyer | T14: Gold | U14: 1000 | V14: BL
A15: Conway Regional | B15: Gold | C15: 1000 | D15: 500 | E15: BL | F15: 12.30.24 | J15: 4.9.25 | K15: 500 | L15: Rebekah Fincher | N15: rfincher@conwayregional.org | P15: JE | S15: Smith Ford | T15: Gold | U15: 500 | V15: BL
A16: TriTechne | B16: Gold | C16: 1000 | D16: 1500 | E16: BL-N | F16: 1.9.25 | G16: Please send all invoices to ap@tritechne.com and Kara.Turner@tritechne.com | J16: 5.12.25 | K16: 1500 | L16: Lauren Blackwell | N16: lauren.blackwell@tritechne.com | P16: JE-N | S16: State Farm, Jay Bernard | T16: Title | U16: 5000 | V16: BL-N
A17: Crafton Tull | B17: Gold | C17: 1000 | D17: 1000 | E17: BL | F17: 1.10.25 | H17: YES | J17: 45887 | K17: 1000 | L17: Lane Housley | N17: lane.housley@craftontull.com | P17: JE-O | S17: Virco | T17: Gold | U17: 1000 | V17: BL
A18: Smith Ford | B18: Gold | C18: 1000 | D18: 500 | E18: BL | F18: 2.1.25 | J18: 4.7.25 | K18: 500 | L18: Cate McConnell | N18: cate.mcconnell@smithford.com | P18: JG
A19: Klaasmeyer | B19: Gold | C19: 1000 | D19: 1000 | E19: BL | F19: 3.4.25 | G19: Use money being held in BP account. | H19: YES | P19: JG-N
P20: JG-O
P21: LC
P22: LC-N
K23: =SUM(K9:K22) -> 16500 | P23: LC-O
P24: LH
P25: LH-N
P26: LH-O
P27: (blank)
P28: TOTAL | Q28: 17500
E300: BL-O
E301: BL-N
E302: BL
E303: CP-O
E304: CP-N
E305: CP
E306: JG-O
E307: JG-N
E308: JG
E309: JE-O
E310: JE-N
E311: JE
... E317: LH

Sheet Annual Meeting
A1: ANNUAL MEETING | B1: 2025 | S1: ANNUAL MEETING | T1: 2024
A2: Total Sponsorship Amount Sold | B2: =SUM(D9:D117) -> 293000 | G2: WAITLIST: | K2: OUTSTANDING | S2: Total Sponsorship Amount Sold | T2: =SUM(U9:U100) -> 305120
A3: Budget Goal | B3: 255000 | K3: =MIN(K120-B2) -> -22064.5 | S3: Budget Goal | T3: 215000
A4: Remaining Balance | B4: =MIN(B2-B3) -> 38000 | K4: =K120/B2 -> 0.92469454 | S4: Remaining Balance | T4: =MIN(T2-T3) -> 90120
A5: Stretch Goal | B5: 305000 | S5: Stretch Goal | T5: 300000
A6: Remaining Balance | B6: =MIN(B2-B5) -> -12000 | S6: Remaining Balance | T6: =MIN(T2-T5) -> 5120
A8: SPONSOR NAME | B8: SPONSORSHIP | C8: COST | D8: PRICE PLEDGED | E8: SOLD BY | F8: DATE SOLD | G8: NOTES | H8: SPECIAL BILLING | I8: INVOICED | J8: DATE PAID | K8: PAID AMOUNT | L8: CONTACT | M8: PHONE | N8: EMAIL | P8: SOLD BY | Q8: PLEDGED | S8: SPONSOR NAME | T8: SPONSORSHIP | U8: PRICE PLEDGED | V8: SOLD BY
A9: EOS Drew Spurgers | B9: Title | C9: 25000 | D9: 20000 | E9: LH-N | F9: 1.28.25 | G9: Drew wants to talk + do a video | H9: YES | J9: 45954 | K9: 8925 | L9: Drew Spurgers | N9: drew.spurgers@eosworldwide.com | P9: BL | Q9: 133000 | S9: Acxiom | T9: Presenting | U9: 15000 | V9: BL
A10: Acxiom | B10: Presenting | C10: 15000 | D10: 15000 | E10: BL | F10: 1.8.25 | J10: 3.13.25 | K10: 15000 | L10: Crystal Floyd, Alison Cowles | N10: Crystal.Floyd@acxiom.com; Alison.Cowles@acxiom.com | P10: BL-N | Q10: 12350 | S10: American Safeguard Insurance | T10: Silver | U10: 1500 | V10: LH
A11: First Security Bank/Crews & Associates | B11: Presenting | C11: 15000 | D11: 15000 | E11: BL | F11: 2.12.25 | J11: 2.26.25, 3.14.25 | K11: 7500 | L11: Jon Ross Henderson, Stefanie Vann | P11: BL-O | S11: ARcare | T11: Silver | U11: 1500 | V11: LH-N
B12: Presenting | C12: 15000 | J12: 3.14.25 | K12: 7500 | P12: CP | S12: Arkansas Business Publishing Group | T12: Silver | U12: 1500 | V12: BL
A13: UCA | B13: Underwriter | C13: 10000 | D13: 7000 | E13: LH-O | F13: 12.11.24 | G13: Plus $3,000 in-kind fo facility rental. | J13: 4.30.25 | K13: 7000 | L13: Amy Whitehead, Mary Lackie | N13: amyw@uca.edu; mlackie@uca.edu | P13: CP-N | Q13: 10850 | S13: Arkansas Roofing Kompany | T13: Gold | U13: 2850 | V13: LC
A14: Conway Regional | B14: Underwriter | C14: 10000 | D14: 10000 | E14: BL | F14: 12.30.24 | J14: 5.22.25 | K14: 10000 | L14: Rebekah Fincher | N14: rfincher@conwayregional.org | P14: CP-O | S14: Arvest | T14: Gold | U14: 2850 | V14: BL
A15: Turbare | B15: Underwriter | C15: 10000 | D15: 10000 | E15: BL | F15: 1.3.25 | G15: Turbare rep. speaks at event, 3 tables | H15: YES | J15: 4.15.25 | K15: 10000 | L15: Laura Martin, Andria White | N15: ceo@turbare.org; awhite@turbare.org | P15: JE | Q15: 8000 | S15: AT&T | T15: Silver | U15: 1500 | V15: JG-N
A16: Entergy | B16: Platinum | C16: 5000 | D16: 5000 | E16: BL-N | J16: 46010 | K16: 5000 | P16: JE-N | Q16: 5850 | S16: Bank OZK | T16: Silver | U16: 1500
A17: Virco | B17: Platinum | C17: 5000 | D17: 5000 | E17: BL | F17: 12.2.24 | G17: $1,500 in-kind for chair donation + one more table in addition to what they receive as a platinum sponsor. | H17: YES | J17: 1.29.25, 9/2/25, 9/8/25 | K17: =686.25+2813.75+1500 -> 5000 | L17: Scotty Bell, Steve Presley | N17: scottybell@virco.com; stevepresley@virco.com | P17: JE-O | S17: Baptist Health Conway | T17: Platinum | U17: 5000 | V17: JG
A18: Green Bay Packaging | B18: Platinum | C18: 5000 | D18: 5000 | E18: BL | F18: 12.3.24 | H18: YES | J18: 1.30.25 | K18: 5000 | L18: Brad Harville, Christy Prater | N18: bharville@gbp.com, cprater@gbp.com | P18: JG | Q18: 18500 | S18: Cadence Bank | T18: Silver | U18: 1500 | V18: LH
A19: Crafton Tull | B19: Platinum | C19: 5000 | D19: 5000 | E19: BL | F19: 1.10.25 | H19: YES | J19: 1.30.25; 8/18/25 | K19: =2755+1017 -> 3772 | L19: Lane Housley | N19: lane.housley@craftontull.com | P19: JG-N | Q19: 3000 | S19: Catalyst | T19: Platinum | U19: 5000 | V19: LH
J20: 3.19.25 | K20: 1228 | P20: JG-O | S20: Centennial Bank | T20: Gold | U20: 2850 | V20: BL
A21: Baptist Health | B21: Platinum | C21: 5000 | D21: 5000 | E21: JG | F21: 1.13.25 | J21: 3.7.25 | K21: 5000 | L21: April Bennett | P21: LC | Q21: 10000 | S21: Central Baptist College | T21: Silver | U21: 1500 | V21: LH-N
A22: Nabholz | B22: Platinum | C22: 5000 | D22: 5000 | E22: BL | F22: 2.2.25 | J22: 3.11.25 | K22: 5000 | L22: Jake Nabholz | N22: jake.nabholz@nabholz.com | P22: LC-N | Q22: 9000 | S22: Century 21 Sandstone Real Estate Group | T22: Silver | U22: 1500 | V22: LH
A23: Landmark CPAs | B23: Platinum | C23: 5000 | D23: 5000 | E23: LH | F23: 2.14.25 | H23: YES | J23: 6.6.25, 11/12/25 | K23: =241.25+672.5 -> 913.75 | L23: Randy Milligan | N23: RMilligan@landmarkcpas.com | P23: LC-O | S23: Chambers Bank | T23: Silver | U23: 1500 | V23: LC
J24: 6.16.25 | K24: 4086.25 | P24: LH | Q24: 34725 | S24: Cherokee Casino & Hotel Roland + Legends Resort & Casino | T24: Awards | U24: 5000 | V24: LH
A25: GARVER | B25: Platinum | C25: 5000 | D25: 5000 | E25: JG | F25: 2.18.25 | J25: 3.5.25 | K25: 5000 | L25: Dustin Tackett | N25: DLTackett@GarverUSA.com | P25: LH-N | Q25: 24500 | S25: Chick-fil-A | T25: Silver | U25: 1500 | V25: LH
A26: Trinity Development | B26: Platinum | C26: 5000 | D26: 5000 | E26: LH | F26: 2.26.25 | J26: 4.7.25 | K26: 5000 | L26: Courtnie Pledger | N26: cpledger@trinitydevelopmentinc.com | P26: LH-O | Q26: 12850 | S26: Chris Crain Enterprises | T26: Gold | U26: 2850 | V26: BL-N
A27: Cousins' Office Furniture | B27: Platinum | C27: 5000 | D27: 3500 | E27: LH | F27: 2.26.25 | J27: 3.24.25 | K27: 3500 | L27: Adam Robertson, Tara Robertson | N27: adam@cousinsfurniture.com; tara@cousinsfurniture.com | P27: (blank) | Q27: 7375 | S27: Cintas | T27: Gold | U27: 2450 | V27: LH
A28: Clayton Conway | B28: Platinum | C28: 5000 | D28: 4000 | E28: CP-N | F28: 2.28.25 | G28: All communications – Jamar Murchison – jamar.murchison@claytonhomes.com All communications – Stephanie Amerson – stephanie.amerson@claytonhomes.com Billing – Jake Turpin – jake.turpin@claytonhomes.com | J28: 45902 | K28: 4000 | L28: Jake Turpin | N28: jake.turpin@claytonhomes.com | P28: MM | Q28: 1500 | S28: City of Conway | T28: Silver | U28: 1500
A29: Tipton Hurst | B29: Floral | C29: 5000 | D29: 0 | G29: in-kind | P29: TP-N | Q29: 0 | S29: Coldwell Banker RPM: Lori Quinn & Velda Lueders | T29: Silver | U29: 1500 | V29: BL
A30: Conway Corp. | B30: Photo Booth | C30: 7500 | D30: 7500 | E30: BL | F30: 12.12.24 | H30: YES | J30: 3.24.25 | K30: 7500 | L30: Crystal Kemp | N30: Crystal.Kemp@conwaycorp.com | P30: KW-N | Q30: 1500 | S30: Colliers | T30: Silver | U30: 1500 | V30: BL
A31: Insight | B31: Awards | C31: 5000 | D31: 4000 | E31: CP-N | F31: 2.19.25 | H31: YES | J31: 2.28.25 | K31: 4000 | L31: Steven Tyler, Jenny Vallas | N31: steven.tyler@insight.com; jenny.vallas@insight.com | P31: TOTAL | Q31: 293000 | S31: Conductor | T31: Gold | U31: 2850 | V31: LH-N
S32: Conway Behavioral Health | T32: Silver | U32: 1500 | V32: LH
A33: Log Cabin Democrat | B33: Media | C33: 5000 | D33: 4000 | E33: JG | F33: 2.13.25 | J33: 3.27.25 | K33: 4000 | S33: Conway Corporation | T33: Photo Booth | U33: 7500 | V33: BL
A34: Crain Team | B34: Power Hour | C34: 20000 | D34: 15000 | E34: BL | F34: 1.7.25 | G34: Visit with Drew to determine which dealership(s) will be incorporated and how to handle billing. | J34: 4.14.25 | K34: 15000 | L34: Drew Dees, Christian Crain, Cameron Burdess, Justin Kervin | M34: Cameron: 501-339-1492 Justin: 501-687-3945 | N34: ddees@ltdconnect.com; christiancrain@crainteam.net; cameronburdess@crainteam.net; justinkervin@crainteam.net | S34: Conway Regional | T34: Underwriter | U34: 10000 | V34: BL
A35: Tommy's Express | B35: Arrival | C35: 5000 | D35: 5000 | E35: JE | F35: 12.16.24 | H35: YES | J35: 2.24.25 | K35: 5000 | L35: Kason Kimbrell | N35: kasonk@advancedwashnetwork.com | S35: Conway Wealth Management | T35: Silver | U35: 1500 | V35: BL
B36: Awards Reception | C36: 2500 | S36: Corco | T36: Silver | U36: 1500 | V36: BL-N
B37: Awards Reception | C37: 2500 | S37: Cousins' Office Furniture | T37: Speaker Reception | U37: 3500 | V37: LH
A38: Lake Liquor | B38: Beverage | C38: 2500 | D38: 2500 | E38: LC | F38: 3.6.25 | G38: Plus alcohol, no tables | S38: Covington Companies | T38: Silver | U38: 1500 | V38: BL
A39: Chris Crain Enterprises | B39: Gold | C39: 2850 | D39: 2850 | E39: BL | F39: 11.20.24 | G39: Confirm with NK/BB which Chris Crain Enterprises company/companies will be featured on event. | J39: 5.5.25 | K39: 2850 | L39: Brett Berry, Nita Kat Freeman | N39: brettberry@chriscraingroup.com; nitafreeman@chriscraingroup.com | S39: Crafton Tull | T39: Platinum | U39: 5000 | V39: BL
A40: Rogers Group | B40: Gold | C40: 2850 | D40: 2850 | E40: BL | F40: 1.3.25 | J40: 2.24.25 | K40: 2850 | L40: Mike Connelly | N40: mike.connelly@rogersgroupinc.com | S40: Crain Team | T40: Power Hour | U40: 15000 | V40: BL-N
A41: Simmons Bank | B41: Gold | C41: 2850 | D41: 2850 | E41: BL | F41: 1.2.25 | J41: 3.7.25 | K41: 2850 | L41: Justin McCarty | N41: justin.mccarty@simmonsbank.com | S41: Cromwell Architects | T41: Silver | U41: 1500 | V41: JG-N
A42: Conductor | B42: Gold | C42: 2850 | D42: 2850 | E42: LH-O | F42: 1.13.25 | J42: 2.18.25 | K42: 2850 | L42: Grace Rains | N42: grace@arconductor.org | S42: Dave Creek Media | T42: Silver | U42: 1500 | V42: LH-O
A43: Engage Management | B43: Gold | C43: 2850 | D43: 2850 | E43: BL | F43: 2.2.25 | J43: 2.25.25 | K43: 2850 | L43: Morgan Lefler | N43: morgan.lefler@engagemanagement.com | S43: Diamond State Restoration | T43: Silver | U43: 1500 | V43: LC
A44: First Service Bank | B44: Gold | C44: 2850 | D44: 2850 | E44: BL | F44: 2.2.25 | J44: 2.26.25 | K44: 2850 | L44: Kevin Wish, Destiny Lankford | N44: kevin.wish@firstservicebank.com; destiny.lankford@firstservicebank.com | S44: Edafio | T44: Silver | U44: 1500 | V44: LC
A45: Events Rental | B45: Gold | C45: 2850 | D45: 0 | E45: TP-N | F45: 2.4.25 | G45: in-kind for discounted invoice | S45: Empower Healthcare Solutions | T45: Silver | U45: 1500 | V45: LH-N
A46: Arvest | B46: Gold | C46: 2850 | D46: 2850 | E46: BL | F46: 2.4.25 | H46: YES | J46: 4.28.25 | K46: 2850 | L46: Brooks Davis, Maret Cahill Wicks | N46: mcahillwicks@arvest.com; bdavis3@arvest.com | S46: Engage Management | T46: Gold | U46: 2850 | V46: BL
A47: Cintas | B47: Gold | C47: 2850 | D47: 2450 | E47: LH | F47: 2.25.25 | S47: EOS Worldwide: Drew Spurgers | T47: Presenting | U47: 15000 | V47: LH-N
A48: DKM Construction | B48: Gold | C48: 2850 | D48: 2850 | E48: CP-N | F48: 2.17.25 | H48: YES | J48: 4.7.25 | K48: 2850 | L48: Kim Morehart, Daniel Morehart | N48: kimm.dkm@gmail.com; danielm.dkm@gmail.com | S48: ERI | T48: Silver | U48: 1500 | V48: BL
A49: Catalyst Financial | B49: Gold | C49: 2850 | D49: 2850 | E49: LH | F49: 2.24.25 | J49: 2.28.25 | K49: 2850 | L49: Drew Gainor, Danielle Davis | N49: DanielleDavis@financialguide.com; dgainor@financialguide.com | S49: Exchange Capital | T49: Silver | U49: 1500 | V49: JE
A50: Ensono | B50: Gold | C50: 2850 | D50: 2850 | E50: BL-N | F50: 2.24.25 | H50: YES | J50: 4.3.25 | K50: 2850 | L50: Michelle McKown | N50: michelle.mckown@ensono.com | S50: Express Employment | T50: Silver | U50: 1500 | V50: LH
A51: Centennial Bank | B51: Gold | C51: 2850 | D51: 2850 | E51: BL | J51: 3.7.25 | K51: 2850 | S51: Fairfield by Mariott | T51: Ticket | U51: 300
A52: Farris Agency | B52: Gold | C52: 2850 | D52: 2850 | E52: JE-N | F52: 2.18.25 | J52: 3.3.25 | K52: 2850 | L52: Alan White, Travis Mulhearn, Christina Horn | S52: Farris Agency | T52: Silver | U52: 1500 | V52: JE-N
A53: Kutak Rock | B53: Gold | C53: 2850 | D53: 2850 | E53: BL | F53: 3.17.25 | G53: One table only | J53: 5.6.25 | K53: 2850 | L53: Gordon Wilbourn | N53: gordon.wilbourn@kutakrock.com | S53: First Arkansas Bank & Trust | T53: Silver | U53: 925 | V53: LH
A54: Pafford | B54: Gold | C54: 2850 | D54: 2850 | E54: BL | F54: 3.17.25 | G54: One table only | J54: 3.18.25 | K54: 2850 | S54: First Community Bank | T54: Silver | U54: 1500 | V54: BL
A55: Westrock Coffee | B55: Gold | C55: 2850 | D55: 2850 | E55: BL | F55: 3.17.25 | G55: One table only | H55: YES | J55: 4.25.25 | K55: 2850 | L55: Melissa Mackay, Blaire Peterson | N55: melissa.mackay@westrockcoffee.com; blair.peterson@westrockcoffee.com | S55: First Security Bank/Crews & Associates | T55: Presenting | U55: 15000 | V55: BL
A56: B&A Property Maintenance | B56: Silver | C56: 1500 | D56: 1500 | E56: JG-N | J56: 3.11.25 | K56: 1500 | N56: alan@farrisagency.com travis@farrisagency.com christina@farrisagency.com | S56: First Service Bank | T56: Platinum | U56: 5000 | V56: BL-N
A57: Exchange Capital | B57: Silver | C57: 1500 | D57: 1500 | E57: JE | F57: 12.10.24 | J57: 3.24.25 | K57: 1500 | L57: Scott Coffey | N57: scott@excap.com | S57: Flywheel Energy | T57: Silver | U57: 1500 | V57: BL
A58: Bank OZK | B58: Silver | C58: 1500 | D58: 1500 | E58: MM | F58: 12.12.24 | J58: 3.12.25 | K58: 1500 | L58: Debbie Townsend | N58: debbie.townsend@ozk.com | S58: Garcia Wealth Management | T58: Silver | U58: 1500 | V58: LH
A59: First Arkansas Bank & Trust | B59: Silver | C59: 1500 | D59: 925 | E59: LH | F59: 12.9.24 | H59: YES | J59: 1.31.25 | K59: 925 | L59: John Simmons, Roger Sundermeier, Mark Wilson, Jessica Pint | N59: jsimmons@fabandt.bank; rsundermeier@fabandt.bank; mwilson@fabandt.bank; jpint@fabandt.bank | S59: GARVER | T59: Platinum | U59: 5000 | V59: JG
A60: Natural State Consulting | B60: Silver | C60: 1500 | D60: 1500 | E60: JG | F60: 12.18.24 | G60: Ask Jamie how to invoice | J60: 2.3.25 | K60: 1500 | L60: Steve Goode | N60: stevegoode.naturalstate@gmail.com | S60: Green Bay Packaging | T60: Platinum | U60: 5000 | V60: BL
B61: Silver | C61: 1500 | S61: H+N Architects | T61: Gold | U61: 2850 | V61: LH-N
A62: Covington | B62: Silver | C62: 1500 | D62: 1500 | E62: BL | J62: 5.1.25 | K62: 1500 | L62: George Covington, Savannah Brorman | N62: gcov@conwaycorp.net; savannah@covingtoncompanies.net | S62: Hampton Inn & Suites | T62: Silver | U62: 1500 | V62: JE-O
A63: American Safeguard Insurance | B63: Silver | C63: 1500 | D63: 1500 | E63: LH | F63: 12.23.24 | H63: YES | J63: 1.17.25 | K63: 1441.25 | L63: Jeremy Davis, Jason Smith, Brittney Gwatney | N63: jdavis@asiagents.com; jsmith@asiagents.com; bgwatney@asiagents.com | S63: Hawkins Insurance | T63: Silver | U63: 1500 | V63: JE
J64: 4.9.25 | K64: 58.75 | S64: HCJ CPAs & Advisors | T64: Silver | U64: 1500 | V64: BL
A65: Watson Homes/RE/Max Elite | B65: Silver | C65: 1500 | D65: 1500 | E65: JE-N | F65: 1.16.25 | G65: Both names on the table tent. Send invoice to Watson Homes. | J65: 3.3.25 | K65: 1500 | L65: Lauren Fulmer | N65: lauren@watsonhomesinc.com | S65: HSA Engineering | T65: Speaker Reception | U65: 2545 | V65: LH-N
A66: City Church | B66: Silver | C66: 1500 | D66: 1500 | E66: BL-N | F66: 1.23.25 | G66: Per Brad send invoice now. | J66: 2.4.25 | K66: 1500 | L66: Erin Long | N66: erin@citychurch.tv | S66: Insight | T66: Gold | U66: 2850 | V66: CP-N
A67: TriTechne | B67: Silver | C67: 1500 | D67: 1500 | E67: BL-N | F67: 1.9.25 | G67: Please send all invoices to ap@tritechne.com and Kara.Turner@tritechne.com | J67: 4.4.25 | K67: 1500 | L67: Lauren Blackwell | N67: lauren.blackwell@tritechne.com | S67: Jason Owens Law Firm | T67: Silver | U67: 1500 | V67: LC
A68: Central Baptist College | B68: Silver | C68: 1500 | D68: 1500 | E68: LH | F68: 1.28.25 | J68: 3.4.25 | K68: 1500 | L68: Jessica Faulkner, Terry Kimbrow, Jeremy Langley | N68: jfaulkner@cbc.edu; tkimbrow@cbc.edu; JLangley@cbc.edu | S68: JSI Metal & Recycling | T68: Silver | U68: 1500 | V68: LH-O
A69: Hawkins Insurance | B69: Silver | C69: 1500 | D69: 1500 | E69: JE | F69: 1.28.25 | L69: Andy Hawkins | N69: andy@justuslandryhawkins.com | S69: Kelley Commercial Partners | T69: Silver | U69: 1500 | V69: BL
A70: Smith Ford | B70: Silver | C70: 1500 | D70: 1500 | E70: BL | F70: 2.1.25 | J70: 4.7.25 | K70: 1500 | L70: Cate McConnell | N70: cate.mcconnell@smithford.com | S70: Kindred Mercantile | T70: Silver | U70: 1500
A71: Winthrop Rockefeller Institute | B71: Silver | C71: 1500 | D71: 1500 | E71: JG | F71: 2.4.24 | J71: 4.9.25 | K71: 1500 | L71: Austin DuVall, Julia Dossett Morgan | N71: ADuVall@rockefellerinstitute.org; JMorgan@rockefellerinstitute.org | S71: Kutak Rock | T71: Gold | U71: 2850 | V71: BL-N
A72: Sissy's Log Cabin | B72: Silver | C72: 1500 | D72: 1500 | E72: LH | F72: 2.4.25 | L72: Sonya Williams | S72: Lake Liquor | T72: Beverage | U72: 2500 | V72: LC
A73: RE/MAX Elite: The Emily Walter Team | B73: Silver | C73: 1500 | D73: 1500 | E73: LC | F73: 2.7.25 | J73: 3.24.25 | K73: 1500 | L73: Emily Walter | N73: emilywalterrealtor@gmail.com | S73: Landmark CPAs | T73: Platinum | U73: 5000 | V73: LH
A74: Ott Insurance | B74: Silver | C74: 1500 | D74: 1500 | E74: LC | F74: 2.7.25 | J74: 3.18.25 | K74: 1500 | L74: Michelle Mallett | N74: michellemallett@ottinsurance.com | S74: MAC Aesthetics and Wellness | T74: Silver | U74: 1500 | V74: LC-N
A75: Jason Owen's Law Firm | B75: Silver | C75: 1500 | D75: 1500 | E75: LC | F75: 2.7.25 | J75: 3.7.25 | K75: 1500 | L75: Brooklyn Parker | N75: parker@jowenslawfirm.com | S75: Malvern National Bank | T75: Silver | U75: 1500 | V75: LH
A76: WACO Title | B76: Silver | C76: 1500 | D76: 1500 | E76: LC-N | F76: 2.7.25 | L76: Ryke Dismuke, Brooklyn Burnett | N76: idismuke@wacotitle.com: bburnett1@wacotitle.com | S76: Mark Ledbetter | T76: Ticket | U76: 900
A77: CARTI | B77: Silver | C77: 1500 | D77: 1500 | E77: LC-N | F77: 2.12.25 | J77: 4.9.25 | K77: 1500 | L77: Carroll Jo Malloy | N77: CarrollJo.Malloy@CARTI.com | S77: Nabholz | T77: Platinum | U77: 5000 | V77: BL
A78: HSA Engineering | B78: Silver | C78: 1500 | D78: 1500 | E78: LH | F78: 2.7.25 | H78: YES | J78: 3.7.25 | K78: 1500 | L78: Trey White, Michael Rappold | N78: twhite@hsaconsultants.com; mrappold@hsaconsultants.com | S78: Natural State Consulting & Strategies | T78: Silver | U78: 1500 | V78: JG
A79: United Way | B79: Silver | C79: 1500 | D79: 1500 | F79: 2.13.25 | J79: 4.17.25 | K79: 1500 | S79: Northwestern Mutual | T79: Silver | U79: 1500 | V79: LH-N
A80: PCSI | B80: Silver | C80: 1500 | D80: 1500 | E80: LC-N | F80: 2.13.25 | J80: 4.3.25 | K80: 1500 | S80: Ott Insurance | T80: Silver | U80: 1500 | V80: LC
A81: Fair & Company | B81: Silver | C81: 1500 | D81: 1500 | E81: KW-N | F81: 2.14.25 | J81: 3.18.25 | K81: 1500 | L81: Nick Schroeder | S81: Pafford | T81: Gold | U81: 2850 | V81: BL-N
A82: Cadance Bank | B82: Silver | C82: 1500 | D82: 1500 | E82: LH | F82: 2.14.25 | J82: 2.21.25 | K82: 1500 | L82: Tom Nelson | S82: RE/MAX Elite: The Emily Walter Team | T82: Silver | U82: 1500 | V82: LC
A83: Pine Street Backpack Program | B83: Silver | C83: 1500 | D83: 1500 | E83: JE-N | F83: 2.14.25 | J83: 2.27.25 | K83: 1500 | L83: Gena Ester | N83: Gester64@yahoo.com | S83: Rogers Group | T83: Gold | U83: 2850 | V83: BL
B84: Silver | C84: 1500 | S84: SGA | T84: Silver | U84: 0
A85: Coldwell Banker RPM | B85: Silver | C85: 1500 | D85: 1500 | F85: 2.14.25 | J85: 3.7.25 | K85: 1500 | L85: Lori Quinn, Velda Lueders | N85: loriquinn@conwaycorp.net; velda@veldalueders.com | S85: Simmons Bank | T85: Title | U85: 20000 | V85: BL-N
A86: Colliers | B86: Silver | C86: 1500 | D86: 1500 | E86: BL | F86: 2.14.25 | J86: 3.7.25 | K86: 1500 | L86: TJ Johnston, Amy Meins | N86: tj.johnston@colliers.com; amy.meins@colliers.com | S86: Sissy's Log Cabin | T86: Underwriter | U86: 10000 | V86: LH-N
A87: Century 21 Sandstone Real Estate Group | B87: Silver | C87: 1500 | D87: 1500 | E87: LH | F87: 2.17.25 | J87: 4.28.25 | K87: 1500 | L87: Korry Garrett | N87: korrygarrett@yahoo.com | S87: Smith Ford | T87: Silver | U87: 1500 | V87: BL
A88: Sowell Ferris Architects | B88: Silver | C88: 1500 | D88: 1500 | E88: LH | F88: 2.18.25 | J88: 3.3.25 | K88: 1500 | L88: Cody Ferris, Emily Ferris | N88: cody@sowellarchitects.com; emily@sowellarchitects.com | S88: Sowell Architects | T88: Silver | U88: 1500 | V88: LH-N
A89: Malvern National Bank | B89: Silver | C89: 1500 | D89: 1500 | E89: LH | F89: 2.18.25 | J89: 4.14.25 | K89: 1500 | L89: Andy Harris, Alica Brown, Alexander Baney | N89: aharris@mnbbank.com; abrown@mnbbank.com; abaney@mnbbank.com | S89: State Farm Insurance, Jay Bernard | T89: Silver | U89: 1500 | V89: BL-N
A90: HCJ CPAs & Advisors | B90: Silver | C90: 1500 | D90: 1500 | E90: LH-O | F90: 2.20.25 | J90: 3.18.25 | K90: 1500 | L90: Karen Garrett | N90: KGarrett@hcjcpa.com | S90: Steve Wade | T90: Ticket | U90: 300 | V90: LH
A91: Hardwyre | B91: Silver | C91: 1500 | D91: 1500 | E91: LH-N | F91: 2.21.25 | J91: 3.31.25 | K91: 1500 | L91: Steve Wade | N91: steve.wade@hardwyre.com | S91: The Log Cabin | T91: Media | U91: 4000 | V91: JG
A92: Douglas Companies | B92: Silver | C92: 1500 | D92: 1500 | E92: JG-N | F92: 2.21.25 | J92: 3.3.25 | K92: 1500 | L92: Susie Munson | N92: smunson@douglascomp.com | S92: Tipton Hurst | T92: Floral | U92: 0 | V92: BL
A93: H+N Architects | B93: Silver | C93: 1500 | D93: 1500 | E93: LH | F93: 2.21.25 | H93: YES | J93: 4.25.25 | K93: 1500 | L93: Liz Hamilton | N93: liz@hnarch.com | S93: Tommy's Express Carwash | T93: Arrival | U93: 5000 | V93: JE-N
A94: ERI | B94: Silver | C94: 1500 | D94: 1500 | E94: BL | F94: 2.23.25 | J94: 3.10.25 | K94: 1500 | L94: Rob Bell | N94: rob@ericrobisaac.com | S94: Trinity Development | T94: Platinum | U94: 5000 | V94: LH
A95: Conway Wealth Management | B95: Silver | C95: 1500 | D95: 1500 | E95: BL | F95: 2.23.25 | H95: YES | J95: 3.21.25 | K95: 885 | L95: Greg Pillow, Rita Stapleton | N95: rita@conwaywm.com; greg@conwaywm.com | S95: Turbare | T95: Underwriter | U95: 10000 | V95: BL-N
J96: 4.28.25 | K96: 615 | S96: UACCM | T96: Silver | U96: 1500 | V96: JG
A97: Ascend | B97: Silver | C97: 1500 | D97: 1500 | E97: LC | F97: 2.24.25 | J97: 3.31.25 | K97: 1500 | L97: Kenny Kinley | N97: kkinley@teamascend.com | S97: UCA | T97: Underwriter | U97: 7000 | V97: LH-O
A98: JSI Metal Recycling | B98: Silver | C98: 1500 | D98: 1500 | E98: LH-O | F98: 2.24.25 | J98: 3.21.25 | K98: 1500 | L98: Jessie McCoy | N98: jessie@jsimetal.com | S98: Virco | T98: Platinum | U98: 3500 | V98: BL-N
A99: Arkansas Business | B99: Silver | C99: 1500 | D99: 1500 | E99: BL | F99: 2.24.25 | J99: 4.17.25 | K99: 1500 | L99: Mitch Bettis | N99: mbettis@abpg.com | S99: Westrock Coffee | T99: Gold | U99: 2850 | V99: BL-N
A100: Gratus Wealth Management Northwestern Mutual | B100: Silver | C100: 1500 | D100: 1500 | E100: LH-N | F100: 2.13.25 | H100: YES | J100: 3.13.25; 8/4/25 | K100: =64.5+192 -> 256.5 | L100: Osmar Garcia, Gilberto Garcia, Miranda Hogg | N100: osmar.a.garcia@nm.com; miranda.hogg@nm.com; gilberto.garcia@nm.com | S100: Winthrop Rockefeller Institute | T100: Silver | U100: 1500 | V100: JG
J101: 4.15.25 | K101: 414.5
...

Sheet Baggo for Business
A1: BAGGO FOR BUSINESS | B1: 2025 | S1: BAGGO FOR BUSINESS | T1: 2024
A2: Total Sponsorship Amount Sold | B2: =SUM(D9:D74) -> 29800 | G2: 2026: Rhea Lana's waive 2 teams | K2: OUTSTANDING | S2: Total Sponsorship Amount Sold | T2: =SUM(U9:U54) -> 29300
A3: Budget Goal | B3: 20000 | K3: =MIN(K62-B2) -> -2000 | S3: Budget Goal | T3: 17500
A4: Remaining Balance | B4: =MIN(B2-B3) -> 9800 | K4: =K62/B2 -> 0.93288591 | S4: Remaining Balance | T4: =MIN(T2-T3) -> 11800
A5: Stretch Goal | B5: 32000 | S5: Stretch Goal | T5: 27000
A6: Remaining Balance | B6: =MIN(B2-B5) -> -2200 | S6: Remaining Balance | T6: =MIN(T2-T5) -> 2300
A8: SPONSOR NAME | B8: SPONSORSHIP | C8: COST | D8: PRICE PLEDGED | E8: SOLD BY | F8: DATE SOLD | G8: NOTES | H8: SPECIAL BILLING | I8: INVOICED | J8: DATE PAID | K8: PAID AMOUNT | L8: CONTACT | M8: PHONE | N8: EMAIL | P8: SOLD BY | Q8: PLEDGED | S8: SPONSOR NAME | T8: SPONSORSHIP | U8: PRICE PLEDGED | V8: SOLD BY
A9: American Safeguard Insurance | B9: Title | C9: 5000 | D9: 5000 | E9: LH | F9: 12.23.24 | H9: YES | J9: 4.9.25 | K9: 4027.5 | L9: Jeremy Davis, Jason Smith, Brittney Gwatney | N9: jdavis@asiagents.com; jsmith@asiagents.com; bgwatney@asiagents.com | P9: BL | Q9: 5150 | S9: AFCU | T9: Silver | U9: 350
J10: 7.28.25 | K10: 972.5 | P10: BL-N | Q10: 4000 | S10: American Safeguard Insurance | T10: Title | U10: 5000 | V10: LH
A11: Turbare | B11: Presenting | C11: 2500 | D11: 2500 | E11: BL-N | F11: 1.3.25 | G11: 8 players | H11: YES | J11: 46008 | K11: 500 | L11: Laura Martin, Andria White | N11: ceo@turbare.org; awhite@turbare.org | P11: BL-O | S11: Andy's Frozen Custard | T11: Silver | U11: 350 | V11: LH-N
A12: HD Roofing | B12: Presenting | C12: 2500 | D12: 2500 | E12: LC | F12: 8.7.25 | I12: 8/15/25 GB | J12: 45931 | K12: 2500 | L12: Amber Watkins | N12: office@hdroofing-construction.com | P12: CP | Q12: 1100 | S12: Bank OZK | T12: Silver | U12: 400
A13: Rock City Outfitters | B13: T-Shirt | C13: 1500 | D13: 1000 | E13: LC | F13: 2.24.25 | I13: 7/17/25 GB | J13: 45910 | K13: 1000 | L13: Ryan Ritchie | N13: ryan@rockcityoutfitters.com | P13: CP-N | Q13: 600 | S13: Bledsoe Chiropractic | T13: Gold | U13: 600 | V13: LC
A14: Farris Agency | B14: Lunch | C14: 1000 | D14: 1000 | E14: JE | F14: 12.4.24 | I14: 7/17/25 GB | J14: 7.25.25 | K14: 1000 | L14: Alan White, Travis Mulhearn, Christina Horn | N14: alan@farrisagency.com travis@farrisagency.com christina@farrisagency.com | P14: CP-O | S14: Cadence Bank | T14: Silver | U14: 350 | V14: LH-N
A15: Smith Ford | B15: Lunch | C15: 1000 | D15: 1000 | E15: BL | F15: 2.1.25 | I15: 7/17/25 GB | J15: 45917 | K15: 1000 | L15: Cate McConnell | N15: cate.mcconnell@smithford.com | P15: JE | Q15: 1850 | S15: Chambers Bank | T15: Gold | U15: 600 | V15: LC-N
A16: Cross Creek Sandwich Shop | B16: Lunch | C16: 1000 | D16: 0 | E16: LC | F16: 4.28.25 | G16: in-kind for food | I16: 0 | K16: 0 | L16: Caitlin Bailey | N16: crosscreekcaitlin@gmail.com | P16: JE-N | Q16: 350 | S16: Chris Crain Enterprises | T16: Silver | U16: 0 | V16: BL
A17: RE/MAX Elite: The Emily Walter Team | B17: Baggo Brews | C17: 1000 | D17: 1000 | E17: LC-N | F17: 2.7.25 | I17: 7/17/25 GB | J17: 45911 | K17: 1000 | L17: Emily Walter | N17: emilywalterrealtor@gmail.com | P17: JE-O | S17: City of Conway | T17: Silver | U17: 0
A18: Car-Son Construction | B18: Baggo Brews | C18: 1000 | D18: 1000 | E18: BL-N | F18: 2.28.25 | G18: 2 teams, 4 players total | H18: YES | J18: 45950 | K18: 1000 | L18: Brad Fason, Brian Fason | N18: bfason@car-son.com; bradfason@car-son.com | P18: JG | S18: Conway Regional | T18: Gold | U18: 500 | V18: BL
A19: Rouge Roundabout | B19: Baggo Brews | C19: 1000 | D19: 0 | F19: 8.21.25 | G19: in-kind for alcohol | I19: 0 | K19: 0 | P19: JG-N | Q19: 0 | S19: Crain Team | T19: Silver | U19: 0 | V19: BL-N
A20: Dyermark | B20: Photo Booth | C20: 1000 | D20: 1000 | E20: LC | F20: 2.11.25 | H20: YES | J20: 9/16/2025, 10/13/25, 11/18/25 | K20: =112.5+512.5+375 -> 1000 | L20: Ali Dyer | N20: ali@dyermark.com | P20: JG-O | S20: Cross Creek Sandwich Shop | T20: Lunch | U20: 0 | V20: LC-N
A21: Green Bay Packaging | B21: Gold | C21: 600 | D21: 500 | E21: BL | F21: 12.3.24 | H21: YES | I21: 0 | J21: 6.5.25 | K21: 500 | L21: Brad Harville, Christy Prater | N21: bharville@gbp.com, cprater@gbp.com | P21: LC | Q21: 6050 | S21: Diamond State Restoration | T21: Gold | U21: 600 | V21: LC-N
A22: Conway Regional | B22: Gold | C22: 600 | D22: 500 | E22: BL | F22: 12.30.24 | I22: 7/17/25 GB | J22: 7.23.25 | K22: 500 | L22: Rebekah Fincher | N22: rfincher@conwayregional.org | P22: LC-N | Q22: 3000 | S22: DKM Construction | T22: Gold | U22: 600 | V22: CP-N
A23: Simmons Bank | B23: Gold | C23: 600 | D23: 500 | E23: BL | F23: 1.2.25 | I23: 7/17/25 GB | J23: 7.28.25 | K23: 500 | L23: Justin McCarty | N23: justin.mccarty@simmonsbank.com | P23: LC-O | S23: Dyermark | T23: Photo Booth | U23: 1000 | V23: LC-N
A24: Insight | B24: Gold | C24: 600 | D24: 500 | E24: CP | F24: 2.19.25 | H24: YES | I24: 0 | J24: 4.8.25 | K24: 500 | L24: Steven Tyler, Jenny Vallas | N24: steven.tyler@insight.com; jenny.vallas@insight.com | P24: LH | Q24: 5700 | S24: Engage Management | T24: Silver | U24: 350 | V24: BL-N
A25: Sowell Ferris Architects | B25: Gold | C25: 600 | D25: 600 | E25: LH-O | F25: 2.18.25 | I25: 7/17/25 GB | J25: 45903 | K25: 600 | L25: Cody Ferris, Emily Ferris | N25: cody@sowellarchitects.com; emily@sowellarchitects.com | P25: LH-N | S25: Farris Agency | T25: Lunch | U25: 1000 | V25: JE-N
A26: Sinco | B26: Gold | C26: 600 | D26: 600 | E26: CP | F26: 2.21.25 | H26: YES | J26: 45888 | K26: 600 | L26: Parker Spradlin, Grey Williams, Rhonda Wilson | N26: Pspradlin@sincoinc.com; gwilliams@sincoinc.com; rwilson@sincoinc.com | P26: LH-O | Q26: 950 | S26: First Arkansas Bank & Trust | T26: Silver | U26: 0 | V26: LH
A27: Entergy | B27: Gold | C27: 600 | D27: 600 | E27: CP-N | F27: 2.26.25 | G27: Region Construction team will pay for this, so invoice James Warren | I27: 7/17/25 GB | J27: 7.17.25 | K27: 600 | L27: Zack Hale, James Warren | N27: zhale@entergy.com; jwarren@entergy.com | P27: (blank) | Q27: 1050 | S27: First Community Bank | T27: Gold | U27: 500 | V27: BL
A28: Chambers Bank | B28: Gold | C28: 600 | D28: 600 | E28: LC | F28: 2.27.25 | I28: 7/17/25 GB | J28: 7.22.25 | K28: 600 | L28: Ethan Barnes | N28: ebarnes@chambers.bank | P28: TOTAL | Q28: 29800 | S28: First Security Bank | T28: Gold | U28: 500 | V28: BL
A29: State Farm Jay Bernard | B29: Gold | C29: 600 | D29: 500 | E29: BL-N | F29: 2.28.25 | H29: YES | I29: 0 | J29: 3.19.25 | K29: 500 | L29: Jay Bernard | N29: jay.bernard.l8if@statefarm.com | S29: Green Bay Packaging | T29: Gold | U29: 500 | V29: BL
A30: Bledsoe Chiropractic | B30: Gold | C30: 600 | D30: 600 | E30: LC | F30: 3.19.25 | H30: YES | I30: 0 | J30: 6.16.25 | K30: 600 | L30: Amanda Bledsoe, Sarah Lockard | N30: dramandabledsoe@gmail.com; sarah@bledsoechiropractic.com | S30: HD Roofing | T30: Presenting | U30: 2500 | V30: LC
A31: First Security Bank | B31: Gold | C31: 600 | D31: 500 | E31: BL | F31: 3.19.25 | I31: 7/17/25 GB | J31: 45925 | K31: 500 | L31: Stefanie Vann | N31: stefanie.vann@fsbank.com | S31: Insight | T31: Gold | U31: 500 | V31: CP
A32: Molex | B32: Gold | C32: 600 | D32: 1800 | E32: BL | F32: 3.28.25 | I32: 7/17/25 GB | J32: 45905 | K32: 1800 | L32: Cory Ensley | N32: cory.ensley@molex.com | S32: Jakob Henry | T32: Silver | U32: 350 | V32: JE-N
A33: Pro-Land Title | B33: Gold | C33: 600 | D33: 600 | E33: LC-N | F33: 4.11.25 | I33: 7/17/25 GB | J33: 45910 | K33: 600 | L33: Brooklyn Cardin | N33: bcardin@prolandtitle.com | S33: Lake Liquor | T33: Baggo Brews | U33: 1000 | V33: LC
B34: Gold | C34: 600 | S34: Malvern National Bank | T34: Silver | U34: 200 | V34: LH
B35: Gold | C35: 600 | S35: Market Place Grill | T35: Silver | U35: 350 | V35: JE-N
A36: Arkansas Federal Credit Union | B36: Silver | C36: 350 | D36: 350 | E36: LH-O | F36: 8.28.25 | G36: One team from 10:00 - 12:00: Tiffany Mitchell and Sidney Foltz | I36: 9/4/25 GB | J36: 45917 | K36: 350 | L36: Denise Goforth | N36: dgoforth@arcu.org | S36: Molex | T36: Gold | U36: 1800 | V36: BL-N
A37: Chris Crain Enterprises | B37: Silver | C37: 350 | D37: 0 | E37: BL | F37: 11.20.24 | G37: Confirm with NK/BB which Chris Crain Enterprises company/companies will be featured on event. | I37: 0 | L37: Brett Berry, Nita Kat Freeman | N37: brettberry@chriscraingroup.com; nitafreeman@chriscraingroup.com | S37: Ott Insurance | T37: Gold | U37: 600 | V37: LC
A38: Rhea Lana's | B38: Silver | C38: 350 | D38: 0 | E38: LH-O | F38: 45620 | G38: 2 Teams | I38: 0 | L38: Rhea Lana Riner, Hannah Johnson, Abbie Kent | N38: rhealana@rhealana.com; hannahjohnson@rhealana.com; abbie@rhealana.com | S38: Paladino Nash | T38: Silver | U38: 0 | V38: LH-N
A39: First Arkansas Bank & Trust | B39: Silver | C39: 350 | D39: 0 | E39: LH | F39: 12.9.24 | I39: 0 | L39: John Simmons, Roger Sundermeier, Mark Wilson, Jessica Pint | N39: jsimmons@fabandt.bank; rsundermeier@fabandt.bank; mwilson@fabandt.bank; jpint@fabandt.bank | S39: Pro Ridge Roofing | T39: Silver | U39: 350 | V39: LC-N
A40: Crain Team | B40: Silver | C40: 350 | D40: 0 | E40: BL | F40: 1.7.25 | G40: 2 teams - one for each dealership | I40: 0 | L40: Drew Dees, Christian Crain, Cameron Burdess, Justin Kervin | M40: Cameron: 501-339-1492 Justin: 501-687-3945 | N40: ddees@ltdconnect.com; christiancrain@crainteam.net; cameronburdess@crainteam.net; justinkervin@crainteam.net | S40: Rhea Lana's | T40: Silver | U40: 700 | V40: JE-N
A41: Engage Management | B41: Silver | C41: 350 | D41: 350 | E41: BL | F41: 2.2.25 | I41: 7/17/25 GB | J41: 45880 | K41: 350 | L41: Morgan Lefler | N41: morgan.lefler@engagemanagement.com | S41: Rock City Outfitters | T41: T-Shirt | U41: 1000 | V41: LC
A42: Ott Insurance | B42: Silver | C42: 350 | D42: 350 | E42: LC | F42: 2.7.25 | I42: 7/17/25 GB | J42: 45887 | K42: 350 | L42: Michelle Mallett | N42: michellemallett@ottinsurance.com | S42: Rogue Roundabout | T42: Baggo Brews | U42: 0 | V42: LH-N
A43: St. Francis Veterinary Clinic | B43: Silver | C43: 350 | D43: 850 | E43: JE | F43: 2.24.25 | G43: 5 total teams | I43: 7/17/25 GB | J43: 45883 | K43: 850 | L43: Sharon Stone, Rachel Mears | N43: stfrancisvet@conwaycorp.net | S43: Sam's Club | T43: Silver | U43: 350 | V43: LH-N
A44: Sam's Club | B44: Silver | C44: 350 | D44: 350 | E44: LH | F44: 4.8.25 | I44: 7/17/25 GB | J44: 45912 | K44: 350 | L44: Alex Breckenridge | N44: a0b0q84.s04749.us@samsclub.com | S44: Simmons Bank | T44: Gold | U44: 500 | V44: BL
A45: Window Depot | B45: Silver | C45: 350 | D45: 350 | E45: LC-N | F45: 4.21.25 | I45: 7/17/25 GB | J45: 45936 | K45: 350 | L45: Zack Venable, Karen | N45: zack@windowdepotar.com; office.windowdepotar@gmail.com | S45: Sinco | T45: Gold | U45: 600 | V45: CP-N
A46: Staley Electric- moving pmt to spark | B46: Silver | C46: 350 | D46: 0 | E46: JG-N | F46: 7.3.25 | G46: Cancelled and moved money to SPARK! | I46: 7/17/25 GB | J46: 45869 | L46: Heather Finch, Matt Benton, Troy Lampley | N46: heather.finch@staleyelectric.com; matt.benton@staleyelectric.com; Troy.Lampley@staleyelectric.com | S46: Smith Ford | T46: Lunch | U46: 1000 | V46: BL
A47: Haynes Ace Hardware | B47: Silver | C47: 350 | D47: 350 | E47: LC-N | F47: 7.28.25 | I47: 45874 | J47: 45908 | K47: 350 | L47: Andrew Booth | N47: andrew@haynesace.com | S47: Sowell Architects | T47: Gold | U47: 600
A48: Tommy's Express | B48: Silver | C48: 350 | D48: 0 | E48: JE-N | F48: 8.4.25 | I48: 0 | K48: 0 | L48: Kason Kimbrell | N48: kasonk@advancedwashnetwork.com | S48: St. Francis Vet Clinic | T48: Silver | U48: 850 | V48: JE-N
A49: Watson Homes | B49: Silver | C49: 350 | D49: 350 | E49: JE-N | F49: 8.19.25 | G49: afternoon | I49: 8/26/25 GB | J49: 45902 | K49: 350 | L49: Lauren Watson | N49: lauren@watsonhomesinc.com | S49: State Farm Insurance, Jay Bernard | T49: Gold | U49: 500 | V49: BL
A50: StoneBridge of Conway | B50: Silver | C50: 350 | D50: 350 | J50: 8.21.25 | K50: 350 | S50: The Barking Lot | T50: Gold | U50: 600 | V50: LC-N
A51: L&P Construction | B51: Silver | C51: 350 | D51: 350 | E51: LC-N | F51: 8.27.25 | G51: Morning flight | I51: 8/29/25 GB | J51: 46009 | K51: 350 | N51: claire@homewardhomes.com | S51: Top Notch | T51: Silver | U51: 350 | V51: LC-N
A52: Cadence Bank | B52: Silver | C52: 350 | D52: 350 | E52: LH | F52: 9.2.25 | I52: 9/3/25 GB | J52: 45911 | K52: 350 | L52: Tom Nelson | N52: tom.nelson@cadencebank.com | S52: Turbare | T52: Silver | U52: 1050 | V52: BL-N
A53: HSA Engineering | B53: Silver | C53: 350 | D53: 350 | F53: 9.2.25 | I53: 9/3/25 GB | J53: 45903 | K53: 350 | L53: Trey White | N53: twhite@hsaconsultants.com | S53: UCA Outreach and Conference Services | T53: Silver | U53: 0
A54: Bank OZK | B54: Silver | C54: 350 | D54: 350 | F54: 9.3.25 | I54: 9/4/25 GB | J54: 45904 | K54: 350 | L54: Debbie Townsend | S54: Watson Homes | T54: Silver | U54: 350 | V54: JE-N
A55: BluSky | B55: Silver | C55: 350 | D55: 350 | E55: LC-N | F55: 9.4.25 | I55: 9/5/25 GB | J55: 46008 | K55: 350 | N55: Lisa.graham@goblusky.com
A56: UCA Outreach & Community Engagement | B56: Silver | C56: 350 | D56: 0 | E56: LH | F56: 9.8.25 | I56: 0 | K56: 0 | L56: Reuel Shepherd | N56: rshepherd@uca.edu
K62: =SUM(K9:K61) -> 27800
E300: BL-O
E301: BL-N
E302: BL
E303: CP-O
E304: CP-N
E305: CP
E306: JG-O
E307: JG-N
E308: JG
E309: JE-O
E310: JE-N
E311: JE
... E317: LH

Sheet Biketoberfest
A1: BIKETOBERFEST | B1: 2025 | S1: BIKETOBERFEST | T1: 2024
A2: Total Sponsorship Amount Sold | B2: =SUM(D9:D45) -> 24000 | K2: OUTSTANDING | S2: Total Sponsorship Amount Sold | T2: =SUM(U9:U28) -> 32250
A3: Budget Goal | B3: 30000 | K3: =MIN(K30-B2) -> -2500 | S3: Budget Goal | T3: 30000
A4: Remaining Balance | B4: =MIN(B2-B3) -> -6000 | K4: =K30/B2 -> 0.89583333 | S4: Remaining Balance | T4: =MIN(T2-T3) -> 2250
A5: Stretch Goal | B5: 35000 | S5: Stretch Goal | T5: 40000
A6: Remaining Balance | B6: =MIN(B2-B5) -> -11000 | S6: Remaining Balance | T6: =MIN(T2-T5) -> -7750
A8: SPONSOR NAME | B8: SPONSORSHIP | C8: COST | D8: PRICE PLEDGED | E8: SOLD BY | F8: DATE SOLD | G8: NOTES | H8: SPECIAL BILLING | I8: INVOICED | J8: DATE PAID | K8: PAID AMOUNT | L8: CONTACT | M8: PHONE | N8: EMAIL | P8: SOLD BY | Q8: PLEDGED | S8: SPONSOR NAME | T8: SPONSORSHIP | U8: PRICE PLEDGED | V8: SOLD BY
A9: Conway Regional | B9: Title | C9: 10000 | D9: 7500 | E9: BL | F9: 12.30.24 | I9: 9/17/25 GB | J9: 45924 | K9: 7500 | L9: Rebekah Fincher | N9: rfincher@conwayregional.org | P9: BL | Q9: 15000 | S9: Caldwell Toyota | T9: Presenting | U9: 5000 | V9: JG-N
A10: Caldwell Toyota | B10: Presenting | C10: 5000 | D10: 4000 | E10: JG-N | F10: 12.20.24 | I10: 9/25/25 GB | J10: 45936 | K10: 4000 | L10: Jay Caldwell | N10: jay@caldwellcares.com | P10: BL-N | S10: Conway Regional | T10: Title | U10: 7500 | V10: BL
A11: Meridian Investment Advisors | B11: Presenting | C11: 5000 | D11: 5000 | E11: LH | F11: 3.19.25 | I11: 9/17/25 GB | J11: 45917 | K11: 5000 | L11: Pat Moon | N11: pmoon@meridiania.com | P11: BL-O | S11: Cousins' Office Furnitre | T11: Taco Ride | U11: 0 | V11: LH-N
B12: Presenting | C12: 5000 | P12: CP | S12: Crafton Tull | T12: Route | U12: 2500 | V12: BL
B13: Presenting | C13: 5000 | P13: CP-N | S13: Engage Management | T13: Route | U13: 2500 | V13: BL
B14: Presenting | C14: 5000 | P14: CP-O | S14: First Security Bank | T14: Route | U14: 2500 | V14: BL
B15: Themed Ride #1 | C15: 3000 | P15: JE | S15: Home2/Hilton Garden Inn | T15: Route | U15: 1000 | V15: JE
B16: Themed Ride #1 | C16: 3000 | P16: JE-N | S16: Meridian Investment Advisors | T16: Presenting | U16: 5000 | V16: LH
B17: Themed Ride #2 | C17: 3000 | P17: JE-O | S17: Point Remove Brewing | T17: Bike, Brunch & Brews | U17: 3750 | V17: LH
B18: Themed Ride #2 | C18: 3000 | P18: JG | S18: Rogers Group | T18: Route | U18: 2500 | V18: BL
B19: Themed Ride #3 | C19: 3000 | P19: JG-N | Q19: 4000 | S19: Rogue Roundabout | T19: Kick-off Ride | U19: 0 | V19: LH
B20: Themed Ride #3 | C20: 3000 | P20: JG-O | S20: The Ride | T20: Ride Partner | U20: 0
A21: Rogers Group | B21: Route | C21: 2500 | D21: 2500 | E21: BL | F21: 1.3.25 | I21: 9/17/25 GB | J21: 45930 | K21: 2500 | L21: Mike Connelly | N21: mike.connelly@rogersgroupinc.com | P21: LC
A22: Crafton Tull | B22: Route | C22: 2500 | D22: 2500 | E22: BL | F22: 1.10.25 | H22: YES | J22: 45980 | K22: 2500 | L22: Lane Housley | N22: lane.housley@craftontull.com | P22: LC-N
A23: Engage Management | B23: Route | C23: 2500 | D23: 2500 | E23: BL | F23: 2.2.25 | I23: 9/17/25 GB | L23: Morgan Lefler | N23: morgan.lefler@engagemanagement.com | P23: LC-O
A24: Cousins' | B24: Route | C24: 2500 | D24: 0 | E24: LH | F24: 2.26.25 | G24: in-kind for hauling event materials | I24: 0 | L24: Adam Robertson, Tara Robertson | N24: adam@cousinsfurniture.com; tara@cousinsfurniture.com | P24: LH | Q24: 5000
B25: Virtual Ride | C25: 2500 | P25: LH-N
B26: Virtual Ride | C26: 2500 | P26: LH-O
P27: (blank)
P28: TOTAL | Q28: 24000
K30: =SUM(K9:K29) -> 21500
E300: BL-O
E301: BL-N
E302: BL
E303: CP-O
E304: CP-N
E305: CP
E306: JG-O
E307: JG-N
E308: JG
E309: JE-O
E310: JE-N
E311: JE
... E317: LH

Sheet Bowling for Business
A1: BOWLING FOR BUSINESS | B1: 2025 | S1: BOWLING FOR BUSINESS | T1: 2024
A2: Total Sponsorship Amount Sold | B2: =SUM(D9:D69) -> 27650 | G2: 2026: Rhea Lana's waive 2 teams | K2: OUTSTANDING | S2: Total Sponsorship Amount Sold | T2: =SUM(U9:U67) -> 30250
A3: Budget Goal | B3: 20000 | K3: =MIN(K69-B2) -> 0 | S3: Budget Goal | T3: 17500
A4: Remaining Balance | B4: =MIN(B2-B3) -> 7650 | K4: =K69/B2 -> 1 | S4: Remaining Balance | T4: =MIN(T2-T3) -> 12750
A5: Stretch Goal | B5: 34000 | S5: Stretch Goal | T5: 30000
A6: Remaining Balance | B6: =MIN(B2-B5) -> -6350 | S6: Remaining Balance | T6: =MIN(T2-T5) -> 250
A8: SPONSOR NAME | B8: SPONSORSHIP | C8: COST | D8: PRICE PLEDGED | E8: SOLD BY | F8: DATE SOLD | G8: NOTES | H8: SPECIAL BILLING | I8: INVOICED | J8: DATE PAID | K8: PAID AMOUNT | L8: CONTACT | M8: PHONE | N8: EMAIL | P8: SOLD BY | Q8: PLEDGED | S8: SPONSOR NAME | T8: SPONSORSHIP | U8: PRICE PLEDGED | V8: SOLD BY
B9: Title | C9: 5000 | P9: BL | Q9: 5500 | S9: Acxiom | T9: Lane | U9: 1000 | V9: BL-N
A10: Superior Plumbing | B10: Presenting | C10: 2500 | D10: 2500 | E10: LC | F10: 4.23.25 | J10: 6.17.25 | K10: 2500 | L10: Dustin Smith | N10: DUSTIN.SMITH@SUPERIORPLUMBINGAR.COM | P10: BL-N | Q10: 2700 | S10: Alpha Countertops | T10: Lane | U10: 600 | V10: LC-N
B11: Presenting | C11: 2500 | P11: BL-O | S11: American Safeguard Insurance | T11: Team | U11: 0 | V11: LH
A12: Rock City Outfitters | B12: T-Shirt | C12: 1500 | D12: 1000 | E12: LC | F12: 2.24.25 | J12: 6.30.25 | K12: 1000 | L12: Ryan Ritchie | N12: ryan@rockcityoutfitters.com | P12: CP | Q12: 1800 | S12: Andy's Frozen Custard | T12: Lane | U12: 600 | V12: LH-N
A13: Turbare | B13: Meal | C13: 1000 | D13: 1350 | E13: BL-N | F13: 1.3.25 | G13: Meal sponsor + one additional team, 2 teams of 5 | H13: YES | J13: 7.7.25 | K13: 1350 | L13: Laura Martin, Andria White | N13: ceo@turbare.org; awhite@turbare.org | P13: CP-N | Q13: 600 | S13: Arkansas Roofing Kompany | T13: Presenting | U13: 2500 | V13: LC
A14: Insight | B14: Meal | C14: 1000 | D14: 1200 | E14: CP | F14: 2.19.25 | G14: Include lane signage and two teams of five | H14: YES | J14: 4.8.25 | K14: 1200 | L14: Steven Tyler, Jenny Vallas | N14: steven.tyler@insight.com; jenny.vallas@insight.com | P14: CP-O | S14: Attorney's Title Group | T14: Team | U14: 350 | V14: LC-N
B15: Meal | C15: 1000 | P15: JE | Q15: 2250 | S15: B&A Property Maintenance | T15: Team | U15: 300
A16: Car-Son Construction | B16: Beverage | C16: 1000 | D16: 1000 | E16: BL-N | F16: 2.28.25 | H16: YES | J16: 6.9.25 | K16: 1000 | L16: Brad Fason, Brian Fason | N16: bfason@car-son.com; bradfason@car-son.com | P16: JE-N | Q16: 1050 | S16: Bank OZK | T16: Team | U16: 450
A17: Fair and Company | B17: Beverage | C17: 1000 | D17: 1000 | E17: LC | F17: 5.7.25 | J17: 6.20.25 | K17: 1000 | L17: Nick Schroeder | N17: nschroeder@fairandcompany.com | P17: JE-O | S17: Bledsoe Chiropractic | T17: Lane | U17: 600 | V17: LC
A18: Conway Family Dental | B18: Photo Booth | C18: 1000 | D18: 1000 | E18: BL | F18: 5.30.25 | J18: 6.2.25 | K18: 1000 | P18: JG | S18: Chambers Bank | T18: Lane | U18: 600 | V18: LC-N
A19: Green Bay Packaging | B19: Lane | C19: 600 | D19: 500 | E19: BL | F19: 12.3.24 | H19: YES | J19: 45903 | K19: 500 | L19: Brad Harville, Christy Prater | N19: bharville@gbp.com, cprater@gbp.com | P19: JG-N | Q19: 0 | S19: Chris Crain Enterprises | T19: Team | U19: 0 | V19: BL-N
A20: Farris Agency | B20: Lane | C20: 600 | D20: 600 | E20: JE | F20: 12.4.24 | J20: 5.16.25 | K20: 600 | L20: Alan White, Travis Mulhearn, Christina Horn | N20: alan@farrisagency.com travis@farrisagency.com christina@farrisagency.com | P20: JG-O | S20: City of Conway | T20: Team | U20: 0
A21: Hampton Inn & Suites | B21: Lane | C21: 600 | D21: 600 | E21: JE | F21: 12.19.24 | J21: 6.23.25 | K21: 600 | L21: Allan Gammill | N21: allan.gammill@hilton.com | P21: LC | Q21: 7350 | S21: Conway Corp. | T21: Team | U21: 300
A22: Conway Regional | B22: Lane | C22: 600 | D22: 500 | E22: BL | F22: 12.30.24 | J22: 5.22.25 | K22: 500 | L22: Rebekah Fincher | N22: rfincher@conwayregional.org | P22: LC-N | Q22: 3950 | S22: Conway Family Dental | T22: Photo Booth | U22: 1000 | V22: BL-N
A23: Rogers Group | B23: Lane | C23: 600 | D23: 500 | E23: BL | F23: 1.3.25 | J23: 6.16.25 | K23: 500 | L23: Mike Connelly | N23: mike.connelly@rogersgroupinc.com | P23: LC-O | S23: Conway Fire Department | T23: Team | U23: 0
A24: Simmons Bank | B24: Lane | C24: 600 | D24: 500 | E24: BL | F24: 1.2.25 | J24: 7.14.25 | K24: 500 | L24: Justin McCarty | N24: justin.mccarty@simmonsbank.com | P24: LH | Q24: 0 | S24: Conway Regional | T24: Lane | U24: 500 | V24: BL
A25: Acxiom | B25: Lane | C25: 600 | D25: 1000 | E25: BL | F25: 1.8.25 | J25: 6.12.25 | K25: 1000 | L25: Crystal Floyd, Alison Cowles | N25: Crystal.Floyd@acxiom.com; Alison.Cowles@acxiom.com | P25: LH-N | Q25: 2000 | S25: Crain Team | T25: Team | U25: 0 | V25: BL-N
A26: WACO Title | B26: Lane | C26: 600 | D26: 600 | E26: LC-N | F26: 2.7.25 | J26: 5.19.25 | K26: 600 | L26: Ryke Dismuke, Brooklyn Burnett | N26: idismuke@wacotitle.com: bburnett1@wacotitle.com | P26: LH-O | S26: Dave Creek Media | T26: Team | U26: 300 | V26: JG
A27: Dyermark | B27: Lane | C27: 600 | D27: 600 | E27: LC | F27: 2.11.25 | H27: YES | J27: 6.17.25 | K27: 175 | L27: Ali Dyer | N27: ali@dyermark.com | P27: (blank) | Q27: 450 | S27: Diamond State Restoration | T27: Lane | U27: 600 | V27: LC-N
J28: 4.25.25 | K28: 425 | P28: TOTAL | Q28: 27650 | S28: DKM Construction | T28: Lane | U28: 600 | V28: CP-N
A29: Sowell Ferris Architects | B29: Lane | C29: 600 | D29: 600 | E29: LH-N | F29: 2.18.25 | J29: 5.27.25 | K29: 600 | L29: Cody Ferris, Emily Ferris | N29: cody@sowellarchitects.com; emily@sowellarchitects.com | S29: Douglas Companies | T29: Team | U29: 0
A30: Sinco | B30: Lane | C30: 600 | D30: 600 | E30: CP | F30: 2.21.25 | H30: YES | J30: 6.9.25, 8/19/25 | K30: 600 | L30: Parker Spradlin, Grey Williams, Rhonda Wilson | N30: Pspradlin@sincoinc.com; gwilliams@sincoinc.com; rwilson@sincoinc.com | S30: Dyermark | T30: Lane | U30: 600 | V30: LC-N
A31: Entergy | B31: Lane | C31: 600 | D31: 600 | E31: CP-N | F31: 2.26.25 | G31: Region Construction team will pay for this, so invoice James Warren | J31: 6.10.25 | K31: 600 | L31: Zack Hale, James Warren | N31: zhale@entergy.com; jwarren@entergy.com | S31: Edward Jones, Stacey Alston | T31: Team | U31: 350 | V31: LC
A32: Chambers Bank | B32: Lane | C32: 600 | D32: 600 | E32: LC | F32: 2.27.25 | J32: 5.12.25 | K32: 600 | L32: Ethan Barnes | N32: ebarnes@chambers.bank | S32: Engage Management | T32: Team | U32: 350 | V32: BL-N
A33: State Farm Jay Bernard | B33: Lane | C33: 600 | D33: 500 | E33: BL | F33: 2.28.25 | H33: YES | J33: 3.19.25 | K33: 500 | L33: Jay Bernard | N33: jay.bernard.l8if@statefarm.com | S33: Fair & Company | T33: Drink | U33: 1000 | V33: LC-N
A34: Bledsoe Chiropractic | B34: Lane | C34: 600 | D34: 600 | E34: LC | F34: 3.19.25 | H34: YES | J34: 6.16.25 | K34: 600 | L34: Amanda Bledsoe, Sarah Lockard | N34: dramandabledsoe@gmail.com; sarah@bledsoechiropractic.com | S34: Farris Agency | T34: Lane | U34: 600 | V34: JE-N
A35: Pro-Land Title | B35: Lane | C35: 600 | D35: 600 | E35: LC-N | F35: 4.11.25 | J35: 5.30.25 | K35: 600 | L35: Brooklyn Cardin | N35: bcardin@prolandtitle.com | S35: First Arkansas Bank & Trust | T35: Team | U35: 0 | V35: LH
A36: Window Depot | B36: Lane | C36: 600 | D36: 600 | E36: LC-N | F36: 4.21.25 | J36: 5.21.25 | K36: 600 | L36: Zack Venable, Karen | N36: zack@windowdepotar.com; office.windowdepotar@gmail.com | S36: First Community Bank | T36: Lane | U36: 500 | V36: BL
A37: Westport Dental | B37: Lane | C37: 600 | D37: 1200 | E37: LC-N | F37: 5.9.25 | G37: Noon/lunch flight, t-shirt sizes: 1 - XL, 4 - L, 7 - M, Leo said we can charge for the additional shirts. | J37: 6.2.25 | K37: 1200 | L37: Cyndi Winter | N37: cwinter.westport@conwaycorp.net | S37: First Security Bank | T37: Team | U37: 300 | V37: BL-O
A38: Nabco | B38: Lane | C38: 600 | D38: 600 | E38: LC-N | F38: 5.29.25 | J38: 6.25.25 | K38: 600 | L38: Dusty Brand | N38: cbrand@nabco.com | S38: Green Bay Packaging | T38: Lane | U38: 500 | V38: BL
A39: Stonebridge | B39: Team | C39: 350 | D39: 350 | E39: JE-N | F39: 3.10.25 | J39: 6.9.25 | K39: 350 | L39: Shelley Culwell | N39: shelley.culwell@sbseniorliving.com | S39: Hampton Inn and Suites | T39: Lane | U39: 600 | V39: JE-N
A40: Chris Crain Enterprises | B40: Team | C40: 350 | D40: 0 | E40: BL | F40: 11.20.24 | G40: Confirm with NK/BB which Chris Crain Enterprises company/companies will be featured on event. | I40: 0 | L40: Brett Berry, Nita Kat Freeman | N40: brettberry@chriscraingroup.com; nitafreeman@chriscraingroup.com | S40: Honda World | T40: Team | U40: 0
A41: Rhea Lana's | B41: Team | C41: 350 | D41: 0 | E41: LH-N | F41: 45597 | G41: 2 teams | I41: 0 | L41: Rhea Lana Riner, Hannah Johnson, Abbie Kent | N41: rhealana@rhealana.com; hannahjohnson@rhealana.com; abbie@rhealana.com | S41: Insight | T41: Lane | U41: 1200 | V41: CP-N
A42: First Arkansas Bank & Trust | B42: Team | C42: 350 | D42: 0 | E42: LH | F42: 12.9.24 | I42: 0 | L42: John Simmons, Roger Sundermeier, Mark Wilson, Jessica Pint | N42: jsimmons@fabandt.bank; rsundermeier@fabandt.bank; mwilson@fabandt.bank; jpint@fabandt.bank | S42: Integrity Insurance | T42: Lunch & Snack | U42: 1000 | V42: LC-N
A43: American Safeguard Insurance | B43: Team | C43: 350 | D43: 1050 | E43: LH-N | F43: 12.23.24 | G43: One team per flight, and please give each player a shirt | H43: YES | J43: 4.9.25 | K43: 1050 | L43: Jeremy Davis, Jason Smith, Brittney Gwatney | N43: jdavis@asiagents.com; jsmith@asiagents.com; bgwatney@asiagents.com | S43: Market Place Grill | T43: Team | U43: 350 | V43: JE-N
A44: Crain Team | B44: Team | C44: 350 | D44: 0 | E44: BL | F44: 1.7.25 | G44: 2 teams - one for each dealership | I44: 0 | L44: Drew Dees, Christian Crain, Cameron Burdess, Justin Kervin | M44: Cameron: 501-339-1492 Justin: 501-687-3945 | N44: ddees@ltdconnect.com; christiancrain@crainteam.net; cameronburdess@crainteam.net; justinkervin@crainteam.net | S44: Megan Stewart (Pipeline) | T44: Team | U44: 350 | V44: LC-N
A45: Conductor | B45: Team | C45: 350 | D45: 0 | E45: LH-N | F45: 1.13.25 | I45: 0 | L45: Grace Rains | N45: grace@arconductor.org | S45: Melvin's Painting | T45: Team | U45: 300
A46: Engage Management | B46: Team | C46: 350 | D46: 350 | E46: BL | F46: 2.2.25 | J46: 5.27.25 | K46: 350 | L46: Morgan Lefler | N46: morgan.lefler@engagemanagement.com | S46: Nabco | T46: Team | U46: 450 | V46: LC-N
A47: RE/MAX Elite: The Emily Walter Team | B47: Team | C47: 350 | D47: 350 | E47: LC | F47: 2.7.25 | J47: 6.11.25 | K47: 350 | L47: Emily Walter | N47: emilywalterrealtor@gmail.com | S47: NRG Insurance | T47: Lane | U47: 600 | V47: LC-N
A48: Ott Insurance | B48: Team | C48: 350 | D48: 350 | E48: LC | F48: 2.7.25 | J48: 5.30.25 | K48: 350 | L48: Michelle Mallett | N48: michellemallett@ottinsurance.com | S48: Ott Insurance | T48: Lane | U48: 500 | V48: LC
A49: St. Francis Veterinary Clinic | B49: Team | C49: 350 | D49: 700 | E49: JE | F49: 2.24.25 | J49: 6.16.25 | K49: 700 | L49: Sharon Stone, Rachel Mears | N49: stfrancisvet@conwaycorp.net | S49: Partners Bank | T49: Team | U49: 350 | V49: LC-N
A50: First Security Bank | B50: Team | C50: 350 | D50: 300 | E50: BL | F50: 3.19.25 | J50: 5.27.25 | K50: 300 | L50: Stefanie Vann | N50: stefanie.vann@fsbank.com | S50: PCSI | T50: Team | U50: 450 | V50: LC-N
A51: NRG Insurance | B51: Team | C51: 350 | D51: 350 | E51: LC | F51: 4.30.25 | J51: 5.8.25 | K51: 350 | L51: Nick Rougeau | N51: nick@nrgins.com | S51: RE/MAX Elite: The Emily Walter Team | T51: Team | U51: 350 | V51: LC-N
A52: First Star Exteriors | B52: Team | C52: 350 | D52: 350 | E52: JE-N | F52: 5.14.25 | J52: 6.17.25 | K52: 350 | L52: Deric Herring | N52: dherring@firststarext.com | S52: Rock City Outfitters | T52: T-Shirt | U52: 1000 | V52: LC
A53: Marketplace Grill | B53: Team | C53: 350 | D53: 350 | E53: JE | F53: 5.14.25 | J53: 6.9.25 | K53: 350 | L53: Sydney Camp | N53: jbasey@marketplacegrill.com; sydney.camp@marketplacegrill.com | S53: Rogers Group | T53: Lane | U53: 500 | V53: BL
B54: Team | C54: 350 | S54: Simmons Bank | T54: Lane | U54: 500 | V54: BL
A55: Honda World | B55: Team | C55: 350 | D55: 0 | E55: JE | F55: 5.20.25 | G55: Morning flight | I55: 0 | L55: Sydney Lee | N55: slee@winrockautomotive.com | S55: Sinco | T55: Lane | U55: 600 | V55: CP-N
A56: Century 21 Parker & Scroggins | B56: Team | C56: 350 | D56: 350 | E56: JE-N | F56: 5.20.25 | G56: 12:00 - 2:30 flight | J56: 6.20.25 | K56: 350 | L56: Comeatrieze Ester | N56: Comeatrieze.ester@gmail.com | S56: St. Francis Vet Clinic | T56: Team | U56: 700 | V56: JE-N
A57: Arkansas Federal Credit Union | B57: Team | C57: 350 | D57: 350 | E57: LH-N | F57: 5.29.25 | J57: 6.9.25 | K57: 350 | L57: Denise Goforth | N57: dgoforth@AFCU.org | S57: State Farm Insurance, Jay Bernard | T57: Lane | U57: 500 | V57: BL
A58: Baptist Health - Conway | B58: Team | C58: 350 | D58: 0 | E58: JG-N | F58: 6.4.25 | G58: Comp 2 teams per Jamie | I58: 0 | S58: Summit Utilities | T58: Team | U58: 300
A59: Hardwyre | B59: Team | C59: 350 | D59: 350 | F59: 6.4.25 | J59: 7.16.25 | K59: 350 | S59: Superior Plumbing & Rooter | T59: Presenting | U59: 2500 | V59: LC-N
A60: Verizon | B60: Team | C60: 350 | D60: 350 | E60: LC-N | F60: 6.9.25 | J60: 6.25.25 | K60: 350 | L60: Mark Jones | N60: mark.jones@verizonwireless.com | S60: TriTechne | T60: Team | U60: 300
A61: Little Creek Behavioral | B61: Team | C61: 350 | D61: 0 | E61: JE-N | F61: 6.9.25 | G61: 2:30 - 4:30 shift | L61: Nedra Allen-Jones | N61: Nedra.allen-jones@littlecreekbehavioral.com | S61: Tucker Creek Vet | T61: Team | U61: 700 | V61: JE-N
A62: Bank OZK | B62: Team | C62: 350 | D62: 350 | E62: BL | F62: 6.9.25 | G62: 2:30 shift | J62: 7.25.25 | K62: 350 | L62: Sarah Shaw | N62: sarah.shaw@ozk.com | S62: Turbare | T62: Lunch & Snack | U62: 1000 | V62: BL
A63: Ensono | B63: Team | C63: 350 | D63: 350 | E63: BL-N | F63: 6.9.25 | G63: 12:00 - 2:00 shift | J63: 6.17.25 | K63: 350 | L63: Michelle McKown | N63: michelle.mckown@ensono.com | S63: UCA Outreach and Conference Services | T63: Team | U63: 0
A64: B&A Property Maintenance | B64: Team | C64: 350 | D64: 100 | J64: 6.13.25 | K64: 100 | S64: Weaver Bailey | T64: Team | U64: 300
A65: City of Conway | B65: Team | C65: 350 | D65: 0 | S65: Window Depot | T65: Team | U65: 350 | V65: LC-N
A66: Beard Chiropractic | B66: Team | C66: 350 | D66: 0
A67: Crosscreek | B67: Team | C67: 350 | D67: 0
A68: Piraino Security | B68: Team | C68: 350 | D68: 0
K69: =SUM(K9:K68) -> 27650
E300: BL-O
E301: BL-N
E302: BL
E303: CP-O
E304: CP-N
E305: CP
E306: JG-O
E307: JG-N
E308: JG
E309: JE-O
E310: JE-N
E311: JE
... E317: LH

Sheet Business Expo & Taste of Conway
A1: BUSINESS EXPO & TASTE OF CONWAY | B1: 2025 | S1: BUSINESS EXPO & TASTE OF CONWAY | T1: 2024
A2: Total Sponsorship Amount Sold | B2: =SUM(D9:D146) -> 99570 | K2: OUTSTANDING | S2: Total Sponsorship Amount Sold | T2: =SUM(U9:U184) -> 117965
A3: Budget Goal | B3: 85000 | K3: =MIN(K146-B2) -> -6395 | S3: Budget Goal | T3: 75000
A4: Remaining Balance | B4: =MIN(B2-B3) -> 14570 | K4: =K146/B2 -> 0.93577383 | S4: Remaining Balance | T4: =MIN(T2-T3) -> 42965
A5: Stretch Goal | B5: 120000 | S5: Stretch Goal | T5: 105000
A6: Remaining Balance | B6: =MIN(B2-B5) -> -20430 | S6: Remaining Balance | T6: =MIN(T2-T5) -> 12965
A8: SPONSOR NAME | B8: SPONSORSHIP | C8: COST | D8: PRICE PLEDGED | E8: SOLD BY | F8: DATE SOLD | G8: NOTES | H8: SPECIAL BILLING | I8: INVOICED | J8: DATE PAID | K8: PAID AMOUNT | L8: CONTACT | M8: PHONE | N8: EMAIL | P8: SOLD BY | Q8: PLEDGED | S8: SPONSOR NAME | T8: SPONSORSHIP | U8: PRICE PLEDGED | V8: SOLD BY
B9: Title | C9: 7500 | P9: BL | Q9: 33620 | S9: 7 Brew | T9: Booth Space | U9: 500
A10: Simmons Bank | B10: Presenting | C10: 5000 | D10: 5000 | E10: BL | F10: 1.2.25 | I10: 7/31/25 GB | J10: 45898 | K10: 5000 | L10: Justin McCarty | N10: justin.mccarty@simmonsbank.com | P10: BL-N | Q10: 500 | S10: 7 Brew | T10: TOC Food Vendor | U10: 0
A11: Cousins' Office Furniture | B11: Presenting | C11: 5000 | D11: 5000 | E11: LH | F11: 2.26.25 | I11: 7/31/25 GB | J11: 45939 | K11: 5000 | L11: Adam Robertson, Tara Robertson | N11: adam@cousinsfurniture.com; tara@cousinsfurniture.com | P11: BL-O | S11: Acxiom | T11: Silver | U11: 1000 | V11: BL
A12: Arkansas Game & Fish Commission | B12: Platinum | C12: 3500 | D12: 3000 | E12: JG | F12: 1.7.25 | I12: 7/31/25 GB | L12: Spencer Griffith | N12: spencer.griffith@agfc.ar.gov | P12: CP | Q12: 1000 | S12: Adams Pest Control | T12: Booth Space | U12: 500 | V12: JE-N
A13: Conductor | B13: Platinum | C13: 3500 | D13: 0 | E13: LH | F13: 1.13.25 | I13: 0 | L13: Grace Rains | N13: grace@arconductor.org | P13: CP-N | Q13: 1250 | S13: Advance Ticket Sales | T13: Tickets | U13: 2460
A14: Dave Creek Media | B14: Platinum | C14: 3500 | D14: 3500 | E14: JG-N | F14: 2.28.25 | G14: Sponsor deliverables per Jamie: 1) We would host a lunch here for Expo participants well in advance of the event so you could share similar content in-person. 2) Break-out session at the Expo. 3) Video commercial that runs during Expo 4) Included in Expo promotion and Social Media. | I14: 7/31/25 GB | J14: 46003 | K14: 3500 | L14: Jakob Michaelis | N14: jakob@davecreekmedia.com | P14: CP-O | S14: All Clean USA | T14: Premier Vendor | U14: 750 | V14: JE-N
A15: CARTI | B15: Platinum | C15: 3500 | D15: 2500 | E15: LC-N | F15: 9.19.25 | G15: Will also have a breakout session. | I15: 9/23/25 GB | J15: 45953 | K15: 2500 | L15: Carroll Jo Malloy | N15: CarrollJo.Malloy@CARTI.com | P15: JE | Q15: 3530 | S15: Alpha Countertops & Tile | T15: Booth Space | U15: 530 | V15: JE-N
A16: DKM Construction | B16: Gold | C16: 2000 | D16: 1000 | E16: CP | F16: 2.17.25 | H16: YES | J16: 45985 | K16: 1000 | L16: Kim Morehart, Daniel Morehart | N16: kimm.dkm@gmail.com; danielm.dkm@gmail.com | P16: JE-N | Q16: 8920 | S16: Ambassadors | T16: 1 Taste, 1 Breakfast OR Lunch, 1 session ticket | U16: 0
A17: Snap-on | B17: Gold | C17: 2000 | D17: 2000 | E17: BL | F17: 3.10.25 | H17: YES | J17: 6.25.25 | K17: 2000 | L17: Scott Champlin, Lynne Sponer | N17: scott.l.champlin@snapon.com; lynne.sponer@snapon.com | P17: JE-O | S17: Andy's Frozen Custard | T17: Booth Space | U17: 500 | V17: LH-N
A18: Pafford | B18: Gold | C18: 2000 | D18: 2500 | E18: BL | F18: 7.1.25 | I18: 7/31/25 GB | J18: 45895 | K18: 2500 | L18: Dylan Kelsey | P18: JG | Q18: 5600 | S18: Andy's Frozen Custard | T18: TOC Food Vendor | U18: 0 | V18: LH
A19: Staley Electric | B19: Gold | C19: 2000 | D19: 2000 | E19: JG-N | F19: 7.3.25 | I19: 7/31/25 GB | J19: 45873 | K19: 2000 | L19: Heather Finch, Matt Benton, Troy Lampley | N19: heather.finch@staleyelectric.com; matt.benton@staleyelectric.com; Troy.Lampley@staleyelectric.com | P19: JG-N | Q19: 6500 | S19: Aramark | T19: TOC Food Vendor | U19: 0 | V19: LH
A20: TGI Friday's Catering | B20: Silver | C20: 1000 | D20: 1000 | E20: JG-N | F20: 10.1.25 | I20: 10/2/25 GB | J20: 45989 | K20: 1000 | L20: Jeremy Gardner | N20: TGIFboss@gmail.com | P20: JG-O | S20: Arisa Health | T20: Premier Vendor | U20: 750 | V20: JE
A21: Arisa Health | B21: Silver | C21: 1000 | D21: 1000 | E21: JE-N | F21: 5.21.25 | I21: 7/31/25 GB | J21: 45950 | K21: 1000 | L21: Teresa Wilson, Brad Hyde | N21: Teresa.wilson@arisahealth.org; brad.hyde@arisahealth.org | P21: LC | Q21: 13105 | S21: Arkansas Division of Services for the Blind | T21: Booth Space | U21: 520 | V21: JE-N
A22: Green Bay Packaging | B22: Silver | C22: 1000 | D22: 1400 | E22: BL | F22: 12.3.24 | H22: YES | J22: 9/3/2025, 11/19/25 | K22: =1251.25+148.75 -> 1400 | L22: Brad Harville, Christy Prater | N22: bharville@gbp.com, cprater@gbp.com | P22: LC-N | Q22: 7000 | S22: Arkansas Game & Fish | T22: Platinum | U22: 3500 | V22: JG
A23: Conway Regional | B23: Silver | C23: 1000 | D23: 1000 | E23: BL | F23: 12.30.24 | I23: 7/31/25 GB | J23: 45924 | K23: 1000 | L23: Rebekah Fincher | N23: rfincher@conwayregional.org | P23: LC-O | S23: Arkansas Secretary of State | T23: Booth Space | U23: 515
A24: Acxiom | B24: Silver | C24: 1000 | D24: 1000 | E24: BL | F24: 1.8.25 | I24: 7/31/25 GB | J24: 45902 | K24: 1000 | L24: Crystal Floyd, Alison Cowles | N24: Crystal.Floyd@acxiom.com; Alison.Cowles@acxiom.com | P24: LH | Q24: 7175 | S24: Arkansas Spine and Pain | T24: Premier Vendor | U24: 750 | V24: JE-N
A25: Crafton Tull | B25: Silver | C25: 1000 | D25: 1000 | E25: BL | F25: 1.10.25 | G25: Wants booth next to Rogers Group | H25: YES | J25: 45980 | K25: 1000 | L25: Lane Housley | N25: lane.housley@craftontull.com | P25: LH-N | Q25: 500 | S25: ARORA: Arkansas Regional Organ Recovery Agency | T25: Booth Space | U25: 545
A26: Smith Ford | B26: Silver | C26: 1000 | D26: 1000 | E26: BL | F26: 2.1.25 | I26: 7/31/25 GB | J26: 45967 | K26: 1000 | L26: Cate McConnell | N26: cate.mcconnell@smithford.com | P26: LH-O | S26: Arvest | T26: Booth Space | U26: 500 | V26: BL
A27: RE/MAX Elite: Karen Ferguson | B27: Silver | C27: 1000 | D27: 1000 | E27: LC | F27: 2.4.25 | I27: 7/31/25 GB | J27: 45895 | K27: 1000 | L27: Karen Ferguson | N27: karenferguson501@gmail.com | P27: (blank) | Q27: 10870 | S27: ASAP Personal Services | T27: Booth Space | U27: 570 | V27: JE-N
A28: First Security Bank | B28: Silver | C28: 1000 | D28: 1090 | E28: BL | F28: 3.19.25 | I28: 7/31/25 GB | J28: 45960 | K28: 1090 | L28: Stefanie Vann | N28: stefanie.vann@fsbank.com | P28: MM | Q28: 0 | S28: Attorney's Title Group | T28: Booth Space | U28: 530 | V28: LC-N
A29: Klaasmeyer | B29: Silver | C29: 1000 | D29: 1000 | E29: BL | F29: 4.10.25 | I29: 7/31/25 GB | L29: Jessica Press | N29: jessica@klaasmeyer.com | P29: TOTAL | Q29: 99570 | S29: Baptist Health Conway | T29: Title | U29: 7500 | V29: JG
A30: Attorney's Title Group | B30: Silver | C30: 1000 | D30: 1000 | E30: LC-N | F30: 7.8.25 | I30: 7/31/25 GB | J30: 45873 | K30: 1000 | L30: Whitley Compton-Hobbs | N30: wcompton-hobbs@TheWilsonLawFirm.com | S30: Baptist Health Urgent Care | T30: Premier Vendor | U30: 750 | V30: LH-N
A31: Southern Tee's | B31: Silver | C31: 1000 | D31: 1000 | E31: LC-N | F31: 7.8.25 | I31: 7/31/25 GB | J31: 45869 | K31: 1000 | L31: Sean Barber | N31: sotees@hotmail.com | S31: Bledsoe Chiropractic | T31: Premier Vendor | U31: 850 | V31: LC
A32: Ortho Arkansas | B32: Silver | C32: 1000 | D32: 1000 | E32: LC | F32: 7.8.25 | I32: 7/31/25 GB | J32: 45895 | K32: 1000 | L32: Traci Byrd | N32: Traci.Byrd@orthoarkansas.com | S32: Blue Barn Bakery | T32: TOC Food Vendor | U32: 0
A33: Arkansas Spine and Pain | B33: Silver | C33: 1000 | D33: 1000 | E33: JE-N | F33: 8.19.25 | I33: 8/26/25 GB | J33: 45951 | K33: 1000 | L33: Bradley Barber | N33: bradley@arkansasspineandpain.com | S33: Boston Mountain Rural Health | T33: Booth Space | U33: 500 | V33: JE-N
A34: The Max | B34: Silver | C34: 1000 | D34: 1000 | F34: 9.20.25 | G34: Wants booth 67. | J34: 45919 | K34: 1000 | L34: Pete Tanguay | N34: pete@rockpondpros.com | S34: Brick and Forge | T34: TOC Food Vendor | U34: 0
A35: Solid Rock | B35: Silver | C35: 1000 | D35: 0 | G35: In-kind | I35: 0 | S35: Bulgogi | T35: TOC Food Vendor | U35: 0
A36: Chris Crain Enterprises | B36: Taste of Conway | C36: 3500 | D36: 2000 | E36: BL | F36: 11.20.24 | G36: Confirm with NK/BB which Chris Crain Enterprises company/companies will be featured on event. | I36: 7/31/25 GB | J36: 45940 | K36: 2000 | L36: Brett Berry, Nita Kat Freeman | N36: brettberry@chriscraingroup.com; nitafreeman@chriscraingroup.com | S36: Business Ticket Purchases | T36: Tickets | U36: 725
A37: Molex | B37: Taste of Conway | C37: 3500 | D37: 3500 | E37: BL | F37: 3.28.25 | I37: 7/31/25 GB | J37: 45922 | K37: 3500 | L37: Cory Ensley | N37: cory.ensley@molex.com | S37: CARTI | T37: Gold | U37: 2000 | V37: LC
A38: Harvest Cannabis | B38: Networking Game | C38: 2500 | D38: 2500 | E38: LC | F38: 4.14.25 | G38: If they do not pay by September 1 OR confirm payment arrangements they will be removed as a sponsor for 2025. | I38: 7/31/25 GB | J38: 45880 | K38: 2500 | L38: Robbin | N38: robbin@harvestcannabisarkansas.com | S38: Central Baptist College | T38: Booth Space | U38: 670 | V38: LH
A39: Rogers Group | B39: Meal | C39: 2500 | D39: 2000 | E39: BL | F39: 1.3.25 | I39: 7/31/25 GB | J39: 45883 | K39: 2000 | L39: Mike Connelly | N39: mike.connelly@rogersgroupinc.com | S39: Century 21 Parker and Scroggins | T39: Booth Space | U39: 500 | V39: JE-N
A40: GARVER | B40: Meal | C40: 2500 | D40: 1350 | E40: JG | F40: 2.18.25 | I40: 7/31/25 GB | J40: 45891 | K40: 1350 | L40: Dustin Tackett | N40: DLTackett@GarverUSA.com | S40: Certapro | T40: Booth Space | U40: 565 | V40: LC-N
A41: Lane Housley Trucking | B41: Meal | C41: 2500 | D41: 2500 | E41: BL | F41: 2.23.25 | G41: Place booth next to Crafton Tull and Rogers Group | I41: 7/31/25 GB | J41: 45939 | K41: 2500 | L41: Lane Housley | N41: lane.housley@craftontull.com | S41: Chairman's Circle | T41: 1 Taste, 1 Breakfast OR Lunch, 1 session ticket | U41: 0
A42: US Bank | B42: Meal | C42: 2500 | D42: 2000 | E42: JE-N | F42: 9.20.25 | I42: 9/22/25 GB | J42: 45922 | K42: 2000 | L42: Ciara Jackson, Garrett Cubello, Rebecca McRoberts | N42: ciara.browning@usbank.com; Garrett.Curbello@usbank.com; rebecca.mcroberts@usbank.com | S42: Chambers Bank | T42: Booth Space | U42: 580 | V42: LC
B43: Media | C43: 2500 | S43: Chicken Salad Chick | T43: TOC Food Vendor | U43: 0
A44: Crain Team | B44: Networking Lounge Sponsor | C44: 3500 | D44: 3500 | E44: BL | F44: 1.7.25 | G44: Visit with Drew to determine which dealership(s) will be incorporated and how to handle billing. + 2 Cars/booth, if desired. | I44: 7/31/25 GB | J44: 45981 | K44: 3500 | L44: Drew Dees, Christian Crain, Cameron Burdess, Justin Kervin | M44: Cameron: 501-339-1492 Justin: 501-687-3945 | N44: ddees@ltdconnect.com; christiancrain@crainteam.net; cameronburdess@crainteam.net; justinkervin@crainteam.net | S44: Chris Crain Enterprises | T44: Taste of Conway | U44: 2000 | V44: BL
A45: Hampton Inn & Suites | B45: Premier Vendor | C45: 750 | D45: 750 | E45: JE | F45: 12.19.24 | I45: 7/31/25 GB | J45: 45951 | K45: 750 | L45: Allan Gammill | N45: allan.gammill@hilton.com | S45: City of Conway | T45: 1 Taste, 1 Breakfast OR Lunch, 1 session ticket | U45: 0
A46: Direct Auto Insurance | B46: Premier Vendor | C46: 750 | D46: 750 | E46: JE-N | F46: 1.7.24 | I46: 7/31/25 GB | J46: 45971 | K46: 750 | L46: Brandon Pitcock | N46: Brandon.pitcock@directauto.com | S46: Conductor | T46: Platinum | U46: 0 | V46: LH
A47: Leaf Filter | B47: Premier Vendor | C47: 750 | D47: 750 | E47: LC | F47: 2.7.25 | I47: 7/31/25 GB | J47: 45911 | K47: 750 | L47: Aaron Threats | N47: AThreats@leaffilter.com | S47: Conway Financial | T47: Booth Space | U47: 500
A48: WACO Title | B48: Premier Vendor | C48: 750 | D48: Transfer | E48: LC-N | F48: 2.7.25 | I48: 7/31/25 GB | J48: 45873 | K48: 750 | L48: Ryke Dismuke, Brooklyn Burnett | N48: idismuke@wacotitle.com: bburnett1@wacotitle.com | S48: Conway Property Group | T48: Booth Space | U48: 530 | V48: JE-N
A49: The Pest Detective | B49: Premier Vendor | C49: 750 | D49: 750 | E49: LC-N | F49: 2.12.25 | I49: 7/31/25 GB | J49: 45925 | K49: 750 | L49: Westly Sullins | N49: westhepestdetective@gmail.com | S49: Conway Regional | T49: Silver | U49: 1000 | V49: BL
A50: Insight | B50: Premier Vendor | C50: 750 | D50: 0 | E50: CP-N | F50: 2.19.25 | G50: Plus 4 bkf and lunch tickets, 10 TOC tickets | I50: 0 | L50: Steven Tyler, Jenny Vallas | N50: steven.tyler@insight.com; jenny.vallas@insight.com | S50: Conway Wealth Management | T50: Premier Vendor | U50: 500 | V50: BL
B51: Premier Vendor | C51: 750 | S51: Cousins' Office Furniture | T51: Presenting | U51: 5000 | V51: LH
A52: First community Bank | B52: Premier Vendor | C52: 750 | D52: 600 | E52: BL | F52: 3.13.25 | I52: 7/31/25 GB | J52: 45877 | K52: 600 | L52: Lori Melton, Grant Gordy | N52: Lori.Melton@firstcommunity.net; Grant.Gordy@firstcommunity.net | S52: Cracker Barrell | T52: TOC Food Vendor | U52: 0
A53: Bledsoe Chiropractic | B53: Premier Vendor | C53: 750 | D53: 750 | E53: LC | F53: 3.19.25 | H53: YES | I53: 0 | J53: 6.16.25 8/20/25 | K53: =217+533 -> 750 | L53: Amanda Bledsoe, Sarah Lockard | N53: dramandabledsoe@gmail.com; sarah@bledsoechiropractic.com | S53: Crafton Tull | T53: Silver | U53: 1000 | V53: BL
A54: UCA Public Appearances | B54: Premier Vendor | C54: 750 | D54: 750 | E54: JG | F54: 4.3.25 | I54: 7/31/25 GB | J54: 45953 | K54: 750 | L54: Amanda Horton, Wendy Sparks | N54: ahorton@uca.edu; wsparks2@uca.edu | S54: Crain Team | T54: Exhibitor Lounge | U54: 3500 | V54: BL-N
A55: Sam's Club | B55: Premier Vendor | C55: 750 | D55: 750 | E55: LH | F55: 4.8.25 | I55: 7/31/25 GB | L55: Alex Breckenridge | N55: a0b0q84.s04749.us@samsclub.com | S55: Cross Creek Sandwich Shop | T55: TOC Food Vendor | U55: 0
A56: Pro-Land Title | B56: Premier Vendor | C56: 750 | D56: 750 | E56: LC-N | F56: 4.11.25 | I56: 7/31/25 GB | J56: 45981 | K56: 750 | L56: Brooklyn Cardin | N56: bcardin@prolandtitle.com | S56: Cuerden Sign | T56: Premier Vendor | U56: 750
A57: Jan-Pro | B57: Premier Vendor | C57: 750 | D57: 750 | E57: LC | F57: 4.22.25 | I57: 7/31/25 GB | J57: 45887 | K57: 750 | L57: Kiana Waits | N57: kiana.waits@jan-pro.com | S57: D&C | T57: Booth Space | U57: 640 | V57: LC-N
A58: Little Rock/Conway Signs | B58: Premier Vendor | C58: 750 | D58: DROP | E58: JG | F58: 4.30.25 | G58: Invoice Andrea@littlerockconwaysign.com | I58: 7/31/25 GB | K58: 0 | L58: David Glover | N58: David@littlerockconwaysign.com | S58: Dave Creek Media | T58: Booth Space | U58: 450 | V58: JG
A59: Owens and Parker Law Firm | B59: Premier Vendor | C59: 750 | D59: 785 | E59: LC | F59: 5.19.25 | I59: 7/31/25 GB | J59: 45880 | K59: 750 | L59: Brooklyn Parker | N59: parker@jowenslawfirm.com | S59: Day-of Ticket Sales | T59: Tickets | U59: 3290
A60: Shadrachs Coffee | B60: Premier Vendor | C60: 750 | D60: 750 | E60: LC | F60: 5.19.25 | G60: Per Leo, Chamber will buy 200 black coffeess for the day | I60: 7/31/25 GB | J60: 45874 | K60: 750 | L60: Tony Pavan | N60: tony@shadrachscoffee.com | S60: Dewees HVAC | T60: Premier Vendor | U60: 750 | V60: JE-N
A61: Exchange Capital | B61: Premier Vendor | C61: 750 | D61: 750 | E61: JE | F61: 8.19.25 | I61: 8/26/25 GB | J61: 45922 | K61: 750 | L61: Scott Coffey | N61: scott@excap.com | S61: Direct Auto Life Insurance | T61: Booth Space | U61: 500 | V61: JE-N
A62: Homewell Cares | B62: Premier Vendor | C62: 750 | D62: 750 | E62: LC | F62: 5.19.25 | I62: 7/31/25 GB | L62: Brandon Phipps | N62: bphipps@homewellcares.com | S62: DKM Construction | T62: Gold | U62: 2000 | V62: CP-N
A63: Watson Homes | B63: Premier Vendor | C63: 750 | D63: 750 | E63: JE-N | F63: 8.27.25 | I63: 45896 | J63: 45896 | K63: 750 | S63: Dyermark | T63: Booth Space | U63: 500 | V63: LC-N
A64: Temporary Wall Systems | B64: Premier Vendor | C64: 750 | D64: 820 | E64: JE-N | F64: 9.5.25 | J64: 45904 | K64: 820 | L64: Lance Wilson | N64: lance.wilson@tempwallsystems.com | S64: Eat My Catfish | T64: TOC Food Vendor | U64: 0
A65: Conway Financial | B65: Premier Vendor | C65: 750 | D65: 785 | F65: 9.5.25 | J65: 45905 | K65: 785 | S65: Ed Allen CPA | T65: Booth Space | U65: 500 | V65: LC-N
A66: D&C Event Services | B66: Premier Vendor | C66: 750 | D66: 870 | J66: 45906 | K66: 870 | S66: Empire Training | T66: Booth Space | U66: 500 | V66: LC-N
A67: Modern Woodmen of America | B67: Premier Vendor | C67: 750 | D67: 750 | F67: 9.11.25 | J67: 45911 | K67: 750 | S67: Engage Management | T67: Booth Space | U67: 500 | V67: BL
A68: Cubby's | B68: Premier Vendor | C68: 750 | D68: 750 | E68: CP-N | F68: 9.15.25 | I68: 9/22/25 GB | J68: 45952 | K68: 750 | L68: Liz Starr | N68: lstarr@mosestucker.com | S68: Exchange Capital | T68: Premier Vendor | U68: 750 | V68: JE-N
A69: Monarch Dental | B69: Booth Space | C69: 500 | D69: TRANSFER | E69: JE-N | F69: 11.27.24 | I69: 7/31/25 GB | J69: 45891 | K69: 500 | L69: Amber Wyatt, Elisabeth Bondoc | N69: amber.wyatt1@smilebrands.com; Elizabeth.bondoc@smilebrands.com | S69: eXp Realty | T69: Booth Space | U69: 500 | V69: LC-N
A70: First Arkansas Bank & Trust | B70: Booth Space | C70: 500 | D70: 0 | E70: LH | F70: 12.9.24 | I70: 0 | L70: John Simmons, Roger Sundermeier, Mark Wilson, Jessica Pint | N70: jsimmons@fabandt.bank; rsundermeier@fabandt.bank; mwilson@fabandt.bank; jpint@fabandt.bank | S70: Express Employment | T70: Booth Space | U70: 425 | V70: LH
A71: Rhea Lana's | B71: Booth Space | C71: 500 | D71: 300 | F71: 10.1.25 | I71: 10/2/25 GB | J71: 45933 | K71: 300 | S71: Fairfield Bay Conference Center | T71: Booth Space | U71: 500 | V71: LC-N
A72: Central Baptist College | B72: Booth Space | C72: 500 | D72: 425 | E72: LH | F72: 1.28.25 | I72: 7/31/25 GB | J72: 45902 | K72: 425 | L72: Jessica Faulkner, Terry Kimbrow, Jeremy Langley | N72: jfaulkner@cbc.edu; tkimbrow@cbc.edu; JLangley@cbc.edu | S72: First Arkansas Bank & Trust | T72: Booth Space | U72: 0 | V72: LH
A73: Engage Management | B73: Booth Space | C73: 500 | D73: 500 | E73: BL | F73: 2.2.25 | I73: 7/31/25 GB | J73: 45880 | K73: 500 | L73: Morgan Lefler | N73: morgan.lefler@engagemanagement.com | S73: First Arkansas Bank & Trust | T73: Tickets | U73: 80
A74: First Service Bank | B74: Booth Space | C74: 500 | D74: 530 | E74: BL | F74: 2.2.25 | I74: 7/31/25 GB | J74: 45880 | K74: 530 | L74: Kevin Wish, Destiny Lankford | N74: kevin.wish@firstservicebank.com; destiny.lankford@firstservicebank.com | S74: First Community Bank | T74: Premier Vendor | U74: 600 | V74: BL
A75: Arvest | B75: Booth Space | C75: 500 | D75: 500 | E75: BL | F75: 2.4.25 | H75: YES | I75: 0 | J75: 4.28.25 | K75: 500 | L75: Brooks Davis, Maret Cahill Wicks | N75: mcahillwicks@arvest.com; bdavis3@arvest.com | S75: First Security Bank | T75: Silver | U75: 1090 | V75: BL
A76: Dyermark | B76: Booth Space | C76: 500 | D76: 500 | E76: LC | F76: 2.11.25 | H76: YES | I76: 7/31/25 GB | J76: 11/18/2025, 12/18/25 | K76: =137.5+362.5 -> 500 | L76: Ali Dyer | N76: ali@dyermark.com | S76: First Service Bank | T76: Booth Space | U76: 530 | V76: BL-N
A77: Barham's Ozark Beef | B77: Booth Space | C77: 500 | D77: 500 | E77: CP-N | F77: 2.19.25 | I77: 7/31/25 GB | J77: 46006 | K77: 500 | L77: Ed Linck | N77: edlinck@gmail.com | S77: Foundation Investors | T77: 1 Taste, 1 Breakfast OR Lunch, 1 session ticket | U77: 0
A78: Superior Heating and Air | B78: Booth Space | C78: 500 | D78: 500 | E78: JE-N | F78: 2.25.25 | I78: 7/31/25 GB | J78: 45875 | K78: 500 | L78: Jennifer Pettry | N78: Superiorhainc@gmail.com | S78: Fountain Bleu | T78: Premier Vendor | U78: 775 | V78: LC-N
A79: Gratus Wealth Management Northwestern Mutual | B79: Booth Space | C79: 500 | D79: 500 | E79: LH | F79: 2.25.25 | H79: YES | J79: 8/4/2025, 8/20/25 | K79: =222.5+277.5 -> 500 | L79: Osmar Garcia, Gilberto Garcia, Miranda Hogg | N79: osmar.a.garcia@nm.com; miranda.hogg@nm.com; gilberto.garcia@nm.com | S79: GARVER | T79: Meal Sponsor | U79: 1350 | V79: JG
A80: Chambers Bank | B80: Booth Space | C80: 500 | D80: 500 | E80: LC | F80: 2.27.25 | I80: 7/31/25 GB | J80: 45875 | K80: 500 | L80: Ethan Barnes | N80: ebarnes@chambers.bank | S80: Good Day Pottery | T80: 1 Taste, 1 Breakfast OR Lunch, 1 session ticket | U80: 70
A81: Jay Bernard State Farm | B81: Booth Space | C81: 500 | D81: 500 | E81: BL | F81: 3.7.25 | I81: 0 | J81: 3.19.25 | K81: 500 | L81: Jay Bernard | N81: jay.bernard.l8if@statefarm.com | S81: Grace & Truth Books | T81: Booth Space | U81: 500
A82: Conway Wealth Management | B82: Booth Space | C82: 500 | D82: 500 | E82: BL | F82: 3.5.25 | H82: YES | J82: 8/26/2025, 9/24/25 | K82: =235+265 -> 500 | L82: Greg Pillow, Rita Stapleton | N82: rita@conwaywm.com; greg@conwaywm.com | S82: Green Bay Packaging | T82: Silver | U82: 1400 | V82: BL
A83: AT&T | B83: Booth Space | C83: 500 | D83: 500 | F83: 10.3.25 | I83: 10/6/25 GB | J83: 45937 | K83: 300 | S83: Hampton Inn and Suites | T83: Premier Vendor | U83: 750 | V83: JE-N
A84: Pediatrics Plus | B84: Booth Space | C84: 500 | D84: 500 | E84: LC | F84: 5.15.25 | I84: 0 | J84: 5.15.25 | K84: 500 | L84: Brooke Bagley | S84: Harvest Cannabis | T84: Networking Game | U84: 2500 | V84: LC
A85: Restoration Health | B85: Booth Space | C85: 500 | D85: 500 | I85: 10/6/25 GB | J85: 45960 | K85: 500 | S85: HD Roofing | T85: Premier Vendor | U85: 750 | V85: LC-N
A86: eXp Realty | B86: Booth Space | C86: 500 | D86: 500 | E86: LC | F86: 5.19.25 | I86: 7/31/25 GB | J86: 45938 | K86: 250 | L86: Samantha Newman | N86: Samantha.newman@exprealty.net | S86: Holiday Inn & Suites | T86: Booth Space | U86: 535
A87: Empire Training | B87: Booth Space | C87: 500 | D87: 500 | E87: LC | F87: 5.19.25 | I87: 7/31/25 GB | L87: Jacob Jasper | N87: jacob@elevatecreative.co | S87: Home Instead Senior Care | T87: Premier Vendor | U87: 750 | V87: LC-N
A88: Alleviant Integrated Mental Health | B88: Booth Space | C88: 500 | D88: 500 | E88: JE-N | F88: 5.27.25 | I88: 7/31/25 GB | J88: 45936 | K88: 500 | L88: Cassandra Hensley | N88: chensley@alleviant.com | S88: Homeward Realty | T88: Booth Space | U88: 570 | V88: LC-N
A89: Andy's Frozen Custard | B89: Booth Space | C89: 500 | D89: 500 | E89: LH | F89: 6.2.25 | I89: 7/31/25 GB | J89: 46007 | K89: 500 | L89: Brandon Crabtree | N89: Brandon@ciseandys.com | S89: Homewell Cares | T89: Premier Vendor | U89: 750 | V89: LC-N
A90: Nothing Bundt Cakes | B90: Booth Space | C90: 500 | D90: 500 | E90: LH-N | F90: 7.7.25 | J90: 45888 | K90: 500 | L90: Shelby Hambuchen | N90: shelbyhambuchen@icloud.com | S90: Hummingbird Media | T90: Booth Space | U90: 500 | V90: LC-N
A91: The Lighthouse Companies | B91: Booth Space | C91: 500 | D91: 500 | F91: 6.10.25 | I91: 0 | J91: 6.10.25 | K91: 500 | S91: ICU Protection | T91: Booth Space | U91: 500 | V91: JE-N
A92: Grifols Plasma Center | B92: Booth Space | C92: 500 | D92: 500 | E92: JE-N | F92: 7.17.25 | H92: YES | I92: 7/17/25 JHS | L92: Tevin Cherry, Michelle Defort, Dontavious Gardenhire | N92: Tevin.cherry@grifols.com; michelle.defort@grifols.com; dontavious.gardenhire@grifols.com | S92: Insight | T92: TOC Tickets | U92: 0 | V92: CP-N
A93: Bell & Sward | B93: Booth Space | C93: 500 | D93: 0 | E93: BL-N | F93: 7.18.25 | I93: 0 | L93: Erik Sward | N93: erik@bellandsward.com | S93: J.ws Helping Hands | T93: Booth Space | U93: 500 | V93: JE-N
A94: Smith Family Funeral Home | B94: Booth Space | C94: 500 | D94: 500 | E94: JE-N | F94: 7.30.25 | I94: 0 | J94: 7.29.25 | K94: 500 | L94: Jaimey | N94: conway@smithfamilycares.com | S94: Jan-Pro | T94: Premier Vendor | U94: 910 | V94: LC-N
A95: Secretary of State | B95: Booth Space | C95: 500 | D95: 500 | F95: 8.4.25 | J95: 45894 | K95: 500 | L95: June Wood | N95: June.wood@sos.arkansas.gov | S95: Jill McCollum Catering | T95: TOC Food Vendor | U95: 0
A96: Townley Pool & Spa | B96: Booth Space | C96: 500 | D96: 600 | E96: JE-N | F96: 8.8.25 | G96: waive two tickets to breakfast and lunch, per Jordan | I96: 8/15/25 GB | J96: 45922 | K96: 500 | L96: David Townley | N96: David@ahhtownley.com | S96: JTS Financial Services | T96: Booth Space | U96: 500 | V96: JE-N
A97: Rolling Suds | B97: Booth Space | C97: 500 | D97: 500 | E97: LC-N | F97: 8.19.25 | I97: 8/26/25 GB | J97: 45975 | K97: 500 | N97: jarret.varela@rollingsuds.com | S97: Karen Ferguson, RE/MAX Elite | T97: Silver | U97: 1000 | V97: LC
A98: Century 21 Parker & Scroggins | B98: Booth Space | C98: 500 | D98: 500 | E98: JE | F98: 8.19.25 | G98: Create two separate invoices. One for Comeatrieze Ester and Victoria Stender. Each in the amount of $250. | I98: 9/2/25 GB (split invoices) | J98: 9/2/2025, 10/7/25 | K98: =250+250 -> 500 | L98: Victoria Stender (paid 9/2/25), Comeatrieze Ester | N98: vicstenrealtor@gmail.com; Comeatrieze.ester@gmail.com | S98: Klaasmeyer | T98: Silver | U98: 1000 | V98: BL
A99: Boston Mountain Rural Health Center | B99: Booth Space | C99: 500 | D99: 500 | E99: JE | F99: 8.20.25 | J99: 45888 | K99: 500 | L99: Lisa Weaver | N99: lisaweaver@bmrhc.net | S99: Lane Housley Trucking | T99: Meal Sponsor | U99: 2500 | V99: BL
A100: Window Depot | B100: Booth Space | C100: 500 | D100: 500 | E100: LC | F100: 9.4.25 | I100: 9/9/25 GB | J100: 45936 | K100: 500 | L100: Zack Venable, Karen | N100: zack@windowdepotar.com; office.windowdepotar@gmail.com | S100: Leaf Filter | T100: Silver | U100: 1000 | V100: LC-N
A101: Ed Allen Consulting | B101: Booth Space | C101: 500 | D101: 500 | F101: 9.4.25 | J101: 45904 | K101: 500 | L101: Ed Allen | N101: ed@edallencpa.com | S101: Legends Resort & Casino Arkansas | T101: Silver | U101: 1000 | V101: LH
...

Sheet Catfish & Cold Ones
A1: CATFISH & COLD ONES | B1: 2025 | S1: CATFISH & COLD ONES | T1: 2024
A2: Total Sponsorship Amount Sold | B2: =SUM(D9:D71) -> 43925 | K2: OUTSTANDING | S2: Total Sponsorship Amount Sold | T2: =SUM(U9:U54) -> 39573
A3: Budget Goal | B3: 25000 | K3: =MIN(K72-B2) -> -775 | S3: Budget Goal | T3: 20000
A4: Remaining Balance | B4: =MIN(B2-B3) -> 18925 | K4: =K72/B2 -> 0.98235629 | S4: Remaining Balance | T4: =MIN(T2-T3) -> 19573
A5: Stretch Goal | B5: 45000 | S5: Stretch Goal | T5: 42000
A6: Remaining Balance | B6: =MIN(B2-B5) -> -1075 | S6: Remaining Balance | T6: =MIN(T2-T5) -> -2427
A8: SPONSOR NAME | B8: SPONSORSHIP | C8: COST | D8: PRICE PLEDGED | E8: SOLD BY | F8: DATE SOLD | G8: NOTES | H8: SPECIAL BILLING | I8: INVOICED | J8: DATE PAID | K8: PAID AMOUNT | L8: CONTACT | M8: PHONE | N8: EMAIL | P8: SOLD BY | Q8: PLEDGED | S8: SPONSOR NAME | T8: SPONSORSHIP | U8: PRICE PLEDGED | V8: SOLD BY
A9: ARcare | B9: Title | C9: 7500 | D9: 7500 | E9: LH | F9: 3.4.25 | G9: Award/check presentation of $1,500 to the ARcare Foundation. | J9: 4.29.25 | K9: 7500 | L9: Garrett Morgan, Emily Brenneman | N9: Garrett.Morgan@arcare.net; Emily.Brenneman@arcare.net | P9: BL | Q9: 13500 | S9: Andy's Frozen Custard | T9: Silver | U9: 0 | V9: LH
A10: Green Bay Packaging | B10: Presenting | C10: 5000 | D10: 5000 | E10: BL | F10: 12.3.24 | H10: YES | J10: 6.5.25 | K10: 5000 | L10: Brad Harville, Christy Prater | N10: bharville@gbp.com, cprater@gbp.com | P10: BL-N | Q10: 6000 | S10: ARcare | T10: Title | U10: 7500 | V10: LH
A11: Caldwell Toyota | B11: Presenting | C11: 5000 | D11: 4000 | E11: JG-N | F11: 12.20.24 | J11: 3.31.25 | K11: 4000 | L11: Jay Caldwell | N11: jay@caldwellcares.com | P11: BL-O | S11: Bank OZK | T11: Individual Ticket | U11: 105
A12: Ozark Mountain Construction | B12: Presenting | C12: 5000 | D12: 5000 | E12: BL-N | F12: 4.8.25 | G12: Include Erin Long (erin@citychurch.tv) on event communication. | H12: YES | J12: 5.12.25 | K12: 5000 | L12: Scott and Laura Pelley | N12: laurapelley@gmail.com; scott@ozarkmtnco.com | P12: CP | S12: Belinda Burrier | T12: Individual Ticket | U12: 70
B13: Presenting | C13: 5000 | P13: CP-N | S13: Black Belt Media | T13: Individual Ticket | U13: 55
A14: Malvern National Bank | B14: Fishing Derby | C14: 2500 | D14: 2500 | E14: LH | F14: 2.18.25 | J14: 4.7.25 | K14: 2500 | L14: Andy Harris, Alica Brown, Alexander Baney | N14: aharris@mnbbank.com; abrown@mnbbank.com; abaney@mnbbank.com | P14: CP-O | S14: Bledsoe Chiropractic | T14: Individual Ticket | U14: 175 | V14: LC-N
A15: Rock City Outfitters | B15: T-shirt | C15: 1500 | D15: 1000 | E15: LC | F15: 2.24.25 | J15: 4.30.25 | K15: 1000 | L15: Ryan Ritchie | N15: ryan@rockcityoutfitters.com | P15: JE | Q15: 610 | S15: Caldwell Toyota | T15: Presenting | U15: 0 | V15: JG
A16: Conway Regional | B16: Gold | C16: 2500 | D16: 2500 | E16: BL | F16: 12.30.24 | J16: 4.9.25 | K16: 2500 | L16: Rebekah Fincher | N16: rfincher@conwayregional.org | P16: JE-N | Q16: 260 | S16: Caldwell Toyota | T16: Individual Ticket | U16: 70
A17: Turbare | B17: Gold | C17: 2500 | D17: 2500 | E17: BL | F17: 1.3.25 | G17: 10 tickets | H17: YES | J17: 7.7.25 | K17: 2500 | L17: Laura Martin, Andria White | N17: ceo@turbare.org; awhite@turbare.org | P17: JE-O | S17: Car-son Construction | T17: Gold | U17: 2500 | V17: BL-N
A18: Car-Son Construction | B18: Gold | C18: 2500 | D18: 2500 | E18: BL | F18: 2.28.25 | G18: 4 tickets to the event. | H18: YES | J18: 4.10.25 | K18: 2500 | L18: Brad Fason, Brian Fason | N18: bfason@car-son.com; bradfason@car-son.com | P18: JG | S18: Cintas | T18: Silver | U18: 1350 | V18: LH
B19: Gold | C19: 2500 | P19: JG-N | Q19: 4000 | S19: City of Conway | T19: Individual Ticket | U19: 0
B20: Gold | C20: 2500 | P20: JG-O | S20: Claire Carter Smithson, Homeward Realty | T20: Individual Ticket | U20: 105 | V20: LC-N
B21: Gold | C21: 2500 | P21: LC | Q21: 2930 | S21: Conway Regional | T21: Gold | U21: 2500 | V21: BL-N
A22: Crafton Tull | B22: Silver | C22: 1000 | D22: 1000 | E22: BL | F22: 1.10.25 | H22: YES | J22: 45887 | K22: 1410 | L22: Lane Housley | N22: lane.housley@craftontull.com | P22: LC-N | Q22: 2475 | S22: Crafton Tull | T22: Silver | U22: 1000 | V22: BL
A23: WACO Title | B23: Silver | C23: 1000 | D23: 1000 | E23: LC-N | F23: 2.7.25 | G23: 8 tickets | J23: 45880 | K23: 1000 | L23: Ryke Dismuke, Brooklyn Burnett | N23: idismuke@wacotitle.com: bburnett1@wacotitle.com | P23: LC-O | S23: Custom Glass | T23: Individual Ticket | U23: 815 | V23: JE-N
A24: The Pest Detective | B24: Silver | C24: 1000 | D24: 1000 | E24: LC-N | G24: provide ability for sponsor to have display area | J24: 45925 | K24: 1000 | L24: Westly Sullins | N24: westhepestdetective@gmail.com | P24: LH | Q24: 12015 | S24: Diamond State Restoration | T24: Silver | U24: 1000 | V24: LC
A25: Cintas | B25: Silver | C25: 1000 | D25: 1350 | E25: LH | F25: 2.25.24 | G25: Plus 10 additional tickets | J25: 3.21.25 | K25: 1350 | L25: Mathew Hoppis | N25: HoppisM@cintas.com | P25: LH-N | S25: Empower Healthcare Solutions | T25: Gold | U25: 2500 | V25: LH
A26: Cousins' | B26: Silver | C26: 1000 | D26: 0 | E26: LH | F26: 2.26.25 | G26: in-kind for hauling event materials | K26: 0 | L26: Adam Robertson, Tara Robertson | N26: adam@cousinsfurniture.com; tara@cousinsfurniture.com | P26: LH-O | S26: Farris Agency | T26: Individual Ticket | U26: 180 | V26: JE-N
A27: Snap-on | B27: Silver | C27: 1000 | D27: 1000 | E27: BL-N | F27: 3.10.25 | H27: YES | J27: 3.28.25 | K27: 1000 | L27: Scott Champlin, Lynne Sponer | N27: scott.l.champlin@snapon.com; lynne.sponer@snapon.com | P27: (blank) | Q27: 2035 | S27: Gate Sales | T27: Individual Ticket | U27: 368
A28: Lost Forty | B28: Silver | C28: 1000 | D28: 0 | P28: TOTAL | Q28: 43825 | S28: Green Bay Packaging | T28: Presenting | U28: 5000 | V28: BL
A29: Point Remoe Brewing Co. | B29: Silver | C29: 1000 | D29: 0 | S29: Hampton Inn and Suites | T29: Individual Ticket | U29: 70 | V29: JE-N
A30: The Rogue Roundabout | B30: Silver | C30: 1000 | D30: 0 | S30: Haynes Ace Hardware | T30: Individual Ticket | U30: 35 | V30: JE-N
A31: Westport Dental | B31: Silver | C31: 1000 | D31: 1000 | E31: LC | F31: 3.26.25 | J31: 4.1.25 | K31: 1000 | L31: Cyndi Winter | N31: cwinter.westport@conwaycorp.net | S31: Home2/Hilton Garden Inn | T31: Individual Ticket | U31: 140 | V31: JE-N
A32: Highpoint Park Apartments (Trinity Development) | B32: Individual Ticket | C32: 35 | D32: 455 | E32: LH | F32: 3.6.25 | J32: 3.6.25 | K32: 455 | L32: Courtnie Pledger | N32: cpledger@trinitydevelopmentinc.com | S32: Malvern National Bank | T32: Fishing Derby | U32: 2500 | V32: LH
A33: Ott Insurance | B33: Individual Ticket | C33: 35 | D33: 175 | E33: LC-N | F33: 2.7.25 | G33: 5 tickets | J33: 3.10.25 | K33: 175 | L33: Michelle Mallett | N33: michellemallett@ottinsurance.com | S33: Megan Stewart | T33: Individual Ticket | U33: 110 | V33: LC-N
A34: SMC Conway, A Division of GBP | B34: Individual Ticket | C34: 35 | D34: 210 | E34: LH | F34: 3.14.25 | H34: YES | J34: 45877 | K34: 210 | L34: Jimmy Toal, Sonya Griffis | N34: jimmy.toal@smcpackaging.com; sonya.griffis@smcpackaging.com | S34: Online Sales | T34: Individual Ticket | U34: 1210
A35: Morgan Drayton | B35: Individual Ticket | C35: 35 | D35: 125 | G35: 4 tickets | J35: 4.17.25 | K35: 125 | S35: Ott Insurance | T35: Individual Ticket | U35: 140 | V35: LC
A36: Tommy's Car Wash | B36: Individual Ticket | C36: 35 | D36: 0 | E36: JE | F36: 3.21.25 | G36: 3 tickets | L36: Kason | S36: PCSI | T36: Individual Ticket | U36: 140 | V36: LC-N
A37: Window Depot | B37: Individual Ticket | C37: 35 | D37: 70 | E37: LC | F37: 3.24.25 | J37: 3.24.25 | K37: 70 | L37: Zack Venable, Karen | N37: zack@windowdepotar.com; office.windowdepotar@gmail.com | S37: Power Spine and Sport | T37: Individual Ticket | U37: 60 | V37: JE-N
A38: P.I. Roofing and Construction | B38: Individual Ticket | C38: 35 | D38: 70 | F38: 3.24.25 | J38: 3.24.25 | K38: 70 | S38: Rock City Outfitters | T38: T-Shirt | U38: 1000 | V38: LC
A39: Major A Yard Games | B39: Individual Ticket | C39: 35 | D39: 105 | E39: JE-N | F39: 3.31.25 | G39: 3 tickets | J39: 4.22.25 | K39: 105 | L39: Lyn Alexander | N39: alexanderlynbusiness@gmail.com | S39: Scott Coffey | T39: Individual Ticket | U39: 70
A40: Turbare | B40: Individual Ticket | C40: 35 | D40: 420 | F40: 3.31.25 | J40: 3.31.25 | K40: 420 | S40: Simmons Bank | T40: Individual Ticket | U40: 70
A41: Adena White | B41: Individual Ticket | C41: 35 | D41: 55 | F41: 3.31.25 | J41: 3.31.25 | K41: 55 | S41: Steve Wade | T41: Individual Ticket | U41: 70
A42: Chamber Banks | B42: Individual Ticket | C42: 35 | D42: 385 | E42: LC | F42: 4.2.25 | J42: 4.2.25 | K42: 385 | S42: Superior Plumbing | T42: Individual Ticket | U42: 315 | V42: LC-N
A43: Westport Dental | B43: Individual Ticket | C43: 35 | D43: 195 | E43: LC | F43: 4.2.25 | J43: 4.1.25 | K43: 195 | S43: The Barking Lot | T43: Dog Area | U43: 2500 | V43: LC-N
A44: Henderson | B44: Individual Ticket | C44: 35 | D44: 55 | F44: 4.2.25 | S44: The Pest Detective | T44: Gold | U44: 1000 | V44: LC
A45: Steve Wade | B45: Individual Ticket | C45: 35 | D45: 0 | G45: 2 tickets | S45: Tommy's Express and Car Wash | T45: Individual Ticket | U45: 105 | V45: JE
A46: Custom Glass | B46: Individual Ticket | C46: 35 | D46: 570 | E46: JE | F46: 4.3.25 | G46: 2 – Youth Small 1 – Adult Small 2 – Adult Mediums 2 – Adult Large 4 – Adult XL 3 – Adult 2XL | J46: 6.10.25 | K46: 570 | L46: Greg Jumper | N46: greg@customglass501.com | S46: Top Notch | T46: Individual Ticket | U46: 110 | V46: LC-N
A47: Exchange Capital | B47: Individual Ticket | C47: 35 | D47: 70 | E47: JE-N | F47: 4.3.25 | L47: Scott Coffey | N47: scott@excap.com
B48: Individual Ticket | C48: 35 | S48: Trinity Development | T48: Individual Ticket | U48: 450 | V48: LH
A49: Verizon | B49: Individual Ticket | C49: 35 | D49: 70 | E49: LC-N | F49: 4.9.25 | L49: Joey Paysoukham Tanthaphengsai | N49: joey.tanthaphengsai@verizonwireless.com | S49: Turbare | T49: Gold | U49: 2500 | V49: BL-N
A50: Noah Clay | B50: Individual Ticket | C50: 20 | D50: 20 | K50: 20 | S50: Waco Title | T50: Individual Ticket | U50: 175 | V50: LC-N
A51: Hampton Inn & Suites | B51: Individual Ticket | C51: 20 | D51: 40 | E51: JE | K51: 40 | S51: Westport Dental | T51: Silver | U51: 1000 | V51: LC
A52: Westport Dental | B52: Individual Ticket | C52: 20 | D52: 40 | E52: LC | K52: 40 | S52: Westport Dental | T52: Individual Ticket | U52: 230 | V52: LC-N
A53: Storybook Renovations/Ustorage | B53: Individual Ticket | C53: 20 | D53: 70 | J53: 5.12.25 | K53: 70 | S53: Window Depot | T53: Individual Ticket | U53: 70 | V53: LC-N
A54: Pro-Land Title | B54: Individual Ticket | C54: 20 | D54: 80 | E54: LC-N | F54: 4.11.25 | J54: 45917 | K54: 80 | L54: Brooklyn Cardin | N54: bcardin@prolandtitle.com | S54: Wonder State | T54: Individual Ticket | U54: 210 | V54: LH-N
A55: Bank OZK | B55: Individual Ticket | C55: 20 | D55: 40 | J55: 4.14.25 | K55: 40
A56: Superior Plumbing & Rooter | B56: Individual Ticket | C56: 20 | D56: 240 | E56: LC | J56: 6.17.25, 4/15/25 | K56: =200+100 -> 300
A57: Turbare | B57: Individual Ticket | C57: 20 | D57: 20 | J57: 4.16.25 | K57: 20
A58: Belinda Boyd | B58: Individual Ticket | C58: 20 | N58: belinda.boyd@apmarkansas.net
A59: DeTASO Software | B59: Individual Ticket | C59: 20 | D59: 30 | J59: 4.17.25 | K59: 30
A60: McClurkins | B60: Individual Ticket | C60: 20 | D60: 40 | J60: 4.17.25 | K60: 40
A61: Champion Chiropractic | B61: Individual Ticket | C61: 20 | D61: 40 | J61: 4.17.25 | K61: 40
A62: Ginny Pryor | B62: Individual Ticket | C62: 20 | D62: 40 | J62: 4.7.25 | K62: 40
A63: Belinda Burrier | B63: Individual Ticket | C63: 20 | D63: 110 | E63: LC-N | J63: 5.8.25 | K63: 110 | N63: belinda.boyd@apmarkansas.net
A64: The Studio Downtown | B64: Individual Ticket | C64: 20 | D64: 85 | E64: JE-N | J64: 4.18.25 | K64: 85
A65: Lane Housley | B65: Individual Ticket | C65: 20 | D65: 410 | H65: YES
A66: Becca White | B66: Individual Ticket | C66: 20 | D66: 40 | E66: LC-N | N66: becca@homewardhomes.com
A67: Event Gate Sales - Adults | B67: Individual Ticket | C67: 20 | D67: 420
A68: Event Gate Sales - Kids | B68: Individual Ticket | C68: 10 | D68: 140
A69: Event Tee Sales - Adults | B69: Individual Ticket | C69: 15 | D69: 30
A70: Event Tee Sales - Youth | B70: Individual Ticket | C70: 10 | D70: 10
B71: Individual Ticket | C71: 100 | D71: 100 | K71: 100
K72: =SUM(K9:K71) -> 43150
E307: BL-O
E308: BL-N
E309: BL
E310: CP-O
E311: CP-N
E312: CP
E313: JG-O
E314: JG-N
E315: JG
E316: JE-O
E317: JE-N
E318: JE
... E324: LH

Sheet CDC Membership
A1: CDC MEMBERSHIP | B1: 2025
A2: Total Sponsorship Amount Sold | B2: =SUM(D9:D117) -> 171850 | K2: OUTSTANDING
A3: Budget Goal | B3: 173000 | K3: =MIN(K119-B2) -> -3350
A4: Remaining Balance | B4: =MIN(B2-B3) -> -1150 | K4: =K119/B2 -> 0.98050626
A5: Stretch Goal | B5: 173000
A6: Remaining Balance | B6: =MIN(B2-B5) -> -1150
A8: SPONSOR NAME | B8: MEMBERSHIP LEVEL | C8: COST | D8: PRICE PLEDGED | E8: SOLD BY | F8: DATE SOLD | G8: NOTES | H8: SPECIAL BILLING | I8: INVOICED | J8: DATE PAID | K8: PAID AMOUNT | L8: CONTACT | M8: PHONE | N8: EMAIL | P8: SOLD BY | Q8: PLEDGED
A9: Acxiom | B9: Three Voting Members | C9: 3000 | D9: 3000 | E9: BL-N | F9: 1.8.25 | J9: 3.13.25 | K9: 3000 | L9: Crystal Floyd, Alison Cowles | N9: Crystal.Floyd@acxiom.com; Alison.Cowles@acxiom.com | P9: BL | Q9: 21500
A10: Alliance Investment Group, LLC | B10: One Voting Member | C10: 1500 | P10: BL-N | Q10: 37350
A11: American Safeguard Insurance | B11: One Voting Member | C11: 1500 | D11: 1500 | E11: LH-N | F11: 12.23.24 | H11: YES | J11: 1.17.25 | K11: 1500 | L11: Jeremy Davis, Jason Smith, | N11: jdavis@asiagents.com; jsmith@asiagents.com; | P11: BL-O
A12: Arvest Bank | B12: Three Voting Members | C12: 3000 | D12: 3000 | E12: BL-N | F12: 2.4.24 | H12: YES | J12: 3.31.25 | K12: 3000 | L12: Brooks Davis, Maret Cahill Wicks | N12: mcahillwicks@arvest.com; bdavis3@arvest.com | P12: CP | Q12: 6000
A13: AT&T | B13: One Voting Member | C13: 1500 | D13: 1500 | E13: JG-N | F13: 5.9.25 | J13: 5.9.25 | K13: 1500 | P13: CP-N | Q13: 7500
A14: Attorney's Title Group | B14: One Voting Member | C14: 1500 | D14: 1500 | E14: LC | F14: 4.7.25 | J14: 4.7.25 | K14: 1500 | P14: CP-O
A15: B&A Property Maintenance | B15: One Voting Member | C15: 1500 | D15: 1500 | E15: JG-N | F15: 4.25.25 | J15: 45919 | K15: 1500 | L15: Ryan Johnson | N15: rjohnson@bandapm.com | P15: JE
A16: Baptist Health Medical Center, Conway | B16: Three Voting Members | C16: 3000 | D16: 1500 | E16: JG | F16: 1.13.25 | J16: 7.28.25 | K16: 1500 | L16: April Bennett | P16: JE-N | Q16: 1500
A17: Cadence Bank | B17: One Voting Member | C17: 1500 | D17: 1500 | E17: LH-N | F17: 2.28.25 | J17: 6.3.25 | K17: 1500 | L17: Tom Nelson | N17: tom.nelson@cadencebank.com | P17: JE-O
A18: Car-Son Construction | B18: One Voting Member | C18: 1500 | D18: 1350 | E18: BL-N | F18: 2.28.25 | H18: YES | J18: 5.16.25 | K18: 1350 | L18: Brad Fason, Brian Fason | N18: bfason@car-son.com; bradfason@car-son.com | P18: JG | Q18: 7500
A19: Carty, Harding & Hearn, Inc. | B19: One Voting Member | C19: 1500 | D19: 1500 | J19: March | K19: 1500 | P19: JG-N | Q19: 12000
A20: Catalyst Financial | B20: One Voting Member | C20: 1500 | D20: 1500 | E20: LH-N | F20: 2.24.25 | J20: 6.3.25 | K20: 1500 | L20: Drew Gainor | N20: dgainor@financialguide.com | P20: JG-O
A21: Centennial Bank | B21: Three Voting Members | C21: 3000 | D21: 3000 | J21: 45923 | K21: 3000 | P21: LC | Q21: 1500
A22: Central Baptist College | B22: One Voting Member | C22: 1500 | D22: 1500 | E22: LH-N | F22: 1.28.25 | J22: 5.27.25 | K22: 1500 | L22: Terry Kimbrow/Jeremy Langley | N22: tkimbrow@cbc.edu; jlangley@cbc.edu | P22: LC-N | Q22: 7500
A23: Chris Crain Enterprises | B23: One Voting Member | C23: 1500 | D23: 1500 | E23: BL-N | F23: 11.20.24 | J23: 45943 | K23: 1500 | L23: Brett Berry | N23: brettberry@chriscraingroup.com | P23: LC-O
A24: Cintas | B24: One Voting Member | C24: 1500 | D24: 1500 | E24: LH-N | F24: 2.25.24 | J24: 3.21.25 | K24: 1500 | L24: Mathew Hoppis | N24: HoppisM@cintas.com | P24: LH | Q24: 10500
B25: One Voting Member | C25: 1500 | P25: LH-N | Q25: 31500
A26: Clayton Conway | B26: Three Voting Members | C26: 3000 | D26: 3000 | E26: CP-N | G26: All communications – Jamar Murchison – jamar.murchison@claytonhomes.com All communications – Stephanie Amerson – stephanie.amerson@claytonhomes.com Billing – Jake Turpin – jake.turpin@claytonhomes.com | J26: 4.15.25 | K26: 3000 | L26: Jake Turpin | N26: jake.turpin@claytonhomes.com | P26: LH-O | Q26: 5000
A27: Colliers | B27: One Voting Member | C27: 1500 | D27: 1500 | E27: BL | J27: 3.14.25 | K27: 1500 | P27: (blank) | Q27: 13500
A28: Conductor | B28: One Voting Member | C28: 1500 | D28: 1500 | E28: LH-N | F28: 1.13.25 | J28: 2.25.25 | K28: 1500 | L28: Grace Rains | N28: grace@arconductor.org | P28: TOTAL | Q28: 162850
B29: One Voting Member | C29: 1500
A30: Conway Behavioral Health - Acadia Health Care | B30: One Voting Member | C30: 1500 | D30: 1500 | E30: LH-N | F30: 3.10.25 | J30: 4.2.25 | K30: 1500 | L30: Valencia Anderson | N30: Valencia.Anderson@conwaybh.com
A31: Conway Corporation | B31: Five Voting Members | C31: 100000 | D31: 0 | G31: per agreement | K31: 0 | L31: Bret Carroll
A32: Conway Regional | B32: Three Voting Members | C32: 3000 | D32: 3000 | E32: BL | F32: 12.30.24 | J32: 3.14.25 | K32: 3000 | L32: Rebekah Fincher, Matt Troup | N32: rfincher@conwayregional.org; matt.troup@conwayregional.org
A33: Conway Wealth Management | B33: One Voting Member | C33: 1500 | D33: 1500 | E33: BL | K33: 1500
A34: Corco Construction | B34: One Voting Member | C34: 1500 | D34: 1500 | E34: BL-N | F34: 3.18.25 | J34: 45831 | K34: 1500 | L34: Justin Bennett, Jon Virden | N34: jvirden@corcoconstruction.com; jbennett@corcoconstruction.com
A35: Covington Companies | B35: One Voting Member | C35: 1500 | D35: 1500 | E35: BL-N | F35: 3.13.25 | J35: 3.13.25 | K35: 1500
A36: Crafton Tull | B36: One Voting Member | C36: 1500 | D36: 1500 | E36: BL-N | F36: 1.10.25 | H36: YES | J36: 45944 | K36: 1500 | L36: Lane Housley | N36: lane.housley@craftontull.com
A37: Cromwell Architects | B37: One Voting Member | C37: 1500
A38: Cuerden Sign | B38: One Voting Member | C38: 1500
A39: Dave Creek Media | B39: One Voting Member | C39: 1500 | D39: 1500 | E39: JG | F39: 2.28.25 | L39: Jakob Michaelis | N39: jakob@davecreekmedia.com
A40: DKM Construction | B40: One Voting Member | C40: 1500 | D40: 1500 | E40: CP | F40: 2.17.25 | H40: YES | J40: 4.7.25 | K40: 1500 | L40: Kim Morehart, Daniel Morehart | N40: kimm.dkm@gmail.com; danielm.dkm@gmail.com
A41: Eddie Glover | B41: One Voting Member | C41: 1500
A42: Engage Management | B42: Three Voting Members | C42: 3000 | D42: 3000 | E42: BL | F42: 2.2.25 | J42: 45733 | K42: 3000 | L42: Morgan Lefler | N42: morgan.lefler@engagemanagement.com
A43: Entergy | B43: One Voting Member | C43: 1500 | D43: 1500 | E43: CP | F43: 2.25.25 | J43: 2.25.25 | K43: 1500 | L43: Zack Hale, James Warren | N43: zhale@entergy.com; jwarren@entergy.com
A44: EOS Worldwide: Drew Spurgers | B44: One Voting Member | C44: 1500 | D44: 1500 | E44: LH-N | F44: 2.10.25 | H44: YES | J44: 45954 | K44: 1500 | L44: Drew Spurgers | N44: drew.spurgers@eosworldwide.com
A45: ERA Team | B45: One Voting Member | C45: 1500 | D45: 1500 | E45: LH-N | F45: 5.22.25 | J45: 5.22.25 | K45: 1500
A46: Express Employment | B46: One Voting Member | C46: 1500
A47: Farris Agency | B47: One Voting Member | C47: 1500 | D47: 1500 | E47: JE-N | F47: 12.4.24 | J47: 3.10.25 | K47: 1500 | L47: Alan White, Travis Mulhearn, Christina Horn | N47: alan@farrisagency.com travis@farrisagency.com christina@farrisagency.com
A48: Faulkner County Title Company | B48: One Voting Member | C48: 1500 | D48: 1500 | J48: 3.10.25 | K48: 1500
A49: First Arkansas Bank & Trust | B49: Three Voting Members | C49: 3000 | D49: 1500 | E49: LH | F49: 12.9.24 | H49: YES | J49: 1.31.25 | K49: 1500 | L49: John Simmons, Mark Wilson | N49: mwilson@fabandt.bank; jsimmons@fabandt.bank
A50: First Community Bank | B50: One Voting Member | C50: 1500 | D50: 1500 | E50: BL-N | J50: 3.12.25 | K50: 1500 | L50: Lori Melton, Grant Gordy | N50: Lori.Melton@firstcommunity.net; Grant.Gordy@firstcommunity.net
A51: First Security Bank/Crews & Associates | B51: Five Voting Members | C51: 5000 | D51: 5000 | E51: BL | G51: Payment split between Crews and FSB. | J51: 3.12.25 | K51: 2500
J52: 4.16.25 | K52: 2500
A53: First Service Bank | B53: Three Voting Members | C53: 3000 | D53: 3000 | E53: BL | F53: 2.2.25 | J53: 45947 | K53: 3000 | L53: Kevin Wish, Destiny Lankford | N53: kevin.wish@firstservicebank.com; destiny.lankford@firstservicebank.com
A54: Flywheel Energy | B54: One Voting Member | C54: 1500 | D54: 1500 | E54: BL-N | F54: 2.28.25 | J54: 45908 | K54: 1500 | L54: Andy Miller | N54: andy.miller@flywheelenergy.com
A55: Fureigh Electric | B55: One Voting Member | C55: 1500 | D55: 1500 | E55: LC-N | F55: 7.8.25 | H55: YES | J55: 45908 | K55: =892+608 -> 1500 | L55: Ben Fureigh | N55: ben@fureighinc.com
A56: GARVER | B56: Three Voting Members | C56: 3000 | D56: 3000 | E56: JG | F56: 2.18.25 | J56: 3.10.25 | K56: 3000 | L56: Dustin Tackett | N56: DLTackett@GarverUSA.com
A57: Green Bay Packaging | B57: One Voting Member | C57: 1500 | D57: 1500 | E57: BL-N | F57: 12.3.24 | H57: YES | J57: 1.30.25 | K57: 1500 | L57: Brad Harville, Christy Prater | N57: bharville@gbp.com, cprater@gbp.com
A58: H+N Architects | B58: One Voting Member | C58: 1500 | D58: 1500 | E58: LH-N | F58: 12.19.24 | H58: YES | J58: 4.25.25 | K58: 1500 | L58: Liz Hamilton, Joanna Nabholz | N58: liz@hnarch.com; joanna@hnarch.com
A59: Hardwyre | B59: One Voting Member | C59: 1500 | D59: 1500 | E59: LH-N | F59: 3.4.25 | J59: 3.5.25 | K59: 1500 | L59: Steve Wade
A60: Hart Construction | B60: One Voting Member | C60: 1500 | D60: 1500 | E60: CP-N | F60: 9.25.25 | G60: Billing contact: Kayla Hargrove: khargrove@hartconllc.com | J60: 45926 | K60: 1500 | L60: Hudson Jones | N60: hjones@hartconllc.com
A61: Harvest Cannabis Dispensary | B61: One Voting Member | C61: 1500 | D61: 1500 | E61: LC-N | F61: 4.14.25 | J61: 45880 | K61: 1500 | L61: Robbin | N61: robbin@harvestcannabisarkansas.com
A62: HCJ CPA's & Advisors | B62: One Voting Member | C62: 1500 | D62: 1500 | F62: 3.13.25 | J62: 3.13.25 | K62: 1500
A63: Hendrix College | B63: One Voting Member | C63: 1500 | D63: 1500 | E63: JG-N | F63: 12.17.24 | J63: 3.6.25 | K63: 1500 | L63: Karen Petersen | N63: petersen@hendrix.edu
A64: HSA Engineering | B64: One Voting Member | C64: 1500 | D64: 1500 | E64: LH | F64: 2.7.25 | H64: YES | J64: 3.7.25 | K64: 1500 | L64: Trey White, Michael Rappold | N64: twhite@hsaconsultants.com; mrappold@hsaconsultants.com
A65: Insight | B65: Three Voting Members | C65: 3000 | D65: 3000 | E65: CP-N | F65: 2.19.25 | H65: YES | J65: 2.28.25 | K65: 3000 | L65: Steven Tyler, Jenny Vallas | N65: steven.tyler@insight.com; jenny.vallas@insight.com
A66: International Paper | B66: One Voting Member | C66: 1500 | D66: 1500 | J66: 5.2.25 | K66: 1500
A67: Jeff Standridge Innovation Partners | B67: One Voting Member | C67: 1500 | D67: 1500 | J67: 45917 | K67: 1500
A68: Jerry Adams | B68: One Voting Member | C68: 1500 | D68: 1500 | J68: 45925 | K68: 1500
A69: Johnny Adams | B69: One Voting Member | C69: 1500 | D69: 0 | G69: Setup for membership 1/2026
A70: Kinco | B70: One Voting Member | C70: 1500 | D70: 1500 | E70: LH-N | F70: 5.21.25 | J70: 5.21.25 | K70: 1500
A71: Klaasmeyer Construction | B71: Three Voting Members | C71: 3000 | D71: 3000 | E71: BL-N | J71: 3.24.25 | K71: 3000
A72: Kutak Rock | B72: One Voting Member | C72: 1500 | D72: 1500 | E72: BL-N | F72: 3.10.25 | J72: 3.24.25 | K72: 1500 | L72: Gordon Wilbourn | N72: gordon.wilbourn@kutakrock.com
A73: Landmark CPAs | B73: One Voting Member | C73: 1500 | D73: 1500 | E73: LH-N | F73: 2.14.25 | H73: YES | J73: 6.6.25 | K73: 1500 | L73: Randy Milligan | N73: RMilligan@landmarkcpas.com
A74: Lenders Title Company | B74: One Voting Member | C74: 1500 | D74: 1500 | J74: 4.15.25 | K74: 1500
A75: Lewis Ranch | B75: One Voting Member | C75: 1500 | D75: 1500 | J75: 5.22.25 | K75: 1500
A76: Little Rock/Conway Signs | B76: One Voting Member | C76: 1500 | D76: 1500 | E76: JG-N | F76: 4.30.25 | J76: 45919 | K76: 1500 | L76: David Glover | N76: David@littlerockconwaysign.com
A77: Log Cabin Democrat | B77: One Voting Member | C77: 1500 | D77: 1500 | E77: JG-N | F77: 2.13.25 | J77: 45950 | K77: 1500
A78: Lumber One | B78: One Voting Member | C78: 1500 | D78: 1500 | J78: 45846 | K78: 1500
A79: Malvern National Bank | B79: One Voting Member | C79: 1500 | D79: 1500 | E79: LH-N | F79: 2.18.25 | J79: 5.27.25 | K79: 1500 | L79: Andy Harris | N79: aharris@mnbbank.com
A80: Melvin's Painting | B80: One Voting Member | C80: 1500 | D80: 1500 | E80: LH | F80: 3.7.25 | J80: 3.7.25 | K80: 1500
A81: McGeorge Contracting | B81: One Voting Member | C81: 1500 | D81: 1500 | E81: JG-N | F81: 8.26.25 | J81: 45916 | K81: 1500 | L81: Brian McMillian | N81: brian.mcmillian@mcgeorgecontracting.com
A82: Mike's Place | B82: One Voting Member | C82: 1500
A83: MSC Eye Associates | B83: One Voting Member | C83: 1500 | D83: DROP
A84: Nabco | B84: One Voting Member | C84: 1500 | D84: 1500 | E84: LC-N | F84: 3.10.25 | J84: 3.10.25 | K84: 1500
A85: Nabholz | B85: Three Voting Members | C85: 3000 | D85: 3000 | E85: BL-N | F85: 2.2.25 | J85: 3.11.25 | K85: 3000 | L85: Jake Nabholz | N85: jake.nabholz@nabholz.com
A86: Nabholz Properties | B86: One Voting Member | C86: 1500 | D86: 1500 | J86: 45910 | K86: 1500
A87: Nativ State | B87: One Voting Member | C87: 1500 | D87: 1500 | E87: LH-N | F87: 4.16.25 | J87: 5.21.25 | K87: 1500 | L87: Stuart Allen | N87: stuart@nativstate.com
A88: Oaks Brothers | B88: Three Voting Members | C88: 3000 | D88: 3000 | E88: LH | F88: 4.16.25 | J88: 4.16.25 | K88: 3000 | L88: Greg Oaks
A89: Ozark Mountain Construction | B89: One Voting Member | C89: 1500 | D89: 1500 | E89: BL-N | F89: 4.8.25 | H89: YES | J89: 5.12.25 | K89: 1500 | L89: Scott and Laura Pelley | N89: laurapelley@gmail.com; scott@ozarkmtnco.com
A90: Preferred Medical | B90: One Voting Member | C90: 1500 | D90: 1500 | J90: 3.24.25 | K90: 1500
A91: Pumpcon | B91: One Voting Member | C91: 1500 | D91: 1500 | J91: 3.27.25 | K91: 1500
A92: Reliance Health Care, Incite Rehab, Heartland Pharmacy, Heritage Living Center | B92: Three Voting Members | C92: 3000 | D92: 3000 | E92: LH | F92: 4.7.25 | H92: YES | J92: 5.27.25 | K92: 2650
A93: Riddle & Associates | B93: One Voting Member | C93: 1500 | D93: 1500 | E93: LH-N | F93: 2.17.25 | J93: 45943 | K93: 1500 | L93: Jeremy Riddle | N93: springhillstorage@gmail.com
A94: Rogers Group | B94: One Voting Member | C94: 1500 | D94: 1500 | E94: BL | F94: 1.3.25 | J94: 4.2.25 | K94: 1500 | L94: Mike Connelly | N94: mike.connelly@rogersgroupinc.com
A95: SFI of Arkansas | B95: Three Voting Members | C95: 1500
A96: Simmons Bank | B96: One Voting Member | C96: 1500 | D96: 1500 | E96: BL | F96: 1.2.25 | J96: 4.21.25 | K96: 1500 | L96: Justin McCarty | N96: justin.mccarty@simmonsbank.com
A97: Sinco | B97: Three Voting Members | C97: 3000 | D97: 3000 | E97: CP | F97: 2.21.25 | H97: YES | J97: 4.8.25 | K97: 1956.25 | L97: Parker Spradlin, Grey Williams, Rhonda Wilson | N97: Pspradlin@sincoinc.com; gwilliams@sincoinc.com; rwilson@sincoinc.com
J98: 6.9.25 | K98: 1043.75
A99: Smith Ford | B99: One Voting Member | C99: 1500 | D99: 1500 | E99: BL | F99: 2.1.25 | J99: 4.28.25 | K99: 1500 | L99: Cate McConnell
A100: Snap-on Equipment | B100: One Voting Member | C100: 1500 | D100: 1500 | E100: BL-N | F100: 3.10.25 | H100: YES | J100: 3.11.25 | K100: 1500 | L100: Scott Champlin, Lynne Sponer | N100: scott.l.champlin@snapon.com; lynne.sponer@snapon.com
A101: Sowell Ferris Architects | B101: One Voting Member | C101: 1500 | D101: 1500 | E101: LH-N | F101: 2.18.25 | J101: 5.27.25 | K101: 1500 | L101: Cody Ferris, Emily Ferris | N101: cody@sowellarchitects.com; emily@sowellarchitects.com
...

Sheet CDP Annual Meeting
A1: CDP ANNUAL MEETING | B1: 2025 | S1: CDP Annual Meeting | T1: 2024
A2: Total Sponsorship Amount Sold | B2: =SUM(D9:D53) -> 39700 | K2: OUTSTANDING | S2: Total Sponsorship Amount Sold | T2: =SUM(U9:U39) -> 29025
A3: Budget Goal | B3: 30000 | K3: =MIN(K36-B2) -> -9000 | S3: Budget Goal | T3: 38000
A4: Remaining Balance | B4: =MIN(B2-B3) -> 9700 | K4: =K36/B2 -> 0.77329975 | S4: Remaining Balance | T4: =MIN(T2-T3) -> -8975
A5: Stretch Goal | B5: 38000 | S5: Stretch Goal | T5: 40000
A6: Remaining Balance | B6: =MIN(B2-B5) -> 1700 | S6: Remaining Balance | T6: =MIN(T2-T5) -> -10975
A8: SPONSOR NAME | B8: SPONSORSHIP | C8: COST | D8: PRICE PLEDGED | E8: SOLD BY | F8: DATE SOLD | G8: NOTES | H8: SPECIAL BILLING | I8: INVOICED | J8: DATE PAID | K8: PAID AMOUNT | L8: CONTACT | M8: PHONE | N8: EMAIL | P8: SOLD BY | Q8: PLEDGED | S8: SPONSOR NAME | T8: SPONSORSHIP | U8: PRICE PLEDGED | V8: SOLD BY
B9: Title | C9: 7500 | P9: BL | Q9: 14500 | S9: Acxiom | T9: Table | U9: 1000 | V9: BL
A10: GARVER | B10: Presenting | C10: 5000 | D10: 3000 | E10: JG-N | F10: 2.18.25 | I10: 9/15/25 GB | J10: 45922 | K10: 3000 | L10: Dustin Tackett | N10: DLTackett@GarverUSA.com | P10: BL-N | Q10: 9500 | S10: AFCU | T10: Ticket | U10: 250
A11: Clayton Conway | B11: Presenting | C11: 5000 | D11: 2500 | E11: CP-N | F11: 310.25 | G11: All communications – Jamar Murchison – jamar.murchison@claytonhomes.com All communications – Stephanie Amerson – stephanie.amerson@claytonhomes.com Billing – Jake Turpin – jake.turpin@claytonhomes.com | I11: 9/15/25 GB | J11: 45925 | K11: 2500 | L11: Jake Turpin | N11: jake.turpin@claytonhomes.com | P11: BL-O | S11: Angie Davis | T11: Ticket | U11: 375 | V11: LC-N
A12: Ozark Mountain Construction | B12: Presenting | C12: 5000 | D12: 5000 | E12: BL-N | F12: 4.8.25 | G12: Include Erin Long (erin@citychurch.tv) on event communication. | H12: YES | J12: 45894 | K12: 5000 | L12: Scott and Laura Pelley | N12: laurapelley@gmail.com; scott@ozarkmtnco.com | P12: CP | S12: B&A Properties | T12: Ticket | U12: 250 | V12: LC-N
A13: Main Street Arkansas | B13: Underwriter | C13: 5000 | D13: 5000 | F13: 9.25 | G13: This is coming from the CDP grant. Provide same benefits as a presenting sponsor. | H13: Laura will handle | L13: Greg Phillips | N13: greg.phillips@arkansas.gov | P13: CP-N | Q13: 2500 | S13: Cadence Bank | T13: Ticket | U13: 250
A14: H+N Architects | B14: Awards | C14: 2500 | D14: 2500 | E14: LH | F14: 12.19.24 | H14: YES | J14: 4.25.25 | K14: 2500 | L14: Liz Hamilton, Joanna Nabholz | N14: liz@hnarch.com; joanna@hnarch.com | P14: CP-O | S14: Chris Crain Enterprises | T14: Table | U14: 1000 | V14: BL
A15: Turbare | B15: Awards | C15: 2500 | D15: 2500 | E15: BL-N | F15: 1.3.25 | G15: Rep participates and speaks at event | H15: YES | L15: Laura Martin, Andria White | N15: ceo@turbare.org; awhite@turbare.org | P15: JE | S15: Conductor | T15: Table | U15: 1000 | V15: LH
A16: Covington Companies | B16: Awards | C16: 2500 | D16: 2000 | E16: BL | F16: 3.24.25 | I16: 9/15/25 GB | J16: 45931 | K16: 2000 | L16: George Covington, Savannah Brorman | N16: gcov@conwaycorp.net; savannah@covingtoncompanies.net | P16: JE-N | S16: Conway Corporation | T16: Table | U16: 1000 | V16: BL
A17: State Farm Jay Bernard | B17: Speaker | C17: 2500 | D17: 2500 | E17: BL | F17: 2.28.25 | H17: YES | J17: 3.19.25 | K17: 2500 | L17: Jay Bernard | N17: jay.bernard.l8if@statefarm.com | P17: JE-O | S17: Conway Regional | T17: Table | U17: 1000 | V17: BL-N
A18: Chris Crain Enterprises | B18: Table | C18: 1000 | D18: 1000 | E18: BL | F18: 11.20.24 | G18: Confirm with NK/BB which Chris Crain Enterprises company/companies will be featured on event. | I18: 9/15/25 GB | J18: 45922 | K18: 1000 | L18: Brett Berry, Nita Kat Freeman | N18: brettberry@chriscraingroup.com; nitafreeman@chriscraingroup.com | P18: JG | S18: Covington Companies | T18: Awards | U18: 2000 | V18: BL
A19: Green Bay Packaging | B19: Table | C19: 1000 | D19: 1000 | E19: BL | F19: 12.3.24 | H19: YES | J19: 45980 | K19: 1000 | L19: Brad Harville, Christy Prater | N19: bharville@gbp.com, cprater@gbp.com | P19: JG-N | Q19: 3000 | S19: Engage Management | T19: Table | U19: 1000 | V19: BL
A20: UCA | B20: Table | C20: 1000 | D20: 500 | E20: LH | F20: 12.11.24 | I20: 9/15/25 GB | L20: Amy Whitehead, Mary Lackie | N20: amyw@uca.edu; mlackie@uca.edu | P20: JG-O | S20: Fair & Company CPAs | T20: Ticket | U20: 125
A21: Conway Corp. | B21: Table | C21: 1000 | D21: 1000 | E21: BL | F21: 12.12.24 | H21: YES | J21: 3.24.25 | K21: 1000 | L21: Crystal Kemp | N21: Crystal.Kemp@conwaycorp.com | P21: LC | Q21: 1000 | S21: First Community Bank | T21: Table | U21: 1000 | V21: BL
A22: Conway Regional | B22: Table | C22: 1000 | D22: 1000 | E22: BL | F22: 12.30.24 | I22: 9/15/25 GB | J22: 45924 | K22: 1000 | L22: Rebekah Fincher | N22: rfincher@conwayregional.org | P22: LC-N | Q22: 1000 | S22: First Security Bank | T22: Table | U22: 1000 | V22: BL
A23: Rogers Group | B23: Table | C23: 1000 | D23: 1000 | E23: BL | F23: 1.3.25 | I23: 9/15/25 GB | J23: 45947 | K23: 1000 | L23: Mike Connelly | N23: mike.connelly@rogersgroupinc.com | P23: LC-O | S23: GARVER | T23: Presenting | U23: 2975 | V23: JG
A24: Simmons Bank | B24: Table | C24: 1000 | D24: 1000 | E24: BL | F24: 1.2.25 | I24: 9/15/25 GB | J24: 45919 | K24: 1000 | L24: Justin McCarty | N24: justin.mccarty@simmonsbank.com | P24: LH | Q24: 4000 | S24: Green Bay Packaging | T24: Table | U24: 1000 | V24: BL
A25: Acxiom | B25: Table | C25: 1000 | D25: 1000 | E25: BL | F25: 1.8.25 | I25: 9/15/25 GB | J25: 45932 | K25: 1000 | L25: Crystal Floyd, Alison Cowles | N25: Crystal.Floyd@acxiom.com; Alison.Cowles@acxiom.com | P25: LH-N | S25: H+N Architects | T25: Presenting | U25: 2500 | V25: LH
A26: Conductor | B26: Table | C26: 1000 | D26: 1000 | E26: LH | F26: 1.13.25 | I26: 9/15/25 GB | L26: Grace Rains | N26: grace@arconductor.org | P26: LH-O | S26: Hampton Inn and Suites | T26: Table | U26: 1000 | V26: JE-N
A27: Engage Management | B27: Table | C27: 1000 | D27: 1000 | E27: BL | F27: 2.2.25 | I27: 9/15/25 GB | J27: 45951 | K27: 1000 | L27: Morgan Lefler | N27: morgan.lefler@engagemanagement.com | P27: (blank) | Q27: 5200 | S27: Nabholz | T27: Table | U27: 1000 | V27: BL
A28: Nabholz | B28: Table | C28: 1000 | D28: 1000 | E28: BL | F28: 2.2.25 | I28: 9/15/25 GB | J28: 45919 | K28: 1000 | L28: Jake Nabholz | N28: jake.nabholz@nabholz.com | P28: TOTAL | Q28: 40700 | S28: Natural State Consulting and Strategies | T28: Table | U28: 800 | V28: JG-N
A29: Arvest | B29: Table | C29: 1000 | D29: 1000 | E29: BL-N | F29: 2.4.25 | H29: YES | J29: 4.28.25 | K29: 1000 | L29: Brooks Davis, Maret Cahill Wicks | N29: mcahillwicks@arvest.com; bdavis3@arvest.com | S29: Ott Insurance | T29: Table | U29: 1000 | V29: LC
A30: Ott Insurance | B30: Table | C30: 1000 | D30: 1000 | E30: LC | F30: 2.7.25 | I30: 9/15/25 GB | J30: 45933 | K30: 1000 | L30: Michelle Mallett | N30: michellemallett@ottinsurance.com | S30: PCSI | T30: Table | U30: 1000 | V30: LC
A31: First Security Bank | B31: Table | C31: 1000 | D31: 1000 | E31: BL | F31: 3.19.25 | I31: 9/15/25 GB | J31: 45925 | K31: 1000 | L31: Stefanie Vann | N31: stefanie.vann@fsbank.com | S31: Rogers Group | T31: Table | U31: 1000 | V31: BL
A32: Cross Creek Sandwich Shop | B32: Table | C32: 1000 | D32: DROP | E32: LC-N | F32: 4.28.25 | I32: 9/15/25 GB | K32: 0 | L32: Caitlin Bailey | N32: crosscreekcaitlin@gmail.com | S32: Simmons Bank | T32: Table | U32: 1000 | V32: BL
A33: Centennial Bank | B33: Table | C33: 1000 | D33: 1000 | E33: BL-N | F33: 9.14.25 | I33: 9/15/25 GB | J33: 45919 | K33: 1000 | L33: Scott Schwartz | N33: dschwartz@my100bank.com | S33: State Farm Insurance, Jay Bernard | T33: Speaker | U33: 2500 | V33: BL
A34: Kindred Mercantile | B34: Tickets | C34: 80 | D34: 80 | J34: 45922 | K34: 80 | S34: Turbare | T34: Table | U34: 1000 | V34: BL-N
A35: Fair & Company | B35: Tickets | C35: 80 | D35: 120 | F35: 9.24.25 | G35: 3 tickets | J35: 9.24.25 | K35: 120 | S35: UCA | T35: Table | U35: 1000 | V35: LH-N
K36: =SUM(K9:K35) -> 30700
E300: BL-O
E301: BL-N
E302: BL
E303: CP-O
E304: CP-N
E305: CP
E306: JG-O
E307: JG-N
E308: JG
E309: JE-O
E310: JE-N
E311: JE
... E317: LH

Sheet CEO Luncheons
A1: CEO LUNCHEONS | B1: 2025 | S1: CEO LUNCHEONS | T1: 2024
A2: Total Sponsorship Amount Sold | B2: =SUM(D9:D89) -> 23840 | G2: Add Tim Donar (tdonar@me.com) for 1 ticket at each 2026 CEO Luncheon. | K2: OUTSTANDING | S2: Total Sponsorship Amount Sold | T2: =SUM(V9:V51) -> 20275
A3: Budget Goal | B3: 18000 | K3: =SUM(K94-B2) -> -2510 | S3: Budget Goal | T3: 15500
A4: Remaining Balance | B4: =MIN(B2-B3) -> 5840 | K4: =K94/B2 -> 0.89471477 | S4: Remaining Balance | T4: =MIN(T2-T3) -> 4775
A5: Stretch Goal | B5: 23000 | S5: Stretch Goal | T5: 20000
A6: Remaining Balance | B6: =MIN(B2-B5) -> 840 | S6: Remaining Balance | T6: =MIN(T2-T5) -> 275
A8: SPONSOR NAME | B8: SPONSORSHIP | C8: COST | D8: PRICE PLEDGED | E8: SOLD BY | F8: DATE SOLD | G8: NOTES | H8: SPECIAL BILLING | I8: INVOICED | J8: DATE PAID | K8: PAID AMOUNT | L8: CONTACT | M8: PHONE | N8: EMAIL | P8: SOLD BY | Q8: PLEDGED | S8: SPONSOR NAME | T8: SPONSORSHIP | U8: COST | V8: PRICE PLEDGED | W8: SOLD BY
A9: Nabholz | B9: Title | C9: 10000 | D9: 10000 | E9: BL | F9: 12.17.24 | J9: 3.11.25 | K9: 10000 | L9: Jake Nabholz | N9: jake.nabholz@nabholz.com | P9: BL | Q9: 10000 | S9: American Heart Association | T9: Table | U9: 200 | V9: 200 | W9: JE-N
A10: Gratus Wealth Management Northwestern Mutual | B10: Presenting | C10: 7500 | D10: 6000 | E10: LH | F10: 12.17.24 | H10: YES | J10: 3.20.25, 8/18/25 | K10: =1200+3600 -> 4800 | L10: Osmar Garcia, Gilberto Garcia, Miranda Hogg | N10: osmar.a.garcia@nm.com; miranda.hogg@nm.com; gilberto.garcia@nm.com | P10: BL-N | S10: Arkansas Aerial Media | T10: Ticket | U10: 30 | V10: 90
J11: 5.6.25 | K11: 1200 | P11: BL-O | S11: Arkansas Med | T11: Executive Pass | U11: 100 | V11: 25
A12: Central Baptist College | B12: Host | C12: 15960 | D12: 0 | E12: LH | F12: 1.28.25 | G12: in-kind (see shared drive for breakdown) | L12: Jessica Faulkner, Terry Kimbrow, Jeremy Langley | N12: jfaulkner@cbc.edu; tkimbrow@cbc.edu; JLangley@cbc.edu | P12: CP | S12: B&A Property Maintenance | T12: Ticket | U12: 30 | V12: 25
A13: NA | B13: Speaker #1 | C13: 1500 | P13: CP-N | Q13: 0 | S13: Bank OZK | T13: Ticket | U13: 30 | V13: 30
A14: Coldwell Banker RPM: Velda Lueders | B14: Speaker #2 | C14: 1500 | D14: 1500 | E14: LH-N | F14: 2.5.25 | J14: 7.16.25 | K14: 1500 | L14: Velda Lueders | N14: velda@veldalueders.com | P14: CP-O | S14: Central Baptist College | T14: Host | U14: 14560 | V14: 0 | W14: LH
A15: Coldwell Banker RPM: Velda Lueders | B15: Speaker #3 | C15: 1500 | D15: 1500 | E15: LH-N | F15: 2.5.25 | J15: 7.16.25 | K15: 1500 | L15: Velda Lueders | N15: velda@veldalueders.com | P15: JE | S15: Coldwell Banker RPM: Velda Lueders | T15: Speaker #3 | U15: 1500 | V15: 1500 | W15: LH-N
A16: Coldwell Banker RPM: Velda Lueders | B16: Speaker #4 | C16: 1500 | D16: 1500 | E16: LH-N | F16: 2.5.25 | J16: 7.16.25 | K16: 1500 | L16: Velda Lueders | N16: velda@veldalueders.com | P16: JE-N | Q16: 800 | S16: Coldwell Banker RPM: Velda Lueders | T16: Speaker #4 | U16: 1500 | V16: 1500 | W16: LH-N
P17: JE-O | S17: Conway Regional | T17: Executive Pass | U17: 100 | V17: 0 | W17: BL-N
P18: JG | S18: DKM | T18: Ticket | U18: 30 | V18: 0 | W18: CP-N
A19: CEO LUNCHEON #1 - INDIVIDUAL TICKETS | P19: JG-N | S19: Ed Allen | T19: Ticket | U19: 30 | V19: 20 | W19: LC-N
A20: Farris Agency | B20: Table | C20: 200 | D20: 200 | E20: JE-N | F20: 12.4.24 | K20: 200 | L20: Alan White, Travis Mulhearn, Christina Horn | N20: alan@farrisagency.com travis@farrisagency.com christina@farrisagency.com | P20: JG-O | S20: Edward Jones, Chris Masters | T20: Ticket | U20: 30 | V20: 25
A21: Independent Living Services | B21: Ticket | C21: 30 | D21: 120 | K21: 120 | P21: LC | Q21: 120 | S21: Edward Jones, Matthew Carpenter | T21: Ticket | U21: 30 | V21: 50
A22: Arkansas Medicare Resource Center | B22: Ticket | C22: 30 | D22: 30 | K22: 30 | P22: LC-N | Q22: 30 | S22: Edward Jones, Stacey Alston | T22: Ticket | U22: 30 | V22: 25
A23: Merrill Lynch Wealth Management | B23: Ticket | C23: 30 | D23: 30 | K23: 30 | P23: LC-O | S23: Exchange Capital | T23: Ticket | U23: 30 | V23: 50 | W23: JE-N
A24: Renewal ranch | B24: Ticket | C24: 30 | D24: 90 | K24: 90 | P24: LH | Q24: 6000 | S24: Fair & Company | T24: Ticket | U24: 30 | V24: 200 | W24: LC-N
A25: Faulkner County Democratic Party | B25: Ticket | C25: 30 | D25: 60 | K25: 60 | P25: LH-N | Q25: 4530 | S25: Faulkner County Title | T25: Ticket | U25: 30 | V25: 50 | W25: LC-N
A26: Cadron Creek Play | B26: Ticket | C26: 30 | D26: 60 | K26: 60 | P26: LH-O | S26: First National Title | T26: Ticket | U26: 30 | V26: 100 | W26: LC-N
A27: Creative Institute | B27: Ticket | C27: 30 | D27: 30 | J27: 1.23.25 | K27: 30 | P27: (blank) | Q27: 2360 | S27: First Security Bank | T27: Ticket | U27: 30 | V27: 120
A28: First Security | B28: Table | C28: 200 | D28: 60 | K28: 60 | P28: TOTAL | Q28: 23840 | S28: Garcia Wealth Management | T28: Presenting | U28: 7500 | V28: 6000 | W28: LH
A29: Arkansas Federal Credit Union | B29: Table | C29: 200 | D29: 120 | K29: 120 | S29: House Doctor | T29: Ticket | U29: 30 | V29: 0 | W29: JE-N
A30: Scott Trafford, McDonald Companies | B30: Ticket | C30: 30 | D30: 30 | E30: LH-N | F30: 6.11.25 | K30: 30 | L30: Lindsay Immel | N30: lindsay.immel@cmmcdonald.com | S30: In Sync Counseling | T30: Ticket | U30: 30 | V30: 90 | W30: JE-N
S31: Merrill Lynch Management | T31: Ticket | U31: 30 | V31: 25 | W31: LC-N
A32: CEO LUNCHEON #2 - INDIVIDUAL TICKETS | S32: MSC Eye Associates | T32: Ticket | U32: 30 | V32: 25
A33: Farris Agency | B33: Table | C33: 200 | D33: 200 | E33: JE-N | F33: 12.4.24 | K33: 0 | L33: Alan White, Travis Mulhearn, Christina Horn | N33: alan@farrisagency.com travis@farrisagency.com christina@farrisagency.com | S33: Nabholz | T33: Title | U33: 10000 | V33: 10000 | W33: BL
A34: Clayton Conway | B34: Ticket | C34: 30 | D34: 0 | E34: CP-N | F34: 3.10.25 | G34: 2 tickets, All communications – Jamar Murchison – jamar.murchison@claytonhomes.com All communications – Stephanie Amerson – stephanie.amerson@claytonhomes.com Billing – Jake Turpin – jake.turpin@claytonhomes.com | H34: 91 | L34: Jake Turprin | N34: jake.turpin@claytonhomes.com | S34: PI Roofing | T34: Ticket | U34: 30 | V34: 25
B35: Ticket | C35: 30 | S35: Senator Mark Johnson | T35: Ticket | U35: 30 | V35: 25
A36: Window Depot | B36: Ticket | C36: 30 | D36: 30 | E36: LC-N | F36: 4.21.25 | J36: April | K36: 30 | L36: Zack Venable, Karen | N36: zack@windowdepotar.com; office.windowdepotar@gmail.com | S36: Tipton Hurst | T36: Ticket | U36: 30 | V36: 25
A37: Kindred Mercantile | B37: Ticket | C37: 30 | D37: 60 | J37: April | K37: 60 | S37: Tipton Hurst | T37: Ticket | U37: 30 | V37: 25
A38: Cadron Creek Play | B38: Ticket | C38: 30 | D38: 60 | K38: 60 | S38: Windown Depot | T38: Ticket | U38: 30 | V38: 25 | W38: JE-N
A39: New Life Church | B39: Ticket | C39: 30 | D39: 30 | J39: 3.20.25 | K39: 30
A40: B&B Safety Training | B40: Ticket | C40: 30 | D40: 30 | J40: April | K40: 30
B41: Ticket | C41: 30
A42: Arkansas Aerial Media | B42: Ticket | C42: 30 | D42: 30 | K42: 30
A43: Staffmark | B43: Ticket | C43: 30 | D43: 30 | K43: 30
A44: The Studio Downtown | B44: Ticket | C44: 30 | D44: 30 | K44: 30
A45: Temporary Wall Systems | B45: Ticket | C45: 30 | D45: 30
A46: Penmac Staffing | B46: Ticket | C46: 30 | D46: 30 | K46: 30
A47: Blackbelt Media | B47: Ticket | C47: 30 | D47: 90 | K47: 90
A48: Exchange Capital | B48: Ticket | C48: 30 | D48: 60 | K48: 60
A49: Fair & Company | B49: Ticket | C49: 30 | D49: 120 | E49: LC | J49: 6.5.25 | K49: 120
A50: Riggs Cat | B50: Ticket | C50: 30 | D50: 60 | K50: 60
A51: Ensono | B51: Ticket | C51: 30 | D51: 60 | K51: 60
A52: Terry Fiddler | B52: Ticket | C52: 30 | D52: 30 | K52: 30
A53: Cuerden Sign | B53: Ticket | C53: 120 | D53: 120 | K53: 120
A54: Bill Adkisson | B54: Ticket | C54: 30 | D54: 30 | K54: 30
A55: Kirk Netherton | B55: Ticket | C55: 30 | D55: 30 | K55: 30
A56: Malys Entertainment | B56: Ticket | C56: 30 | D56: 30 | K56: 30
A57: Arkansas Federal Credit Union | B57: Ticket | C57: 30 | D57: 120 | K57: 120
A60: CEO LUNCHEON #3 - INDIVIDUAL TICKETS
A61: Farris Agency | B61: Table | C61: 200 | D61: 200 | E61: JE-N | F61: 12.4.24 | J61: 45873 | K61: 200 | L61: Alan White, Travis Mulhearn, Christina Horn | N61: alan@farrisagency.com travis@farrisagency.com christina@farrisagency.com
A62: Clayton Conway | B62: Ticket | C62: 30 | D62: 0 | E62: CP-N | F62: 3.10.25 | G62: 2 tickets, All communications – Jamar Murchison – jamar.murchison@claytonhomes.com All communications – Stephanie Amerson – stephanie.amerson@claytonhomes.com Billing – Jake Turpin – jake.turpin@claytonhomes.com | L62: Jake Turprin | N62: jake.turpin@claytonhomes.com
A63: Arkansas Single Parent Scholarship | B63: Ticket | C63: 30 | D63: 60 | J63: Onsite | K63: 60
A64: Arkansas Aerial Media | B64: Ticket | C64: 30 | D64: 30 | J64: Onsite | K64: 30
A65: Exchange Capital | B65: Ticket | C65: 30 | D65: 60 | J65: Onsite | K65: 60
A66: Terry Kimbrow | B66: Ticket | C66: 30 | D66: 0 | J66: Onsite
A67: Edward Jones | B67: Table | C67: 200 | D67: 0 | J67: Onsite
A68: Zee Barfoot CPA | B68: Table | C68: 200 | D68: 60 | J68: Onsite | K68: 60
A71: CEO LUNCHEON #4 - INDIVIDUAL TICKETS
A72: Farris Agency | B72: Table | C72: 200 | D72: 200 | E72: JE-N | F72: 12.4.24 | L72: Alan White, Travis Mulhearn, Christina Horn | N72: alan@farrisagency.com travis@farrisagency.com christina@farrisagency.com
A73: Clayton Conway | B73: Ticket | C73: 30 | D73: 0 | E73: CP-N | F73: 3.10.25 | G73: 2 tickets, All communications – Jamar Murchison – jamar.murchison@claytonhomes.com All communications – Stephanie Amerson – stephanie.amerson@claytonhomes.com Billing – Jake Turpin – jake.turpin@claytonhomes.com | L73: Jake Turprin | N73: jake.turpin@claytonhomes.com
A74: Arkansas Aerial Media | B74: Ticket | C74: 30 | D74: 30
A75: Zee Barfoot CPA | B75: Ticket | C75: 30 | D75: 60
A76: Temporary Wall Systems | B76: Ticket | C76: 30 | D76: 30
A77: Penmac Staffing | B77: Ticket | C77: 30 | D77: 30
A78: Luke Irvin | B78: Ticket | C78: 30 | D78: 30
A79: Home2 Suites by Hilton | B79: Ticket | C79: 30 | D79: 30
A80: Hart Construction | B80: Table | C80: 200 | D80: 30
A81: Attorney's Title Group | B81: Table | C81: 200 | D81: 60
A82: Level Up Accounting | B82: Ticket | C82: 30 | D82: 30
A83: Arkansas Manufactured Housing Association | B83: Ticket | C83: 30 | D83: 200
A84: Exchange Capital | B84: Ticket | C84: 30 | D84: 60
A85: Wendy Francis | B85: Ticket | C85: 30 | D85: 0
A86: Shannan Knudsen | B86: Ticket | C86: 30 | D86: 0
K94: =SUM(K9:K31) -> 21330
E300: BL-O
E301: BL-N
E302: BL
E303: CP-O
E304: CP-N
E305: CP
E306: JG-O
E307: JG-N
E308: JG
E309: JE-O
E310: JE-N
E311: JE
... E317: LH

Sheet Conway+
A1: CONWAY+ | B1: 2025 | S1: CONWAY+ | T1: 2024
A2: Total Sponsorship Amount Sold | B2: =SUM(D9:D89) -> 101165 | K2: OUTSTANDING | S2: Total Sponsorship Amount Sold | T2: =SUM(U9:U84) -> 112720
A3: Budget Goal | B3: 130000 | K3: =SUM(K65-B2) -> -17160 | S3: Budget Goal | T3: 135000
A4: Remaining Balance | B4: =MIN(B2-B3) -> -28835 | K4: =K65/B2 -> 0.83037612 | S4: Remaining Balance | T4: =MIN(T2-T3) -> -22280
A5: Stretch Goal | B5: 130000 | S5: Stretch Goal | T5: 165000
A6: Remaining Balance | B6: =MIN(B2-B5) -> -28835 | S6: Remaining Balance | T6: =MIN(T2-T5) -> -52280
A8: SPONSOR NAME | B8: SPONSORSHIP | C8: COST | D8: PRICE PLEDGED | E8: SOLD BY | F8: DATE SOLD | G8: NOTES | H8: SPECIAL BILLING | I8: INVOICED | J8: DATE PAID | K8: PAID AMOUNT | L8: CONTACT | M8: PHONE | N8: EMAIL | P8: SOLD BY | Q8: PLEDGED | S8: SPONSOR NAME | T8: SPONSORSHIP | U8: PRICE PLEDGED | V8: SOLD BY
A9: Anonymous | B9: Gift | C9: 0 | D9: 16850 | E9: LH | F9: 4.7.25 | H9: YES | I9: 0 | J9: 5.27.25 | K9: 16850 | P9: BL | Q9: 35625 | S9: 13th Barber Co. | T9: 1/2 Page Vertical/Horizontal | U9: 1495 | V9: BL-N
A10: Anonymous | B10: Gift | C10: 0 | D10: 500 | E10: LH | F10: 7.1.25 | I10: 0 | P10: BL-N | Q10: 3000 | S10: AFCU | T10: 1/2 Page Vertical/Horizontal | U10: 1495 | V10: LH
A11: Coldwell Banker RPM | B11: Meet Your Neighbor | C11: 6000 | D11: 6250 | E11: JG | F11: 5.30.25 | I11: 8/18/25 GB | J11: 45999 | K11: 6250 | L11: Lindsay Hammers | N11: lhammers@cbrpm.com | P11: BL-O | S11: Aramark | T11: 1/2 Page Vertical/Horizontal | U11: 1495 | V11: LH
A12: Cherokee Casino and Hotel Roland | B12: Center Spread | C12: 3995 | D12: 1500 | E12: LH | F12: 5.14.25 | I12: 8/18/25 GB | J12: 45958 | K12: 1500 | L12: Hayley Bell, Teesha Richardson, Samantha Fourkiller | N12: hayley.bell@cnent.com; TEESHA.RICHARDSON@CNENT.COM;SAMANTHA.FOURKILLER@CNENT.COM | P12: CP | S12: Arkansas Game & Fish | T12: Full Page | U12: 2295 | V12: JG
A13: Conway Regional | B13: Back Cover | C13: 3495 | D13: 3000 | E13: BL | F13: 12.30.24 | I13: 8/18/25 GB | J13: 45918 | K13: 3000 | L13: Rebekah Fincher | N13: rfincher@conwayregional.org | P13: CP-N | Q13: 0 | S13: Arkansas Spine and Pain | T13: 1/2 Page Vertical/Horizontal | U13: 1500 | V13: JE-N
A14: Crain Team | B14: General Spread | C14: 3495 | D14: 3495 | E14: BL | F14: 1.7.25 | I14: 8/18/25 GB | J14: 45902 | K14: 3495 | L14: Drew Dees, Christian Crain, Cameron Burdess, Justin Kervin | M14: Cameron: 501-339-1492 Justin: 501-687-3945 | N14: ddees@ltdconnect.com; christiancrain@crainteam.net; cameronburdess@crainteam.net; justinkervin@crainteam.net | P14: CP-O | S14: Arvest | T14: 1/2 Page Vertical/Horizontal | U14: 1495 | V14: BL
A15: Trinity Development | B15: General Spread | C15: 3495 | D15: 2990 | E15: LH-O | F15: 2.26.25 | I15: 8/18/25 GB | J15: 45894 | K15: 2990 | L15: Courtnie Pledger | N15: cpledger@trinitydevelopmentinc.com | P15: JE | Q15: 1500 | S15: Baptist Health Conway | T15: Full Page (facing inside front cover) | U15: 2495 | V15: JG
A16: Bell & Sward | B16: General Spread | C16: 3495 | D16: 3000 | E16: BL-N | F16: 7.18.25 | G16: 2-page spread | H16: YES | J16: 45968 | K16: 300 | L16: Erik Sward | N16: erik@bellandsward.com | P16: JE-N | Q16: 3145 | S16: Bell & Sward | T16: Full Page | U16: 2295 | V16: BL
B17: General Spread | C17: 3495 | P17: JE-O | S17: Bledsoe Chiropractic | T17: 1/2 Page Vertical/Horizontal | U17: 1495 | V17: LC
A18: Braswell & Son | B18: Inside Front Cover | C18: 2495 | D18: 2495 | E18: BL | F18: 2.28.25 | I18: 8/18/25 GB | J18: 46006 | K18: 2495 | L18: Douglas Braswell | N18: douglas@braswellandson.com | P18: JG | Q18: 10315 | S18: Braswell & Son | T18: Inside Front Cover | U18: 2495 | V18: BL
A19: Baptist Health | B19: Full Page (facing inside front cover) | C19: 2495 | D19: 2000 | E19: JG | F19: 1.13.25 | I19: 8/18/25 GB | J19: 45929 | K19: 2000 | L19: April Bennett | P19: JG-N | Q19: 2000 | S19: Centennial Bank | T19: Full Page | U19: 2295 | V19: BL
A20: Ott Insurance | B20: Full Page (facing Table of Contents) | C20: 2495 | D20: 2495 | E20: LC-N | F20: 5.30.25 | I20: 8/18/25 GB | J20: 45933 | K20: 2495 | L20: Michelle Mallett | N20: michellemallett@ottinsurance.com | P20: JG-O | S20: Cherokee Casino & Hotel Roland | T20: Center Spread | U20: 3000 | V20: LH
A21: First Security Bank | B21: Inside Back Cover + Full Page Advertorial | C21: 2495 | D21: 3990 | E21: BL | F21: 3.19.25 | I21: 8/18/25 GB | J21: 45898 | K21: 3990 | L21: Stefanie Vann | N21: stefanie.vann@fsbank.com | P21: LC | Q21: 5980 | S21: Chris Crain Enterprises | T21: Full Page Advertorial | U21: 3000 | V21: BL
A22: Chris Crain Enterprises | B22: Full Page Advertorial | C22: 2595 | D22: 3000 | E22: BL | F22: 11.20.24 | I22: 8/18/25 GB | J22: 45891 | K22: 3000 | L22: Brett Berry, Nita Kat Freeman | N22: brettberry@chriscraingroup.com; nitafreeman@chriscraingroup.com | P22: LC-N | Q22: 5485 | S22: Coldwell Banker RPM Group | T22: Meet Your Neighbor Section | U22: 6250 | V22: JG-N
A23: Conway Corp. | B23: Full Page Advertorial | C23: 2595 | D23: 2295 | E23: BL | F23: 12.12.24 | H23: YES | J23: 3.17.25 | K23: 2295 | L23: Beth Jimmerson | N23: Beth.Jimmerson@ConwayCorp.com | P23: LC-O | S23: Colliers | T23: Full Page | U23: 2295 | V23: BL-N
A24: Clayton Conway | B24: Full Page Advertorial | C24: 2595 | D24: 0 | E24: CP-N | F24: 3.10.25 | G24: All communications – Jamar Murchison – jamar.murchison@claytonhomes.com All communications – Stephanie Amerson – stephanie.amerson@claytonhomes.com Billing – Jake Turpin – jake.turpin@claytonhomes.com | I24: 0 | L24: Jake Turpin | N24: jake.turpin@claytonhomes.com | P24: LH | Q24: 29125 | S24: Conway Corporation | T24: Full Page Advertorial | U24: 2295 | V24: BL
B25: Full Page Advertorial | C25: 2595 | P25: LH-N | S25: Conway Hospitality/Holiday Inn Express & Suites | T25: Full Page | U25: 1800 | V25: JG-N
A26: Arkansas Game & Fish Commission | B26: Full Page | C26: 2295 | D26: 2065 | E26: JG | F26: 1.7.25 | I26: 8/21/25 GB | J26: 45926 | K26: 2065 | L26: Spencer Griffith | N26: spencer.griffith@agfc.ar.gov | P26: LH-O | Q26: 2990 | S26: Conway Regional | T26: Back Cover | U26: 3000 | V26: BL
A27: Conway Wealth Management | B27: Full Page | C27: 2295 | D27: 2295 | E27: BL | F27: 3.5.25 | H27: YES | J27: 10/27/2025, 11/24/25 | K27: =525+885 -> 1410 | L27: Greg Pillow, Rita Stapleton | N27: rita@conwaywm.com; greg@conwaywm.com | P27: (blank) | Q27: 2000 | S27: Conway Wealth Management | T27: Full Page | U27: 2295 | V27: BL
A28: Melvin's Painting | B28: Full Page | C28: 2295 | D28: 2000 | E28: LH | F28: 5.2.25 | G28: Melvin has a credit of $505. Please apply to this invoice and pull the $505 from the blueprint. | H28: YES | L28: Melvin Gonzalez | M28: 501.514.2570 | P28: TOTAL | Q28: 101165 | S28: Covington Companies | T28: 1/2 Page Vertical/Horizontal | U28: 1495 | V28: BL
A29: Stoby's | B29: Full Page | C29: 2295 | D29: 2295 | E29: LH | F29: 6.17.25 | I29: 8/21/25 GB | L29: Patti Stobaugh | S29: Crain Team | T29: General Spread | U29: 3495 | V29: BL-N
A30: Monarch Dental | B30: Full Page | C30: 2295 | D30: 1650 | E30: JE-N | F30: 7.28.25 | I30: 8/21/25 GB | J30: 45950 | K30: 1650 | L30: Elizabeth Bondoc; Amber Wyatt | N30: elizabeth.bondoc@smilebrands.com; amber.wyatt@smilebrands.com | S30: Crosscreek Sandwich Shop | T30: 1/2 Page Vertical/Horizontal | U30: 1495 | V30: LC-N
A31: Centennial Bank | B31: Full Page | C31: 2295 | D31: 2295 | E31: BL | F31: 7.29.25 | G31: Family feature: John Scherrey and family | I31: 8/21/25 GB | J31: 46002 | K31: 2295 | L31: John Scherrey | N31: jscherrey@my100bank.com | S31: Diamond State Restoration | T31: 1/2 Page Vertical/Horizontal | U31: 1495 | V31: LC
A32: Visit Conway | B32: Full Page | C32: 2295 | D32: 2000 | F32: 8.18.25 | I32: 0 | L32: Rachel Shaw | S32: Engage Management | T32: 1/2 Page Vertical/Horizontal | U32: 1495 | V32: BL
A33: Colliers | B33: Full Page | C33: 2295 | D33: 2295 | E33: BL | F33: 9.29.25 | G33: TJ Johnston will be the feature family. Invoice Amy Meins after 1/1/26 | H33: YES | L33: Amy Meins, TJ Johnson | N33: Amy.Meins@ar.colliers.com; tj.johnston@ar.colliers.com | S33: Farris Agency | T33: 1/2 Page Vertical/Horizontal | U33: 1500 | V33: JE-N
B34: Full Page | C34: 2295 | S34: First Arkansas Bank & Trust | T34: 1/2 Page Vertical/Horizontal | U34: 1495 | V34: LH
B35: Full Page | C35: 2295 | S35: First Community Bank | T35: Full Page | U35: 2295 | V35: BL
A36: Farris Agency | B36: 1/2 Page Vertical/Horizontal | C36: 1495 | D36: 1500 | E36: JE | F36: 12.4.24 | I36: 8/21/25 GB | J36: 45898 | K36: 1500 | L36: Alan White, Travis Mulhearn, Christina Horn | N36: alan@farrisagency.com travis@farrisagency.com christina@farrisagency.com | S36: First Security Bank | T36: Inside Back Cover + Full Page Advertorial | U36: 3990 | V36: BL
A37: First Arkansas Bank & Trust | B37: 1/2 Page Vertical/Horizontal | C37: 1495 | D37: 1495 | E37: LH | F37: 12.9.24 | H37: YES | J37: 1.31.25 | K37: 1495 | L37: John Simmons, Roger Sundermeier, Mark Wilson, Jessica Pint | N37: jsimmons@fabandt.bank; rsundermeier@fabandt.bank; mwilson@fabandt.bank; jpint@fabandt.bank | S37: HD Roofing | T37: 1/2 Page Vertical/Horizontal | U37: 1495 | V37: LC
A38: Simmons Bank | B38: 1/2 Page Vertical/Horizontal | C38: 1495 | D38: 1495 | E38: BL | F38: 1.2.25 | I38: 8/21/25 GB | J38: 45918 | K38: 1495 | L38: Justin McCarty | N38: justin.mccarty@simmonsbank.com | S38: Home2/Hilton Garden Inn | T38: 1/3 Page Vertical/Horizontal | U38: 1000 | V38: JE-N
A39: Smith Ford | B39: 1/2 Page Vertical/Horizontal | C39: 1495 | D39: 1495 | E39: BL | F39: 2.1.25 | I39: 8/21/25 GB | J39: 45995 | K39: 1495 | L39: Cate McConnell | N39: cate.mcconnell@smithford.com | S39: Leah Brown | T39: 1/2 Page Vertical/Horizontal | U39: 1495 | V39: LC
A40: Engage Management | B40: 1/2 Page Vertical/Horizontal | C40: 1495 | D40: 1495 | E40: BL | F40: 2.2.25 | I40: 8/21/25 GB | J40: 45951 | K40: 1495 | L40: Morgan Lefler | N40: morgan.lefler@engagemanagement.com | S40: Legends Resort & Casino | T40: Full Page (facing Table of Contents) | U40: 2000 | V40: LH
A41: Arvest | B41: 1/2 Page Vertical/Horizontal | C41: 1495 | D41: 0 | E41: BL | F41: 2.4.25 | I41: 0 | L41: Brooks Davis, Maret Cahill Wicks, Brooke Hamilton | N41: mcahillwicks@arvest.com; bdavis3@arvest.com; bahamilton@arvest.com | S41: Lenders Title | T41: 1/2 Page Vertical/Horizontal | U41: 1500 | V41: LH
A42: RE/MAX Elite: Karen Ferguson | B42: 1/2 Page Vertical/Horizontal | C42: 1495 | D42: 1495 | E42: LC | F42: 2.4.25 | I42: 8/21/25 GB | J42: 45895 | K42: 1495 | L42: Karen Ferguson | N42: karenferguson501@gmail.com | S42: Little Rock Zoo | T42: 1/2 Page Vertical/Horizontal | U42: 1495 | V42: BL-N
A43: State Farm Jay Bernard | B43: 1/2 Page Vertical/Horizontal | C43: 1495 | D43: 1495 | E43: BL | F43: 2.28.25 | H43: YES | J43: 3.19.25 | K43: 1495 | L43: Jay Bernard | N43: jay.bernard.l8if@statefarm.com | S43: Melvin's Painting/MK Events Center | T43: Full Page | U43: 2000 | V43: LH
A44: First Community Bank | B44: 1/2 Page Vertical/Horizontal | C44: 1495 | D44: 1495 | E44: BL | F44: 3.13.25 | I44: 8/21/25 GB | J44: 45902 | K44: 1495 | L44: Lori Melton, Grant Gordy | N44: Lori.Melton@firstcommunity.net; Grant.Gordy@firstcommunity.net | S44: Ortho Arkansas | T44: Full Page Advertorial | U44: 2595 | V44: LC-N
A45: Covington Companies | B45: 1/2 Page Vertical/Horizontal | C45: 1495 | D45: 1495 | E45: BL | F45: 3.24.25 | I45: 8/21/25 GB | J45: 45896 | K45: 1495 | L45: George Covington, Savannah Brorman | N45: gcov@conwaycorp.net; savannah@covingtoncompanies.net | S45: Ott Insurance | T45: 1/2 Page Vertical/Horizontal | U45: 1495 | V45: LC-N
A46: St Joseph School | B46: 1/2 Page Vertical/Horizontal | C46: 1495 | D46: 1495 | E46: LH | F46: 5.6.25 | G46: Meet the Neighbors | I46: 8/21/25 GB | J46: 45902 | K46: 1495 | L46: Teri Breeding | N46: tbreeding@sjbulldogs.org | S46: RE/MAX Elite: Karen Ferguson | T46: 1/2 Page Vertical/Horizontal | U46: 1495 | V46: LC
A47: Leah Brown, ERA Team | B47: 1/2 Page Vertical/Horizontal | C47: 1495 | D47: 1495 | E47: LC | F47: 5.19.25 | I47: 8/21/25 GB | L47: Leah Brown | N47: leahbrownera@gmail.com | S47: RE/MAX Elite: The Emily Walter Team | T47: 1/2 Page Vertical/Horizontal | U47: 1495 | V47: LC-N
A48: NRG Insurance | B48: 1/2 Page Vertical/Horizontal | C48: 1495 | D48: 1495 | E48: LC-N | F48: 5.29.25 | I48: 8/21/25 GB | L48: Nick Rougeau | N48: nick@nrgins.com | S48: Reynolds Performance Hall /Windgate | T48: 1/2 Page Vertical/Horizontal | U48: 1495 | V48: JG-O
A49: Arkansas Federal Credit Union | B49: 1/2 Page Vertical/Horizontal | C49: 1495 | D49: 1495 | E49: LH | F49: 5.29.25 | I49: 8/21/25 GB | J49: 45902 | K49: 1495 | L49: Denise Goforth | N49: dgoforth@afcu.org | S49: Second Baptist Church | T49: Full Page | U49: 2295 | V49: BL-N
A50: UCA Athletics | B50: 1/2 Page Vertical/Horizontal | C50: 1495 | D50: 1495 | E50: LH | F50: 6.19.25 | I50: 8/21/25 GB | J50: 45898 | K50: 1495 | L50: Matt Whiting | N50: mwhiting@uca.edu | S50: Shawn Evans Agency | T50: 1/2 Page Vertical/Horizontal | U50: 1495 | V50: LC-N
A51: Harps | B51: 1/2 Page Vertical/Horizontal | C51: 1495 | D51: 1495 | E51: JE-N | F51: 8.17.25 | I51: 8/18/25 GB | J51: 45894 | K51: 1495 | L51: Sarah Thacker | N51: sthacker@harpsfood.com | S51: Simmons Bank | T51: 1/2 Page Vertical/Horizontal | U51: 1495 | V51: BL
A52: Huskey Heating and Cooling | B52: 1/2 Page Vertical/Horizontal | C52: 1495 | D52: DROP | E52: LC-N | F52: 8.19.25 | I52: 8/21/25 GB | J52: 0 | K52: 0 | L52: David Freyaldenhoven | N52: huskyhvacr@gmail.com | S52: Smith Ford | T52: 1/2 Page Vertical/Horizontal | U52: 1495 | V52: BL
A53: Whole Hog | B53: 1/2 Page Vertical/Horizontal | C53: 1495 | D53: 1495 | E53: LC | F53: 8.20.25 | I53: 8/21/25 GB | L53: Kent Justus | N53: kent@wholehogconway.com | S53: SpaAh | T53: Island | U53: 1295 | V53: LC
A54: Superior Health and Rehab | B54: 1/2 Page Vertical/Horizontal | C54: 1495 | D54: 1495 | E54: LC | F54: 8.21.25 | I54: 8/26/25 GB | J54: 45922 | K54: 1495 | L54: Vickey Kirkemier | N54: admin@superiorhrc.com | S54: St. Joseph School | T54: 1/2 Page Vertical/Horizontal | U54: 1495 | V54: LH
A55: Conway Management (Holiday Inn Express) | B55: 1/2 Page Vertical/Horizontal | C55: 1495 | D55: 2000 | E55: JG-N | F55: 8.28.25 | G55: They will receive 2, 1/2 page ads, advertising the same property in two different sections of the book with some changed up copy. | I55: 8/29/25 GB | J55: 45919 | K55: 2000 | S55: State Farm Insurance, Jay Bernard | T55: 1/2 Page Vertical/Horizontal | U55: 1495 | V55: BL
A56: Matthew Carpenter, Edward Jones | B56: 1/2 Page Vertical/Horizontal | C56: 1495 | D56: 1495 | E56: LC-N | F56: 10.3.25 | I56: 10/16/25 GB | J56: 45967 | K56: 1495 | L56: Matthew Carpenter | N56: matthew.carpenter@edwardjones.com | S56: Stoby's | T56: Full Page | U56: 2295 | V56: LH
A57: Little Rock Zoo | B57: 1/2 Page Vertical/Horizontal | C57: 1495 | D57: 1495 | E57: BL | F57: 11.26.25 | G57: Repeat what they did in last year's guide. | I57: 12/2/25 GB | J57: 45993 | K57: 1495 | L57: Joy Matlock | N57: jmatlock@littlerock.gov | S57: Superior Health & Rehab | T57: 1/2 Page Vertical/Horizontal | U57: 1495 | V57: LC
B58: 1/3 Page Vertical/Horizontal | C58: 1095 | S58: Tipton Hurst | T58: 1/2 Page Vertical/Horizontal | U58: 1495 | V58: BL
B59: 1/3 Page Vertical/Horizontal | C59: 1095 | S59: Tommy's Express | T59: 1/2 Page Vertical/Horizontal | U59: 1500 | V59: JE-N
B60: 1/3 Page Vertical/Horizontal | C60: 1095 | S60: Trinity Development | T60: General Spread | U60: 2990 | V60: LH-O
B61: 1/6 Page | C61: 895 | S61: UACCM | T61: 1/2 Page Vertical/Horizontal | U61: 1495 | V61: JG-N
B62: 1/6 Page | C62: 895 | S62: UCA Athletics | T62: Full Page | U62: 2295 | V62: LH
B63: Single Column | C63: 475 | S63: Visit Conway | T63: Full Page | U63: 2000
S64: Whole Hog | T64: 1/2 Page Vertical/Horizontal | U64: 1495 | V64: LC-N
K65: =SUM(K9:K64) -> 84005 | S65: Window Depot | T65: 1/2 Page Vertical/Horizontal | U65: 1495 | V65: LC-N
E300: BL-O
E301: BL-N
E302: BL
E303: CP-O
E304: CP-N
E305: CP
E306: JG-O
E307: JG-N
E308: JG
E309: JE-O
E310: JE-N
E311: JE
... E317: LH

Sheet Conway Area Healthcare Awards
A1: CONWAY AREA HEALTHCARE AWARDS | B1: 2025 | S1: CONWAY AREA HEALTHCARE AWARDS | T1: 2024
A2: Total Sponsorship Amount Sold | B2: =SUM(D9:D52) -> 43900 | K2: OUTSTANDING | S2: Total Sponsorship Amount Sold | T2: =SUM(U9:U31) -> 29850
A3: Budget Goal | B3: 27500 | K3: =SUM(K33-B2) -> 0 | S3: Budget Goal | T3: 26000
A4: Remaining Balance | B4: =MIN(B2-B3) -> 16400 | K4: =K33/B2 -> 1 | S4: Remaining Balance | T4: =MIN(T2-T3) -> 3850
A5: Stretch Goal | B5: 30000 | S5: Stretch Goal | T5: 37000
A6: Remaining Balance | B6: =MIN(B2-B5) -> 13900 | S6: Remaining Balance | T6: =MIN(T2-T5) -> -7150
A8: SPONSOR NAME | B8: SPONSORSHIP | C8: COST | D8: PRICE PLEDGED | E8: SOLD BY | F8: DATE SOLD | G8: NOTES | H8: SPECIAL BILLING | I8: INVOICED | J8: DATE PAID | K8: PAID AMOUNT | L8: CONTACT | M8: PHONE | N8: EMAIL | P8: SOLD BY | Q8: PLEDGED | S8: SPONSOR NAME | T8: SPONSORSHIP | U8: PRICE PLEDGED | V8: SOLD BY
A9: Cintas | B9: Title | C9: 15000 | D9: 10000 | E9: LH-N | F9: 3.14.25 | J9: 7.29.25 | K9: 10000 | L9: Mathew Hoppis | N9: HoppisM@cintas.com | P9: BL | Q9: 7700 | S9: Alzheimer's Arkansas | T9: Ticket | U9: 225
A10: First Security Bank | B10: Presenting | C10: 10000 | D10: 8000 | E10: BL-N | F10: 3.14.25 | J10: 46003 | K10: 8000 | L10: Stefanie Vann | N10: Stefanie.Vann@fsbank.com | P10: BL-N | Q10: 8000 | S10: Arkansas Blue Cross and Blue Shield | T10: Awards: Mental Health Professional of the Year | U10: 2500 | V10: BL-N
B11: Emerging Healthcare Professionals | C11: 5000 | P11: BL-O | S11: Baptist Health - Conway | T11: Table | U11: 600
A12: Stephens Insurance | B12: Keynote | C12: 5000 | D12: 5000 | E12: LH-N | F12: 5.20.25 | G12: Will introduce Adam Head | J12: 6.9.25 | K12: 5000 | L12: Tom Kane | N12: tkane@stephens.com> | P12: CP | S12: Birchtree Communities | T12: Table | U12: 600
A13: Conway Regional PHO | B13: Physician of the Year | C13: 2500 | D13: 2500 | E13: LH | F13: 6.10.25 | J13: 7.7.25 | K13: 2500 | L13: Bobby Riggs | N13: briggsjr@conwaycorp.net | P13: CP-N | S13: Bledsoe Chiropractic | T13: Table | U13: 600 | V13: LC
A14: UCA | B14: Administrator of the Year | C14: 2500 | D14: 2500 | E14: LH | F14: 12.11.24 | G14: This is what they did last year, however, if we see we need to move them to an award that makes more sense - that is fine. | J14: 6.12.25 | K14: 2500 | L14: Amy Whitehead, Mary Lackie | N14: amyw@uca.edu; mlackie@uca.edu | P14: CP-O | S14: Boston Mountain Rural Health Center | T14: Tickets | U14: 300 | V14: JE-N
A15: CARTI | B15: Healthcare Professional of the Year | C15: 2500 | D15: 2500 | E15: LC | F15: 2.12.25 | J15: 7.11.25 | K15: 2500 | L15: Carroll Jo Malloy | N15: CarrollJo.Malloy@CARTI.com | P15: JE | S15: CARTI | T15: Awards: Healthcare Professional of the Year | U15: 2500 | V15: LC
B16: Health Promotion Specialist of the Year | C16: 2500 | P16: JE-N | Q16: 3100 | S16: Chamber Prospects | T16: Table | U16: 0
A17: Little Rock/Conway Signs | B17: Nurse of the Year | C17: 2500 | D17: 2000 | E17: JG | F17: 4.30.25 | G17: Invoice Andrea@littlerockconwaysign.com | J17: 7.3.25 | K17: 2000 | L17: David Glover | N17: David@littlerockconwaysign.com | P17: JE-O | S17: Chamber Prospects | T17: Table | U17: 0
A18: Delta Dental of Arkansas | B18: Dental Professional of the Year | C18: 2500 | D18: 2500 | E18: BL | F18: 4.17.25 | J18: 6.23.25 | K18: 2500 | L18: Dave Hawsey | N18: dhawsey@deltadentalar.com | P18: JG | Q18: 2600 | S18: Cintas | T18: Awards: Community Impact | U18: 2450 | V18: LH
A19: Turbare | B19: Optical Professional of the Year | C19: 2500 | D19: 2500 | E19: BL | F19: 1.3.25 | G19: Rep participates and speaks at event | H19: YES | J19: 7.7.25, 12/17/25 | K19: =447.5+2052.5 -> 2500 | L19: Laura Martin, Andria White | N19: ceo@turbare.org; awhite@turbare.org | P19: JG-N | S19: Conway Regional | T19: Table | U19: 1200 | V19: BL
P20: JG-O | S20: Conway Regional PHO | T20: Awards: Optical Professional of the Year | U20: 2500 | V20: LH
A21: Little Creek Behavioral Health | B21: Mental Health Professional of the Year | C21: 2500 | D21: 2500 | E21: JE-N | F21: 5.19.25 | G21: Let's confirm that we can have two sponsors | J21: 6.16.25 | K21: 2500 | L21: Nedra Jones | N21: nedra.allen-jones@littlecreekbehavioral.com | P21: LC | Q21: 2500 | S21: Corco | T21: Awards: Physician of the Year | U21: 2500 | V21: BL-N
A22: Arkansas Blue Cross and Blue Shield | B22: Community Impact Award | C22: 2500 | D22: 1500 | E22: BL | F22: 3.18.25 | I22: 45749 | J22: 4.2.25 | K22: 1500 | L22: Rebecca Pittillo | N22: rapittillo@arkbluecross.com | P22: LC-N | S22: Delta Dental | T22: Awards: Dental Professional of the Year | U22: 2500 | V22: BL
A23: Conway Regional | B23: Table | C23: 600 | D23: 1200 | E23: BL | F23: 12.30.25 | J23: 6.12.25 | K23: 1200 | L23: Rebekah Fincher | N23: rfincher@conwayregional.org | P23: LC-O | S23: Faulkner County Alzheimer's | T23: Table | U23: 600
A24: Baptist Health | B24: Table | C24: 600 | D24: 600 | E24: JG | F24: 1.13.25 | J24: 45831 | K24: 600 | L24: April Bennett | P24: LH | Q24: 5000 | S24: Immerse AR | T24: Ticket | U24: 150
A25: Ridgemere Senior Living | B25: Table | C25: 600 | D25: 600 | E25: JE-N | F25: 6.11.25 | J25: 7.2.25 | K25: 600 | L25: Brandy Herrin | N25: bherrin@abbysl.com | P25: LH-N | Q25: 15000 | S25: Jan-Pro | T25: Awards: Health Promotion Specialist of the Year | U25: 2500 | V25: LC-N
B26: Table | C26: 600 | P26: LH-O | S26: Little Rock/Conway Signs | T26: Awards: Nurse of the Year | U26: 2000 | V26: JG-N
B27: Table | C27: 600 | P27: (blank) | S27: Melissa Longing | T27: Ticket | U27: 375
B28: Table | C28: 600 | P28: TOTAL | Q28: 43900 | S28: Ortho Arkansas | T28: Table | U28: 600 | V28: LC-N
B29: Table | C29: 600 | S29: Terry Kimbrow | T29: Ticket | U29: 150
B30: Table | C30: 600 | S30: Turbare | T30: Awards: Optical Professional of the Year | U30: 2500 | V30: BL
B31: Table | C31: 600 | S31: UCA | T31: Awards: Administrator of the Year | U31: 2500 | V31: LH
K33: =SUM(K9:K32) -> 43900
E300: BL-O
E301: BL-N
E302: BL
E303: CP-O
E304: CP-N
E305: CP
E306: JG-O
E307: JG-N
E308: JG
E309: JE-O
E310: JE-N
E311: JE
... E317: LH

Sheet CALI Tuition
A1: CALI TUTION | B1: 2025 | U1: CALI TUITION | V1: 2024
A2: Total Sponsorship Amount Sold | B2: =SUM(D9:D66) -> 85865 | G2: 2026 Prospects: Marcus Arnold (Summit Utilities), Joyia Yorgey (AR Asset Builders), Katie Wilson (Create Conway), Broc Hart (Thrivent) | K2: OUTSTANDING | U2: Total Sponsorship Amount Sold | V2: =SUM(X9:X59) -> 91647.5
A3: Budget Goal | B3: 92750 | K3: =SUM(K69-B2) -> -1795 | U3: Budget Goal | V3: 80775
A4: Remaining Balance | B4: =MIN(B2-B3) -> -6885 | K4: =K69/B2 -> 0.97909509 | U4: Remaining Balance | V4: =MIN(V2-V3) -> 10872.5
A5: Stretch Goal | B5: 92750 | U5: Stretch Goal | V5: 80775
A6: Remaining Balance | B6: =MIN(B2-B5) -> -6885 | U6: Remaining Balance | V6: =MIN(V2-V5) -> 10872.5
A8: SPONSOR NAME | B8: TUITION | C8: COST | D8: PRICE PLEDGED | E8: SOLD BY | F8: DATE SOLD | G8: NOTES | H8: SPECIAL BILLING | I8: INVOICED | J8: DATE PAID | K8: PAID AMOUNT | L8: CONTACT | M8: PHONE | N8: EMAIL | Q8: SOLD BY | R8: PLEDGED | U8: SPONSOR NAME | V8: TUITION | W8: COST | X8: PRICE PLEDGED | Y8: SOLD BY
A9: Acxiom | B9: Tuition | C9: 1795 | D9: 1795 | E9: Bl-N | J9: 4.3.25 | K9: 1795 | Q9: BL | U9: Acxiom | V9: Tuition | W9: 1795 | X9: 3590 | Y9: BL
A10: Acxiom | B10: Tuition | C10: 1795 | D10: 1795 | E10: Bl-N | Q10: Bl-N | R10: 41285 | U10: American Safeguard Insurance | V10: Tuition | W10: 1795 | X10: 1795 | Y10: LH-N
A11: American Safeguard Insurance | B11: Tuition | C11: 1795 | D11: 1795 | E11: LH-N | K11: 1795 | Q11: BL-O | U11: Arvest | V11: Tuition | W11: 1795 | X11: 1795 | Y11: BL-N
A12: ARcare | B12: Tuition | C12: 1795 | D12: 1795 | E12: LH-N | J12: 45891 | K12: 1795 | Q12: CP | U12: Baptist Health Conway | V12: Tuition | W12: 1795 | X12: 1795 | Y12: JG-N
A13: Arkansas Federal Credit Union | B13: Tuition | C13: 1795 | D13: 1795 | E13: LH-N | J13: 3.5.25 | K13: 1795 | Q13: CP-N | R13: 5385 | U13: Baptist Health Conway | V13: Tuition | W13: 1795 | X13: 0 | Y13: JG
A14: Arvest Bank | B14: Tuition | C14: 1795 | D14: 1795 | E14: Bl-N | H14: YES | J14: 3.31.25 | K14: 1795 | Q14: CP-O | U14: Bbsafetytraining Com | V14: Tuition | W14: 1795 | X14: 897.5
A15: Bank OZK | B15: Tuition | C15: 1795 | D15: 1795 | J15: 3.12.25 | K15: 1795 | Q15: JE | U15: Cadron Creek Play (Conway Mfg.) | V15: Tuition | W15: 1795 | X15: 1795
A16: Baptist Health Conway | B16: Tuition | C16: 1795 | D16: 1795 | E16: JG-N | J16: 3.18.25 | K16: 1795 | Q16: JE-N | R16: 1795 | U16: Centennial Bank | V16: Tuition | W16: 1795 | X16: 1795 | Y16: BL-N
A17: Blackbelt Media | B17: Tuition | C17: 1795 | D17: 0 | K17: 0 | Q17: JE-O | U17: Central Baptist College | V17: Tuition | W17: 1795 | X17: 1795 | Y17: LH-N
A18: Centennial Bank | B18: Tuition | C18: 1795 | D18: 1795 | E18: BL-N | J18: 3.7.25 | K18: 1795 | Q18: JG | U18: Chambers Bank | V18: Tuition | W18: 1795 | X18: 1795 | Y18: LC-N
A19: Chris Crain Enterprises | B19: Tuition | C19: 1795 | D19: 1795 | E19: Bl-N | J19: 45960 | K19: 1795 | Q19: JG-N | R19: 5090 | U19: Chris Crain Enterprises | V19: Tuition | W19: 1795 | X19: 1795 | Y19: BL-N
A20: City of Conway | B20: Tuition | C20: 1795 | D20: 1795 | J20: 3.28.25 | K20: 1795 | Q20: JG-O | U20: City of Conway | V20: Tuition | W20: 1795 | X20: 1795 | Y20: CP-N
A21: Conway Corp | B21: Tuition | C21: 1795 | D21: 1795 | E21: Bl-N | H21: YES | J21: 3.24.25 | K21: 1795 | Q21: LC | U21: Conway Corp. | V21: Tuition | W21: 1795 | X21: 4590 | Y21: BL
A22: Conway Corp | B22: Tuition | C22: 1795 | D22: 1795 | E22: Bl-N | H22: YES | J22: 3.24.25 | K22: 1795 | Q22: LC-N | R22: 3590 | U22: Conway Regional | V22: Tuition | W22: 1795 | X22: 1795 | Y22: BL-N
A23: Conway Regional | B23: Tuition | C23: 1795 | D23: 1795 | E23: Bl-N | J23: 4.9.25 | K23: 1795 | Q23: LC-O | U23: CPSD | V23: Tuition | W23: 1795 | X23: 3590 | Y23: CP-N
A24: Conway Regional | B24: Tuition | C24: 1795 | D24: 1795 | E24: Bl-N | J24: 4.9.25 | K24: 1795 | Q24: LH | U24: Crafton Tull | V24: Tuition | W24: 1795 | X24: 1795 | Y24: BL
A25: Conway Regional | B25: Tuition | C25: 1795 | D25: 1795 | E25: Bl-N | J25: 4.9.25 | K25: 1795 | Q25: LH-N | R25: 16155 | U25: Farris Agency | V25: Tuition | W25: 1795 | X25: 1795 | Y25: JE-N
A26: Crafton Tull | B26: Tuition | C26: 1795 | D26: 1795 | E26: Bl-N | H26: YES | J26: 45887 | K26: 1795 | Q26: LH-O | U26: First Arkansas Bank & Trust | V26: Tuition | W26: 1795 | X26: 0
A27: Dillard's | B27: Tuition | C27: 1795 | D27: 1795 | K27: 1795 | Q27: (blank) | R27: 14360 | U27: First Security Bank | V27: Tuition | W27: 1795 | X27: 1795 | Y27: BL
B28: Tuition | C28: 1795 | Q28: TOTAL | R28: 87660 | U28: Green Bay Packaging | V28: Tuition | W28: 1795 | X28: 1795 | Y28: BL-N
A29: Entergy | B29: Tuition | C29: 1795 | D29: 1795 | E29: CP-N | J29: 3.12.25 | K29: 1795 | U29: Halff Associates | V29: Tuition | W29: 1795 | X29: 1795
A30: First Arkansas Bank & Trust | B30: Tuition | C30: 1795 | D30: 0 | E30: LH-N | K30: 0 | U30: Homewell Cares | V30: Tuition | W30: 1795 | X30: 1795
A31: First Security Bank | B31: Tuition | C31: 1795 | D31: 1795 | E31: Bl-N | J31: 4.17.25 | K31: 1795 | U31: Insight | V31: Tuition | W31: 1795 | X31: 3590 | Y31: CP-N
A32: First Service Bank | B32: Tuition | C32: 1795 | D32: 1795 | E32: Bl-N | J32: 3.5.25 | K32: 1795 | U32: Integrity Insurance | V32: Tuition | W32: 1795 | X32: 5385
A33: Green Bay Packaging | B33: Tuition | C33: 1795 | D33: 1795 | E33: Bl-N | H33: YES | K33: 1795 | U33: K&K Tree Service | V33: Tuition | W33: 1795 | X33: 1795
A34: Green Bay Packaging | B34: Tuition | C34: 1795 | D34: 1795 | E34: Bl-N | H34: YES | U34: Keathly Patterson | V34: Tuition | W34: 1795 | X34: 1795 | Y34: CP-N
A35: Healing Path Counseling | B35: Tuition | C35: 1795 | D35: 1795 | K35: 1795 | U35: Leather Brothers | V35: Tuition | W35: 1795 | X35: 1795
A36: Insight | B36: Tuition | C36: 1795 | D36: 1795 | E36: CP-N | H36: YES | J36: 4.8.25 | K36: 1795 | U36: Malvern National Bank | V36: Tuition | W36: 1795 | X36: 1795 | Y36: LH-N
A37: Insight | B37: Tuition | C37: 1795 | D37: 1795 | E37: CP-N | H37: YES | K37: 1795 | U37: McClelland Consulting Engineers | V37: Tuition | W37: 1795 | X37: 1795 | Y37: JE-N
A38: KIDS ABA Services | B38: Tuition | C38: 1795 | D38: 1795 | E38: Bl-N | J38: 3.5.25 | K38: 1795 | U38: Mercer Conway | V38: Tuition | W38: 1795 | X38: 1795 | Y38: JG-N
A39: Landmark CPAs | B39: Tuition | C39: 1795 | D39: 1795 | E39: LH-N | H39: YES | J39: 6.6.25 | K39: 1795 | U39: Microsoft Corporation | V39: Tuition | W39: 1795 | X39: 1795 | Y39: CP-N
A40: Living Stone Lutheran Church | B40: Tuition | C40: 1795 | D40: 1795 | J40: 3.7.25 | K40: 1795 | U40: Moore and Co. | V40: Tuition | W40: 1795 | X40: 1795
A41: Malvern National Bank | B41: Tuition | C41: 1795 | D41: 1795 | E41: LH-N | J41: 5.27.25 | K41: 1795 | U41: Nabholz | V41: Tuition | W41: 1795 | X41: 1795 | Y41: BL-N
A42: McClelland Consulting Engineers | B42: Tuition | C42: 1795 | D42: 1795 | E42: JE-N | J42: 3.10.25 | K42: 1795 | U42: Natural State Consulting | V42: Tuition | W42: 1795 | X42: 1795 | Y42: JG-N
B43: Tuition | C43: 1795 | U43: Northwestern Mutual | V43: Tuition | W43: 1795 | X43: 1795 | Y43: LH-N
A44: Nabholz Construction | B44: Tuition | C44: 1795 | D44: 1795 | E44: Bl-N | J44: 3.11.25 | K44: 1795 | U44: Peace Luthern | V44: Tuition | W44: 1795 | X44: 1795
A45: Natural State Recovery Centers | B45: Tuition | C45: 1795 | D45: 1795 | U45: Rogers Group | V45: Tuition | W45: 1795 | X45: 1795 | Y45: BL-N
A46: New Life Church | B46: Tuition | C46: 1795 | D46: 1795 | K46: 1795 | U46: SBW Wealth Management | V46: Tuition | W46: 1795 | X46: 1795
A47: Northwestern Mutual | B47: Tuition | C47: 1795 | D47: 1795 | E47: LH-N | H47: YES | J47: 8/20/2025, 9/16/25, 10/13/25, 11/18/25, 12/18/25 | K47: =137+414.5+414.5+414.5+414.5 -> 1795 | U47: Simmons Bank | V47: Tuition | W47: 1795 | X47: 1795 | Y47: BL
A48: Ott Insurance Agency | B48: Tuition | C48: 1795 | D48: 1795 | E48: LC-N | J48: 3.10.25 | K48: 1795 | U48: Sinco | V48: Tuition | W48: 1795 | X48: 1795 | Y48: CP-N
A49: RE/MAX Elite | B49: Tuition | C49: 1795 | D49: 1795 | E49: LC-N | J49: 3.24.25 | K49: 1795 | U49: Textbook Brokers | V49: Tuition | W49: 1795 | X49: 1795
A50: Rogers Group Inc. | B50: Tuition | C50: 1795 | D50: 1795 | E50: Bl-N | J50: 4.10.25 | K50: 1795 | U50: Tokusen | V50: Tuition | W50: 1795 | X50: 3590 | Y50: JG-N
A51: Salter Construction | B51: Tuition | C51: 1795 | D51: 1795 | E51: Bl-N | J51: 46010 | K51: 1795 | U51: UCA | V51: Tuition | W51: 1795 | X51: 5385 | Y51: LH
B52: Tuition | C52: 1795 | U52: United Way | V52: Tuition | W52: 1795
A53: Simmons Bank | B53: Tuition | C53: 1795 | D53: 1795 | E53: Bl-N | J53: 3.24.25 | K53: 1795 | U53: Virco | V53: Tuition | W53: 1795 | X53: 1795 | Y53: BL
A54: Krispy Kreme | B54: Tuition | C54: 1795 | D54: 1795 | J54: 3.12.25 | K54: 1795
A55: Turbare Manufacturing | B55: Tuition | C55: 1795 | D55: 0 | E55: Bl-N | J55: 46008 | K55: 1795
A56: Turbare Manufacturing | B56: Tuition | C56: 1795 | D56: 0 | E56: Bl-N | J56: 46008 | K56: 1795
A57: University of Arkansas Pulaski Tech College | B57: Tuition | C57: 1795 | D57: 0 | K57: 0
A58: University of Central Arkansas | B58: Tuition | C58: 1795 | D58: 1795 | E58: LH-N | J58: 3.7.25 | K58: 1795
A59: University of Central Arkansas | B59: Tuition | C59: 1795 | D59: 1795 | E59: LH-N | J59: 3.7.25 | K59: 1795
A60: University of Central Arkansas | B60: Tuition | C60: 1795 | D60: 1795 | E60: LH-N | J60: 3.7.25 | K60: 1795
A61: University of Central Arkansas | B61: Tuition | C61: 1795 | D61: 0 | E61: LH-N | K61: 0
A62: Virco | B62: Tuition | C62: 1795 | D62: 1795 | E62: Bl-N | J62: 45902 | K62: 1795
A63: Virco | B63: Tuition | C63: 0 | D63: 0 | E63: Bl-N | G63: Only one participant per Corey
A64: Weaver-Bailey Contractors | B64: Tuition | C64: 1795 | D64: 1795 | E64: JG-N | J64: 3.17.25 | K64: 1795
A65: Westrock Coffee | B65: Tuition | C65: 1795 | D65: 1795 | E65: Bl-N | H65: YES | J65: 3.3.25 | K65: 1795
A66: Winthrop Rockefeller Institute | B66: Tuition | C66: 1795 | D66: 1500 | E66: JG-N | J66: 3.24.25 | K66: 1500
K69: =SUM(K9:K66) -> 84070
E298: BL-O
E299: BL-N
E300: BL
E301: CP-O
E302: CP-N
E303: CP
E304: JG-O
E305: JG-N
E306: JG
E307: JE-O
E308: JE-N
E309: JE
... E315: LH

Sheet CALI
A1: CALI | B1: 2025 | S1: CALI | T1: 2024
A2: Total Sponsorship Amount Sold | B2: =SUM(H2:H3) -> 50895 | G2: CALI Sponsorships | H2: =SUM(D9:D34) -> 43045 | K2: OUTSTANDING | S2: Total Sponsorship Amount Sold | T2: =SUM(U11:U27) -> 33500
A3: Budget Goal | B3: 46000 | G3: Graduation Tables/Tickets | H3: =SUM(D41:D61) -> 7850 | K3: =SUM(K65-B2) -> -10090 | S3: Total Graduation Table Sold | T3: =SUM(U30:U40) -> 6900
A4: Remaining Balance | B4: =MIN(B2-B3) -> 4895 | K4: =K65/B2 -> 0.8017487 | S4: Total Sponsorship + Tables | T4: =SUM(T2:T3) -> 40400
A5: Stretch Goal | B5: 46000 | S5: Budget Goal | T5: 41500
A6: Remaining Balance | B6: =MIN(B2-B5) -> 4895 | S6: Remaining Balance | T6: =SUM(T4-T5) -> -1100
S7: Stretch Goal | T7: 41500
A8: SPONSOR NAME | B8: SPONSORSHIP | C8: COST | D8: PRICE PLEDGED | E8: SOLD BY | F8: DATE SOLD | G8: NOTES | H8: SPECIAL BILLING | I8: INVOICED | J8: DATE PAID | K8: PAID AMOUNT | L8: CONTACT | M8: PHONE | N8: EMAIL | P8: SOLD BY | Q8: PLEDGED | S8: Remaining Balance | T8: =MIN(T4-T7) -> -1100
A9: First Arkansas Bank & Trust | B9: Title | C9: 20000 | D9: 15000 | E9: LH | F9: 12.9.24 | H9: YES | J9: 1.31.25 | K9: 15000 | L9: John Simmons, Roger Sundermeier, Mark Wilson, Jessica Pint | N9: jsimmons@fabandt.bank; rsundermeier@fabandt.bank; mwilson@fabandt.bank; jpint@fabandt.bank | P9: BL | Q9: 8100
A10: Turbare | B10: Presenting | C10: 5000 | D10: 6795 | E10: BL-N | F10: 1.3.25 | G10: 2 waived tuitions + various opportunities for rep to address class. Corey to work out details with sponsor | H10: YES | J10: 46008 | K10: 3205 | L10: Laura Martin, Andria White | N10: ceo@turbare.org; awhite@turbare.org | P10: BL-N | Q10: 12545 | S10: SPONSOR NAME | T10: SPONSORSHIP | U10: PRICE PLEDGED | V10: SOLD BY
A11: Insight | B11: Presenting | C11: 5000 | D11: 5000 | E11: CP-N | F11: 2.19.25 | H11: YES | K11: 5000 | L11: Steven Tyler, Jenny Vallas | N11: steven.tyler@insight.com; jenny.vallas@insight.com | P11: BL-O | S11: Central Baptist College | T11: Session Underwriter | U11: 0 | V11: LH
A12: Conway Regional | B12: Program Underwriter | C12: 3500 | D12: 2500 | E12: BL | F12: 12.30.24 | J12: 4.9.25 | K12: 2500 | L12: Rebekah Fincher | N12: rfincher@conwayregional.org | P12: CP | S12: Community Foundation | T12: Session Underwriter | U12: 1000 | V12: CP-N
A13: Winthrop Rockefeller Institute | B13: Program Underwriter | C13: 3500 | D13: 3500 | E13: JG | F13: 2.4.25 | J13: 4.28.25 | K13: 3500 | L13: Austin DuVall, Julia Dossett Morgan | N13: ADuVall@rockefellerinstitute.org; JMorgan@rockefellerinstitute.org | P13: CP-N | Q13: 7250 | S13: Conway Corporation | T13: Session Underwriter | U13: 1000 | V13: BL
B14: Program Underwriter | C14: 3500 | P14: CP-O | S14: Conway Regional | T14: Program Sponsor | U14: 2500 | V14: BL-N
A15: Green Bay Packaging | B15: Session Underwriter | C15: 1250 | D15: 1000 | E15: BL | F15: 12.3.24 | H15: YES | J15: 1.30.25 | K15: 253.75 | L15: Brad Harville, Christy Prater | N15: bharville@gbp.com, cprater@gbp.com | P15: JE | S15: Engage Management | T15: CALI Reception Venue Sponsor | U15: 0 | V15: BL
J16: 6.5.25 | K16: 746.25 | P16: JE-N | S16: First Arkansas Bank & Trust | T16: Program Underwriter | U16: 15000 | V16: LH
A17: Conway Corp. | B17: Session Underwriter | C17: 1250 | D17: 1000 | E17: BL | F17: 12.12.24 | H17: YES | J17: 3.24.25 | K17: 1000 | L17: Crystal Kemp | N17: Crystal.Kemp@conwaycorp.com | P17: JE-O | Q17: 1000 | S17: Green Bay Packaging | T17: Session Underwriter | U17: 1000 | V17: BL
A18: H+N Architects | B18: Session Underwriter | C18: 1250 | D18: 1000 | E18: LH | F18: 12.19.24 | H18: YES | J18: 4.25.25 | K18: 1000 | L18: Liz Hamilton, Joanna Nabholz | N18: liz@hnarch.com; joanna@hnarch.com | P18: JG | Q18: 3500 | S18: H+N Architects | T18: Session Underwriter | U18: 1000 | V18: LH
A19: Rogers Group | B19: Session Underwriter | C19: 1250 | D19: 1000 | E19: BL | F19: 1.3.25 | J19: 4.10.25 | K19: 1000 | L19: Mike Connelly | N19: mike.connelly@rogersgroupinc.com | P19: JG-N | S19: Klaasmeyer | T19: Session Underwriter | U19: 1000 | V19: BL
A20: Community Foundation | B20: Session Underwriter | C20: 1250 | D20: 1000 | E20: CP-N | F20: 1.22.25 | G20: Sponsoring Community Leadership session. | K20: 1000 | P20: JG-O | S20: Kutak Rock | T20: Session Underwriter | U20: 1000 | V20: BL
A21: Central Baptist College | B21: Session Underwriter | C21: 1250 | D21: 0 | E21: LH | F21: 1.28.25 | G21: in-kind for hosting/providing class lunch on campus | K21: 0 | L21: Jessica Faulkner, Terry Kimbrow, Jeremy Langley | N21: jfaulkner@cbc.edu; tkimbrow@cbc.edu; JLangley@cbc.edu | P21: LC | Q21: 1000 | S21: Nabholz | T21: Session Underwriter | U21: 1000 | V21: BL
A22: United Way | B22: Session Underwriter | C22: 1250 | D22: 1000 | E22: JE-O | F22: 1.31.25 | G22: Community Leadership Underwriter session | J22: 45999 | K22: 1000 | L22: Jessica Clawson | N22: j.clawson@uwcark.org | P22: LC-N | S22: RE/MAX Elite: The Emily Walter Team | T22: Session Underwriter | U22: 1000 | V22: LC-N
A23: Nabholz | B23: Session Underwriter | C23: 1250 | D23: 1000 | E23: BL | F23: 2.2.25 | J23: 3.11.25 | K23: 1000 | L23: Jake Nabholz | N23: jake.nabholz@nabholz.com | P23: LC-O | S23: Rogers Group | T23: Session Underwriter | U23: 1000 | V23: BL
A24: RE/MAX Elite: The Emily Walter Team | B24: Session Underwriter | C24: 1250 | D24: 1000 | E24: LC | F24: 2.7.25 | J24: 3.24.25 | K24: 1000 | L24: Emily Walter | N24: emilywalterrealtor@gmail.com | P24: LH | Q24: 16000 | S24: S7 Tactical and Gray Beard Ammo | T24: Session Underwriter: Public Safety Session | U24: 1500 | V24: JE-N
A25: Natural State Consulting | B25: Session Underwriter | C25: 1250 | D25: 1250 | E25: CP-N | F25: 2.19.25 | J25: 3.13.25 | K25: 1250 | L25: Tyler Lachowsky | N25: tylerlachowsky@naturalstatestrategies.com | P25: LH-N | S25: Sinco | T25: Session Underwriter | U25: 1000 | V25: CP-N
A26: Klaasmeyer | B26: Session Underwriter | C26: 1250 | D26: 1000 | E26: BL | F26: 4.10.25 | L26: Jessica Press | N26: jessica@klaasmeyer.com | P26: LH-O | Q26: 1500 | S26: United Way of Central Arkansas | T26: Session Underwriter | U26: 1000 | V26: CP-N
B27: Session Underwriter | C27: 1250 | P27: (blank) | S27: Winthrop Rockefeller Institute | T27: Program Sponsor | U27: 3500 | V27: JG
B28: Reception | C28: 2500 | P28: SOLD BY | Q28: 0
B29: Reception | C29: 2500 | P29: TOTAL | Q29: 50895
B30: Reception | C30: 2500 | S30: Acxiom | T30: Graduation Table | U30: 750 | V30: BL-N
B31: Hospitality | C31: 500 | S31: Chris Crain Enterprises | T31: Graduation Table | U31: 750 | V31: BL-N
B32: Hospitality | C32: 500 | S32: Conway Corporation | T32: Graduation Table | U32: 600 | V32: BL
B33: Hospitality | C33: 500 | S33: Insight | T33: Graduation Table | U33: 750 | V33: CP-N
B34: Hospitality | C34: 500 | S34: Nabholz | T34: Graduation Table | U34: 600 | V34: BL
S35: Rogers Group | T35: Graduation Table | U35: 600 | V35: BL
S36: Simmons Bank | T36: Graduation Table | U36: 750 | V36: BL-N
S37: Sinco | T37: Graduation Table | U37: 750 | V37: CP-N
S38: UCA Outreach and Conference Services | T38: Graduation Ticket | U38: 0
S39: Virco | T39: Graduation Table | U39: 600 | V39: BL
A40: SPONSOR NAME | B40: GRADUATE TABLE | C40: COST | D40: PRICE PLEDGED | E40: SOLD BY | F40: DATE SOLD | G40: NOTES | H40: SPECIAL BILLING | I40: INVOICED | J40: DATE PAID | K40: PAID AMOUNT | L40: CONTACT | M40: PHONE | N40: EMAIL | S40: Weaver Bailey | T40: Graduation Table | U40: 750 | V40: JG-N
A41: Chris Crain Enterprises | B41: Table | C41: 850 | D41: 1000 | E41: BL-N | F41: 11.20.24 | G41: Confirm with NK/BB which Chris Crain Enterprises company/companies will be featured on event. | L41: Brett Berry, Nita Kat Freeman | N41: brettberry@chriscraingroup.com; nitafreeman@chriscraingroup.com
A42: Virco | B42: Table | C42: 850 | D42: 1000 | E42: BL-N | F42: 12.2.24 | H42: YES | J42: 45908 | K42: 1000 | L42: Scotty Bell, Steve Presley | N42: scottybell@virco.com; stevepresley@virco.com
A43: Conway Corp. | B43: Table | C43: 850 | D43: 600 | E43: BL | F43: 12.12.24 | H43: YES | J43: 3.24.25 | K43: 600 | L43: Crystalk Kemp | N43: Crystal.Kemp@conwaycorp.com
A44: American Safeguard Insurance | B44: Table | C44: 850 | D44: 750 | E44: LH-O | F44: 12.23.24 | H44: YES | J44: 1.17.25 | K44: 750 | L44: Jeremy Davis, Jason Smith, Brittney Gwatney | N44: jdavis@asiagents.com; jsmith@asiagents.com; bgwatney@asiagents.com
A45: Rogers Group | B45: Table | C45: 850 | D45: 750 | E45: BL-N | F45: 1.3.25 | L45: Mike Connelly | N45: mike.connelly@rogersgroupinc.com
A46: Simmons Bank | B46: Table | C46: 850 | D46: 1000 | E46: BL-N | F46: 1.2.25 | L46: Justin McCarty | N46: justin.mccarty@simmonsbank.com
A47: Acxiom | B47: Table | C47: 850 | D47: 1000 | E47: BL-N | F47: 1.8.25 | L47: Crystal Floyd, Alison Cowles | N47: Crystal.Floyd@acxiom.com; Alison.Cowles@acxiom.com
A48: Nabholz | B48: Table | C48: 850 | D48: 1000 | E48: BL-N | F48: 2.2.25 | L48: Jake Nabholz | N48: jake.nabholz@nabholz.com
A49: Malvern National Bank | B49: Table | C49: 850 | D49: 750 | E49: LH-O | F49: 2.18.25 | L49: Andy Harris, Alica Brown, Alexander Baney | N49: aharris@mnbbank.com; abrown@mnbbank.com; abaney@mnbbank.com
B50: Table | C50: 850
B51: Graduation Ticket | C51: 125
B52: Graduation Ticket | C52: 125
B53: Graduation Ticket | C53: 125
B54: Graduation Ticket | C54: 125
B55: Graduation Ticket | C55: 125
B56: Graduation Ticket | C56: 125
B57: Graduation Ticket | C57: 125
B58: Graduation Ticket | C58: 125
B59: Graduation Ticket | C59: 125
B60: Graduation Ticket | C60: 125
K65: =SUM(K9:K64) -> 40805
E300: BL-O
E301: BL-N
E302: BL
E303: CP-O
E304: CP-N
E305: CP
E306: JG-O
E307: JG-N
E308: JG
E309: JE-O
E310: JE-N
E311: JE
... E317: LH

Sheet Diversity in Business
A1: DIVERSITY IN BUSINESS | B1: 2025 | S1: DIVERSITY IN BUSINESS | T1: 2024
A2: Total Sponsorship Amount Sold | B2: =SUM(D9:D41) -> 17150 | G2: Follow-up with Jake Nabholz closer to the event, re: involvement | K2: OUTSTANDING | S2: Total Sponsorship Amount Sold | T2: =SUM(U9:U31) -> 27925
A3: Budget Goal | B3: 18000 | G3: Follow-up with Southern Tee's: pending date they may join as an Advocate $1,000 | K3: =SUM(K35-B2) -> -2500 | S3: Budget Goal | T3: 16000
A4: Remaining Balance | B4: =MIN(B2-B3) -> -850 | K4: =K35/B2 -> 0.85422741 | S4: Remaining Balance | T4: =MIN(T2-T3) -> 11925
A5: Stretch Goal | B5: 32000 | S5: Stretch Goal | T5: 25000
A6: Remaining Balance | B6: =MIN(B2-B5) -> -14850 | S6: Remaining Balance | T6: =MIN(T2-T5) -> 2925
A8: SPONSOR NAME | B8: SPONSORSHIP | C8: COST | D8: PRICE PLEDGED | E8: SOLD BY | F8: DATE SOLD | G8: NOTES | H8: SPECIAL BILLING | I8: INVOICED | J8: DATE PAID | K8: PAID AMOUNT | L8: CONTACT | M8: PHONE | N8: EMAIL | P8: SOLD BY | Q8: PLEDGED | S8: SPONSOR NAME | T8: SPONSORSHIP | U8: PRICE PLEDGED | V8: SOLD BY
A9: Insight | B9: Title | C9: 5000 | D9: 4500 | E9: CP-N | F9: 2.19.25 | H9: YES | J9: 9/24/2025, 12/2/25 | K9: =1260+3240 -> 4500 | L9: Steven Tyler, Jenny Vallas | N9: steven.tyler@insight.com; jenny.vallas@insight.com | P9: BL | Q9: 6850 | S9: Acxiom | T9: Advocate | U9: 1000 | V9: BL
A10: Conway Corp. | B10: Presenting | C10: 2500 | D10: 2500 | E10: BL | F10: 12.12.24 | H10: YES | J10: 3.24.25 | K10: 2500 | L10: Crystal Kemp | N10: Crystal.Kemp@conwaycorp.com | P10: BL-N | Q10: 2500 | S10: Arkansas Heart Association | T10: Ticket | U10: 0 | V10: JE-N
A11: Turbare | B11: Presenting | C11: 2500 | D11: 2500 | E11: BL-N | F11: 1.3.25 | H11: YES | L11: Laura Martin, Andria White | N11: ceo@turbare.org; awhite@turbare.org | P11: BL-O | S11: Arvest | T11: Advocate | U11: 1000 | V11: BL
B12: Presenting | C12: 2500 | P12: CP | S12: Bledsoe Chiropractic | T12: Advocate | U12: 1000 | V12: LC-N
A13: Cadence Bank | B13: Awards | C13: 1500 | D13: 1500 | E13: LH | F13: 2.28.25 | I13: 10/23/25 GB | J13: 45957 | K13: 1500 | L13: Tom Nelson | N13: tom.nelson@cadencebank.com | P13: CP-N | Q13: 4800 | S13: Cadence Bank | T13: Awards | U13: 1500 | V13: LH-N
A14: Leah Brown, ERA Team | B14: Advocate | C14: 1500 | D14: 1000 | E14: LC | F14: 5.19.25 | I14: 10/23/25 GB | J14: 46006 | K14: 1000 | L14: Leah Brown | N14: leahbrownera@gmail.com | P14: CP-O | S14: Century 21 Sandstone Real Estate Group | T14: Speaker | U14: 1500 | V14: LH
B15: Awards | C15: 1500 | P15: JE | S15: City of Conway | T15: Ticket | U15: 0
B16: Feature | C16: 1500 | P16: JE-N | S16: Conductor | T16: Advocate | U16: 0 | V16: LH
A17: UCA Foundation | B17: Advocate | C17: 1000 | D17: 500 | E17: LH | F17: 12.11.24 | I17: 10/23/25 GB | J17: 45960 | K17: 500 | L17: Amy Whitehead, Mary Lackie | N17: amyw@uca.edu; mlackie@uca.edu | P17: JE-O | S17: Conway Corporation | T17: Presenting | U17: 2500 | V17: BL
A18: Conway Regional | B18: Advocate | C18: 1000 | D18: 1000 | E18: BL | F18: 12.30.24 | I18: 10/23/25 GB | J18: 45961 | K18: 1000 | L18: Rebekah Fincher | N18: rfincher@conwayregional.org | P18: JG | S18: Conway Regional | T18: Advocate | U18: 1000 | V18: BL
A19: Simmons Bank | B19: Advocate | C19: 1000 | D19: 1000 | E19: BL | F19: 1.2.25 | I19: 10/23/25 GB | J19: 45967 | K19: 1000 | L19: Justin McCarty | N19: justin.mccarty@simmonsbank.com | P19: JG-N | S19: EOS Worldwide: Drew Spurgers | T19: Title | U19: 5000 | V19: LH-N
A20: Acxiom | B20: Advocate | C20: 1000 | D20: 1000 | E20: BL | F20: 1.8.25 | I20: 10/23/25 GB | J20: 45981 | K20: 1000 | L20: Crystal Floyd, Alison Cowles | N20: Crystal.Floyd@acxiom.com; Alison.Cowles@acxiom.com | P20: JG-O | S20: First Arkansas Bank & Trust | T20: Advocate | U20: 0 | V20: LH
A21: Conductor | B21: Advocate | C21: 1000 | D21: 0 | E21: LH | F21: 1.13.25 | G21: 15 seats | I21: 0 | L21: Grace Rains | N21: grace@arconductor.org | P21: LC | Q21: 1000 | S21: First Security Bank | T21: Ticket | U21: 350 | V21: BL
A22: Arvest | B22: Advocate | C22: 1000 | D22: 1000 | E22: BL | F22: 2.4.25 | H22: YES | J22: 4.28.25 | K22: 1000 | L22: Brooks Davis, Maret Cahill Wicks | N22: mcahillwicks@arvest.com; bdavis3@arvest.com | P22: LC-N | S22: Insight | T22: Awards | U22: 1500 | V22: CP-N
A23: Clayton Conway | B23: Ticket | C23: 75 | D23: 300 | E23: CP-N | F23: 3.10.25 | G23: 4 tickets, All communications – Jamar Murchison – jamar.murchison@claytonhomes.com All communications – Stephanie Amerson – stephanie.amerson@claytonhomes.com Billing – Jake Turpin – jake.turpin@claytonhomes.com | I23: 10/23/25 GB | J23: 45964 | K23: 300 | L23: Jake Turpin | N23: jake.turpin@claytonhomes.com | P23: LC-O | S23: Lake Liquor | T23: Advocate | U23: 1000 | V23: LC
A24: First Security Bank | B24: Ticket | C24: 75 | D24: 350 | E24: BL | F24: 3.19.25 | I24: 10/23/25 GB | J24: 45973 | K24: 350 | L24: Stefanie Vann | N24: stefanie.vann@fsbank.com | P24: LH | Q24: 2000 | S24: Leah Brown, ERA Team | T24: Presenting | U24: 2500 | V24: LC-N
B25: Ticket | C25: 75 | P25: LH-N | S25: Melvin's Painting/MK Events Center | T25: Advocate | U25: 1000 | V25: LH
B26: Ticket | C26: 75 | P26: LH-O | S26: Nabholz | T26: Advocate | U26: 1000 | V26: BL
B27: Ticket | C27: 75 | P27: (blank) | S27: Simmons Bank | T27: Advocate | U27: 1000 | V27: BL
B28: Ticket | C28: 75 | P28: TOTAL | Q28: 17150 | S28: Snap-on | T28: Presenting | U28: 2500 | V28: BL-N
B29: Ticket | C29: 75 | S29: The Max | T29: Ticket | U29: 75
B30: Ticket | C30: 75 | S30: Turbare | T30: Awards | U30: 1500 | V30: BL
B31: Ticket | C31: 75 | S31: UCA | T31: Advocate | U31: 1000 | V31: LH-N
B32: Ticket | C32: 75
K35: =SUM(K9:K34) -> 14650
E300: BL-O
E301: BL-N
E302: BL
E303: CP-O
E304: CP-N
E305: CP
E306: JG-O
E307: JG-N
E308: JG
E309: JE-O
E310: JE-N
E311: JE
... E317: LH

Sheet Government Affairs
A1: GOVERNMENT AFFAIRS | B1: 2025
A2: Total Sponsorship Amount Sold | B2: =SUM(D9:D47) -> 90000 | K2: OUTSTANDING
A3: Budget Goal | B3: 81000 | K3: =SUM(K47-B2) -> 0
A4: Remaining Balance | B4: =MIN(B2-B3) -> 9000 | K4: =K47/B2 -> 1
A5: Stretch Goal | B5: 90000
A6: Remaining Balance | B6: =MIN(B2-B5) -> 0
A8: SPONSOR NAME | B8: UNDERWRITER | C8: COST | D8: PRICE PLEDGED | E8: SOLD BY | F8: DATE SOLD | G8: NOTES | H8: SPECIAL BILLING | I8: INVOICED | J8: DATE PAID | K8: PAID AMOUNT | L8: CONTACT | M8: PHONE | N8: EMAIL | P8: SOLD BY | Q8: PLEDGED
A9: Acxiom | B9: Underwriter | C9: 3000 | D9: 3000 | E9: BL | F9: 1.8.25 | J9: 4.3.25 | K9: 3000 | L9: Crystal Floyd, Alison Cowles | N9: Crystal.Floyd@acxiom.com; Alison.Cowles@acxiom.com | P9: BL | Q9: 42000
A10: Arvest | B10: Underwriter | C10: 3000 | D10: 3000 | E10: BL | F10: 2.4.25 | J10: 3.31.25 | K10: 3000 | L10: Brooks Davis, Maret Cahill Wicks | N10: mcahillwicks@arvest.com; bdavis3@arvest.com | P10: BL-N | Q10: 15000
A11: Baptist Health Conway | B11: Underwriter | C11: 3000 | D11: 3000 | E11: JG | F11: 1.13.25 | J11: 3.14.25 | K11: 3000 | L11: April Bennett | P11: BL-O
A12: Clayton Conway | B12: Underwriter | C12: 3000 | D12: 0 | E12: CP-N | F12: 3.10.25 | L12: Jamar Murchison | N12: jamar.murchison@claytonhomes.com | P12: CP
A13: Conductor | B13: Underwriter | C13: 3000 | D13: 3000 | E13: LH-O | F13: 1.13.25 | J13: 2.25.25 | K13: 3000 | L13: Grace Rains | N13: grace@arconductor.org | P13: CP-N | Q13: 0
A14: Conway Corp | B14: Underwriter | C14: 3000 | D14: 0 | F14: 8.26.25 | G14: per agreement | L14: Bret Carroll | P14: CP-O
A15: Conway Regional | B15: Underwriter | C15: 3000 | D15: 3000 | E15: BL | F15: 12.30.24 | J15: 2.28.25 | K15: 3000 | L15: Rebekah Fincher, Matt Troup | N15: rfincher@conwayregional.org; matt.troup@conwayregional.org | P15: JE
A16: Crafton Tull | B16: Underwriter | C16: 3000 | D16: 3000 | E16: BL | F16: 1.10.25 | H16: YES | J16: 3.19.25 | K16: 3000 | L16: Lane Housley | N16: lane.housley@craftontull.com | P16: JE-N
A17: Douglas Companies | B17: Underwriter | C17: 3000 | P17: JE-O
A18: Ensono | B18: Underwriter | C18: 3000 | D18: 3000 | E18: BL | F18: 5.4.25 | H18: YES | J18: 8/25/2025, 9/29/25 | K18: =1000+1000+1000 -> 3000 | L18: Michelle McKown | N18: michelle.mckown@ensono.com <Michelle.McKown@Ensono.com> | P18: JG | Q18: 12000
A19: First Arkansas Bank & Trust | B19: Underwriter | C19: 3000 | D19: 3000 | E19: LH | F19: 12.9.24 | H19: YES | J19: 1.31.25 | K19: 3000 | L19: John Simmons, Mark Wilson | N19: jsimmons@fabandt.bank; mwilson@fabandt.bank | P19: JG-N
A20: First Community Bank | B20: Underwriter | C20: 3000 | D20: 3000 | E20: BL-N | F20: 4.7.25 | G20: Invoice Carrie Price: Carrie.Price@firstcommunity.net | J20: 4.14.25 | K20: 3000 | L20: Grant Gordy, Dale Cole, Boris Dover | N20: Grant.Gordy@firstcommunity.net; Dale.Cole@firstcommunity.net Boris.Dover@firstcommunity.net | P20: JG-O
A21: First Security Bank | B21: Underwriter | C21: 3000 | D21: 3000 | E21: BL | F21: 3.19.25 | J21: 3.14.25 | K21: 3000 | P21: LC
A22: First Service Bank | B22: Underwriter | C22: 3000 | D22: 3000 | E22: BL-N | F22: 2.3.25 | J22: 45940 | K22: 3000 | L22: Tom Grumbles | M22: 870.866.9232 | N22: tom.grumbles@firstservicebank.com | P22: LC-N
A23: Flywheel Energy | B23: Underwriter | C23: 3000 | D23: 3000 | E23: BL | F23: 2.28.25 | H23: YES | J23: 45908 | K23: 3000 | L23: Andy Miller | N23: andy.miller@flywheelenergy.com | P23: LC-O
A24: GARVER | B24: Underwriter | C24: 3000 | D24: 3000 | E24: JG | F24: 2.18.25 | J24: 2.28.25 | K24: 3000 | L24: Dustin Tackett | N24: DLTackett@GarverUSA.com | P24: LH | Q24: 15000
A25: Green Bay Packaging | B25: Underwriter | C25: 3000 | D25: 3000 | E25: BL | F25: 12.3.24 | H25: YES | J25: 1.30.25 | K25: 3000 | L25: Brad Harville, Christy Prater | N25: bharville@gbp.com, cprater@gbp.com | P25: LH-N | Q25: 3000
A26: H+N Architects | B26: Underwriter | C26: 3000 | D26: 3000 | E26: LH-N | F26: 12.16.24 | H26: YES | J26: 4.25.25 | K26: 3000 | L26: Liz Hamilton, Joanna Nabholz | N26: liz@hnarch.com; joanna@hnarch.com | P26: LH-O | Q26: 3000
A27: Hendrix | B27: Underwriter | C27: 3000 | D27: 3000 | E27: JG | F27: 12.17.24 | J27: 2.25.25 | K27: 3000 | L27: Karen Petersen | N27: petersen@hendrix.edu | P27: (blank)
A28: HSA Engineering | B28: Underwriter | C28: 3000 | D28: 3000 | E28: LH | F28: 2.7.25 | H28: YES | J28: 3.7.25 | K28: 3000 | L28: Trey White, Michael Rappold | N28: twhite@hsaconsultants.com; mrappold@hsaconsultants.com | P28: TOTAL | Q28: 90000
A29: Klaasmeyer | B29: Underwriter | C29: 3000 | D29: 3000 | E29: BL | F29: 3.4.25 | J29: 3.4.25 | K29: 3000
A30: Mercer Conway | B30: Underwriter | C30: 3000
A31: Nabholz | B31: Underwriter | C31: 3000 | D31: 3000 | E31: BL | F31: 2.2.25 | J31: 3.11.25 | K31: 3000 | L31: Jake Nabholz | N31: jake.nabholz@nabholz.com
A32: Nativ State | B32: Underwriter | C32: 3000 | D32: 3000 | E32: LH | F32: 4.16.25 | J32: 5.29.25 | K32: 3000 | L32: Stuart Allen | N32: stuart@nativstate.com
A33: Ozark Mountain Construction | B33: Underwriter | C33: 3000 | D33: 3000 | E33: BL-N | F33: 4.8.25 | H33: YES | J33: 5.12.25 | K33: 3000 | L33: Scott and Laura Pelley | N33: laurapelley@gmail.com; scott@ozarkmtnco.com
A34: Pafford | B34: Underwriter | C34: 3000 | D34: 3000 | E34: BL | J34: 3.18.25 | K34: 3000
A35: Pediatrics Plus | B35: Underwriter | C35: 3000
A36: Reliance Health Care, Incite Rehab, Heartland Pharmacy, Heritage Living Center | B36: Underwriter | C36: 3000 | D36: 3000 | E36: LH | F36: 4.7.25 | H36: YES | J36: 5.27.25 | K36: 3000
A37: Rogers Group | B37: Underwriter | C37: 3000 | D37: 3000 | E37: BL | F37: 1.3.25 | J37: 3.10.25 | K37: 3000 | L37: Mike Connelly | N37: mike.connelly@rogersgroupinc.com
A38: Tokusen | B38: Underwriter | C38: 3000
A39: TriTechne | B39: Underwriter | C39: 3000 | D39: 3000 | E39: BL-N | F39: 1.9.25 | G39: Please send all invoices to ap@tritechne.com and Kara.Turner@tritechne.com | J39: 46001 | K39: 3000 | L39: Lauren Blackwell | N39: lauren.blackwell@tritechne.com
A40: Turbare | B40: Underwriter | C40: 3000 | D40: 3000 | E40: BL | F40: 1.3.25 | H40: YES | J40: 4.15.25 | K40: 3000 | L40: Laura Martin, Andria White | N40: ceo@turbare.org; awhite@turbare.org
A41: UACCM | B41: Underwriter | C41: 3000
A42: UCA | B42: Underwriter | C42: 3000 | D42: 3000 | E42: LH | F42: 12.11.24 | J42: 7.17.25 | K42: 3000 | L42: Amy Whitehead, Mary Lackie, Houston Davis | N42: amyw@uca.edu; mlackie@uca.edu
A43: Virco | B43: Underwriter | C43: 3000 | D43: 3000 | E43: BL | F43: 12.2.24 | H43: YES | J43: 1.29.25 | K43: 3000 | L43: Scotty Bell, Steve Presley | N43: scottybell@virco.com; stevepresley@virco.com
A44: Weaver Bailey | B44: Underwriter | C44: 3000 | D44: 3000 | E44: JG | F44: 3.26.25 | J44: 3.24.25 | K44: 3000
A45: Westrock Coffee | B45: Underwriter | C45: 3000 | D45: 3000 | E45: BL-N | F45: 3.14.25 | H45: YES | J45: 45902 | K45: 3000 | L45: Will Ford | N45: will.ford@westrockcoffee.com
K47: =SUM(K9:K46) -> 90000
E299: BL-O
E300: BL-N
E301: BL
E302: CP-O
E303: CP-N
E304: CP
E305: JG-O
E306: JG-N
E307: JG
E308: JE-O
E309: JE-N
E310: JE
... E316: LH

Sheet Happy Birthday Conway
A1: HAPPY BIRTHDAY CONWAY | B1: 2025
A2: Total Sponsorship Amount Sold | B2: =SUM(D9:D76) -> 108750 | K2: OUTSTANDING
A3: Budget Goal | B3: 0 | K3: =SUM(K76-B2) -> -13000
A4: Remaining Balance | B4: =MIN(B3-B2) -> -108750 | K4: =K76/B2 -> 0.88045977
A5: Stretch Goal | B5: 75000
A6: Remaining Balance | B6: =MIN(B2-B5) -> 33750
A8: SPONSOR NAME | B8: SPONSORSHIP | C8: COST | D8: PRICE PLEDGED | E8: SOLD BY | F8: DATE SOLD | G8: NOTES | H8: SPECIAL BILLING | I8: INVOICED | J8: DATE PAID | K8: PAID AMOUNT | L8: CONTACT | M8: PHONE | N8: EMAIL | P8: SOLD BY | Q8: PLEDGED
A9: Conway Corp. | B9: Presenting | C9: 10000 | D9: 2500 | E9: BL | F9: 12.12.24 | H9: YES | J9: 3.24.25 | K9: 2500 | L9: Crystal Kemp | N9: Crystal.Kemp@conwaycorp.com | P9: BL | Q9: 2500
A10: Conway Regional | B10: Presenting | C10: 10000 | D10: 5000 | E10: BL-N | F10: 12.30.24 | I10: 8/19/25 GB | J10: 45961 | K10: 5000 | L10: Rebekah Fincher | N10: rfincher@conwayregional.org | P10: BL-N | Q10: 55500
A11: Turbare | B11: Presenting | C11: 10000 | D11: 5000 | E11: BL-N | F11: 1.3.25 | H11: YES | J11: 46008 | K11: 5000 | L11: Laura Martin, Andria White | N11: ceo@turbare.org; awhite@turbare.org | P11: BL-O
A12: GARVER | B12: Presenting | C12: 10000 | D12: 5000 | E12: JG-N | F12: 2.18.25 | I12: 8/19/25 GB | J12: 45902 | K12: 5000 | L12: Dustin Tackett | N12: DLTackett@GarverUSA.com | P12: CP
A13: Snap-on Equipment | B13: Presenting | C13: 10000 | D13: 5000 | E13: BL-N | F13: 9.19.25 | G13: Will donate space to a local business. Provide a blend of Large, XL and XXL shirts. | I13: 9/25/25 GB | J13: 45939 | K13: 5000 | L13: Scott Champlin | N13: Scott.L.Champlin@snapon.com | P13: CP-N | Q13: 7500
A14: Carty, Harding & Hearn | B14: Presenting | C14: 10000 | D14: 5000 | E14: LH-N | F14: 9.25.25 | I14: 9/25/25 GB | J14: 45930 | K14: 5000 | L14: Edmond Hurst | N14: ehurst@cartyco.com | P14: CP-O
A15: Weaver-Bailey Contractors | B15: Platinum | C15: 5000 | D15: 3500 | E15: JG-N | F15: 9.9.25 | I15: 9/16/25 GB | J15: 45951 | K15: 3500 | L15: Jon Stalnaker | N15: jstalnaker@weaverbailey.com | P15: JE
A16: Flywheel Energy | B16: Platinum | C16: 5000 | D16: 5000 | E16: BL-N | F16: 9.12.25 | I16: 9/16/25 GB | J16: 45966 | K16: 5000 | L16: Andy Miller | N16: andy.miller@flywheelenergy.com | P16: JE-N | Q16: 6500
B17: Platinum | C17: 5000 | P17: JE-O
B18: Platinum | C18: 5000 | P18: JG
A19: Chris Crain Enterprises | B19: Gold | C19: 2500 | D19: 2500 | E19: BL-N | F19: 11.20.24 | G19: Confirm with NK/BB which Chris Crain Enterprises company/companies will be featured on event. | I19: 8/19/25 GB | J19: 45902 | K19: =1250+1250 -> 2500 | L19: Brett Berry, Nita Kat Freeman | N19: brettberry@chriscraingroup.com; nitafreeman@chriscraingroup.com | P19: JG-N | Q19: 10250
A20: Rogers Group | B20: Gold | C20: 2500 | D20: 2500 | E20: BL-N | F20: 1.3.25 | I20: 8/19/25 GB | J20: 45902 | K20: 2500 | L20: Mike Connelly | N20: mike.connelly@rogersgroupinc.com | P20: JG-O
A21: TriTechne | B21: Gold | C21: 2500 | D21: 2500 | E21: BL-N | F21: 1.9.25 | G21: Please send all invoices to ap@tritechne.com and Kara.Turner@tritechne.com | I21: 8/19/25 GB | J21: 46001 | K21: 2500 | L21: Lauren Blackwell | N21: lauren.blackwell@tritechne.com | P21: LC
A22: DKM Construction | B22: Gold | C22: 2500 | D22: 2500 | E22: CP-N | F22: 2.17.25 | H22: YES | J22: 45985 | K22: 2500 | L22: Kim Morehart, Daniel Morehart | N22: kimm.dkm@gmail.com; danielm.dkm@gmail.com | P22: LC-N | Q22: 8000
A23: Insight | B23: Gold | C23: 2500 | D23: 2500 | E23: CP-N | F23: 2.19.25 | H23: YES | J23: 45924 | K23: 2500 | L23: Steven Tyler, Jenny Vallas | N23: steven.tyler@insight.com; jenny.vallas@insight.com | P23: LC-O
A24: Sinco | B24: Gold | C24: 2500 | D24: 2500 | E24: CP-N | F24: 2.21.25 | H24: YES | J24: 8/19/2025, 11/18/25 | K24: =543.75+1956.25 -> 2500 | L24: Parker Spradlin, Grey Williams, Rhonda Wilson | N24: Pspradlin@sincoinc.com; gwilliams@sincoinc.com; rwilson@sincoinc.com | P24: LH
A25: SMC Conway, A Division of GBP | B25: Gold | C25: 2500 | D25: 0 | E25: LH-N | F25: 3.14.25 | G25: in-kind for production | I25: 0 | L25: Jimmy Toal, Sonya Griffis | N25: jimmy.toal@smcpackaging.com; sonya.griffis@smcpackaging.com | P25: LH-N | Q25: 18500
A26: Ozark Mountain Construction | B26: Gold | C26: 2500 | D26: 2500 | E26: BL-N | F26: 4.8.25 | G26: Include Erin Long (erin@citychurch.tv) on event communication. | H26: YES | J26: 5.12.25 | K26: 2500 | L26: Scott and Laura Pelley | N26: laurapelley@gmail.com; scott@ozarkmtnco.com | P26: LH-O
A27: Fureigh Electric | B27: Gold | C27: 2500 | D27: 2000 | E27: LC-N | F27: 7.8.25 | H27: YES | L27: Ben Fureigh | N27: ben@fureighinc.com | P27: (blank)
A28: Trinity Development | B28: Gold | C28: 2500 | D28: 2500 | E28: LH-N | F28: 9.10.25 | I28: 9/11/25 GB | J28: 45918 | K28: 2500 | L28: Courtnie Pledger | N28: cpledger@trinitydevelopmentinc.com | P28: TOTAL | Q28: 108750
A29: Nabholz Construction | B29: Gold | C29: 2500 | D29: 2500 | E29: BL-N | F29: 9.14.25 | I29: 9/15/25 GB | J29: 45922 | K29: 2500 | L29: Jake Nabholz | N29: jake.nabholz@nabholz.com
A30: Smurfit Westrock | B30: Gold | C30: 2500 | D30: 2500 | E30: BL-N | F30: 9.17.25 | I30: 9/22/25 GB | J30: 45992 | K30: 2500 | L30: Rickey Reynolds, Austin Tiner | N30: rickey.reynolds@smurfitwestrock.com; austin.tiner@smurfitwestrock.com
A31: Car-son Construction | B31: Gold | C31: 2500 | D31: 2500 | E31: BL-N | F31: 9.18.25 | H31: YES | L31: Brad Fason, Brian Fason | N31: bfason@car-son.com; bradfason@car-son.com
A32: Virco | B32: Gold | C32: 2500 | D32: 1000 | E32: BL-N | F32: 9.18.25 | I32: 9/29/25 GB | J32: 45999 | K32: 1000 | L32: Scotty Bell | N32: scottybell@virco.com
A33: Salter Construction | B33: Gold | C33: 2500 | D33: 2500 | E33: BL-N | F33: 9.22.25 | G33: Please add an additional 2 shirts. | I33: 9/22/25 GB | J33: 45930 | K33: 2500 | L33: Jennifer Mouser | N33: jmouser@salterconst.com
A34: Malys Family Entertainment Center | B34: Gold | C34: 2500 | D34: 2500 | E34: JE-N | F34: 9.22.25 | I34: 9/25/25 GB | J34: 45939 | K34: 2500 | L34: Bailey Webb | N34: bailey@malys-entertainment.com
B35: Gold | C35: 2500
A36: Acxiom | B36: Silver | C36: 1000 | D36: 1000 | E36: BL-N | F36: 1.8.25 | I36: 8/19/25 GB | J36: 45932 | K36: 1000 | L36: Crystal Floyd, Alison Cowles | N36: Crystal.Floyd@acxiom.com; Alison.Cowles@acxiom.com
A37: Baptist Health | B37: Silver | C37: 1000 | D37: 1000 | E37: JG-N | F37: 1.13.25 | I37: 8/19/25 GB | J37: 46010 | K37: 1000 | L37: April Bennett
A38: Crafton Tull | B38: Silver | C38: 1000 | D38: 1000 | E38: BL-N | F38: 1.10.25 | H38: YES | J38: 45943 | K38: 1000 | L38: Lane Housley | N38: lane.housley@craftontull.com
A39: Green Bay Packaging | B39: Silver | C39: 1000 | D39: 1500 | E39: BL-N | F39: 12.3.24 | H39: YES | J39: 45980 | K39: 1500 | L39: Brad Harville, Christy Prater | N39: bharville@gbp.com, cprater@gbp.com
A40: Winthrop Rockefeller Institute | B40: Silver | C40: 1000 | D40: 750 | E40: JG-N | F40: 2.4.25 | I40: 8/19/25 GB | J40: 46001 | K40: 750 | L40: Austin DuVall, Julia Dossett Morgan | N40: ADuVall@rockefellerinstitute.org; JMorgan@rockefellerinstitute.org
A41: Cintas | B41: Silver | C41: 1000 | D41: 1000 | E41: LH-N | F41: 2.25.24 | I41: 8/19/25 GB | L41: Mathew Hoppis | N41: HoppisM@cintas.com
A42: Cousins' | B42: Silver | C42: 1000 | D42: 0 | E42: LH-N | F42: 2.26.25 | G42: in-kind for hauling event materials | I42: 0 | L42: Adam Robertson, Tara Robertson | N42: adam@cousinsfurniture.com; tara@cousinsfurniture.com
A43: State Farm Jay Bernard | B43: Silver | C43: 1000 | D43: 1000 | E43: BL-N | F43: 2.28.25 | H43: YES | I43: 0 | J43: 3.19.25 | K43: 1000 | L43: Jay Bernard | N43: jay.bernard.l8if@statefarm.com
A44: Westrock Coffee | B44: Silver | C44: 1000 | D44: 1000 | E44: BL-N | F44: 3.14.25 | H44: YES | L44: Blair Peterson, Melissa Mackay | N44: blair.peterson@westrockcoffee.com; melissa.mackay@westrockcoffee.com
A45: Covington Companies | B45: Silver | C45: 1000 | D45: 1000 | E45: BL-N | F45: 3.24.25 | I45: 8/19/25 GB | J45: 45896 | K45: 1000 | L45: George Covington, Savannah Brorman | N45: gcov@conwaycorp.net; savannah@covingtoncompanies.net
A46: Klaasmeyer | B46: Silver | C46: 1000 | D46: 1000 | E46: BL-N | F46: 4.10.25 | I46: 8/19/25 GB | J46: 46008 | K46: 1000 | L46: Jessica Press | N46: jessica@klaasmeyer.com
A47: Harps | B47: Silver | C47: 1000 | D47: 1000 | E47: JE-N | F47: 8.29.25 | I47: 8/29/25 GB | J47: 45918 | K47: 1000 | L47: Sarah Thacker | N47: sthacker@harpsfood.com
A48: Farris Agency | B48: Silver | C48: 1000 | D48: 1000 | E48: JE-N | F48: 8.29.25 | I48: 9/4/25 GB | J48: 45912 | K48: 1000 | L48: Christina Horn (Invoice), Travis Mulhearn, Alan White | N48: christina@farrisagency.com; travis@farrisagency.com; alan@farrisagency.com
A49: Arisa Health | B49: Silver | C49: 1000 | D49: 1000 | E49: JE-N | F49: 9.4.25 | I49: 9/4/25 GB | L49: Brad Hyde | N49: brad.hyde@arisahealth.org
A50: Ott Insurance | B50: Silver | C50: 1000 | D50: 1000 | E50: LC-N | F50: 9.8.25 | I50: 9/11/25 GB | J50: 45950 | K50: 1000 | L50: Michelle Mallett | N50: michellemallett@ottinsurance.com
A51: RE/MAX Elite, The Emily Walter Team | B51: Silver | C51: 1000 | D51: 1000 | E51: LC-N | F51: 9.8.25 | I51: 9/11/25 GB | J51: 45953 | K51: 1000 | L51: Emily Walter | N51: emilywalterrealtor@gmail.com
A52: RE/MAX Elite, Karen Ferguson | B52: Silver | C52: 1000 | D52: 1000 | E52: LC-N | F52: 9.9.25 | I52: 9/11/25 GB | L52: Karen Ferguson | N52: karenferguson501@gmail.com
A53: L&P Construction | B53: Silver | C53: 1000 | D53: 1000 | E53: LC-N | F53: 9.9.25 | I53: 9/11/25 GB | J53: 46009 | K53: 1000 | L53: Claire Carter Smithson | N53: claire@homewardhomes.com
A54: Centennial Bank | B54: Silver | C54: 1000 | D54: 1000 | E54: BL-N | F54: 9.12.25 | I54: 9/15/25 GB | J54: 45917 | K54: 1000 | L54: Scott Schwartz | N54: dschwartz@my100bank.com
A55: First Security Bank | B55: Silver | C55: 1000 | D55: 1000 | E55: BL-N | F55: 9.12.25 | I55: 9/15/25 GB | J55: 45973 | K55: 1000 | L55: Stefanie Vann | N55: stefanie.vann@fsbank.com
A56: Interstate Group LLC | B56: Silver | C56: 1000 | D56: 1000 | E56: BL-N | F56: 9.12.25 | G56: Jennifer to complete vendor setup form and return to Leslie. | I56: 9/15/25 GB | J56: 46006 | K56: 1000 | L56: Richard Asbell, Leslie Schreckhise | N56: asbellr@interstatecargo.com; lschreckhise@trailersplus.com
A57: Crosscreek Sandwich Shoppe | B57: Silver | C57: 1000 | D57: 1000 | E57: LC-N | F57: 9.12.25 | I57: 9/15/25 GB
A58: Bell & Company | B58: Silver | C58: 1000 | D58: 1000 | E58: LC-N | F58: 9.15.25 | I58: 9/16/25 GB | J58: 46010 | K58: 1000
A59: Landmark CPAs | B59: Silver | C59: 1000 | D59: 1000 | E59: LH-N | F59: 9.16.25 | G59: small t-shirt | H59: YES | J59: 45973 | K59: 500 | L59: Randy Milligan | N59: RMilligan@landmarkcpas.com
A60: Freyaldenhoven Heating and Cooling | B60: Silver | C60: 1000 | D60: 1000 | E60: LH-N | F60: 9.17.25 | I60: 9/22/25 GB | J60: 45930 | K60: 1000 | L60: John Freyaldenhoven | N60: john@freyaldenhoven.com
A61: American Safeguard Insurance | B61: Silver | C61: 1000 | D61: 1000 | E61: LH-N | F61: 9.17.25 | H61: YES | J61: 45933 | K61: 1000 | L61: Brittany Gwatney, Jeremy Davis, Jason Smith | N61: bgwatney@asiagents.com; jdavis@asiagents.com; jsmith@asiagents.com
A62: Tommy's Express | B62: Silver | C62: 1000 | D62: 1000 | E62: JE-N | F62: 9.17.25 | I62: 9/22/25 GB | J62: 46009 | K62: 1000 | L62: Kason | N62: kasonk@advancedwashnetwork.com
A63: Engage Management | B63: Silver | C63: 1000 | D63: 1000 | E63: BL-N | F63: 9.18.25 | I63: 9/22/25 GB | L63: Morgan Lefler | N63: morgan.lefler@engagemanagement.com
A64: Caldwell Toyota | B64: Silver | C64: 1000 | D64: 1000 | E64: LH-N | F64: 9.18.25 | I64: 9/22/25 GB | J64: 45930 | K64: 1000 | L64: Jay Caldwell | N64: jay@caldwellcares.com
A65: Arkansas Business | B65: Silver | C65: 1000 | D65: 1000 | E65: LH-N | F65: 9.18.25 | I65: 9/22/25 GB | J65: 45951 | K65: 1000 | L65: Mitch Bettis | N65: mbettis@abpg.com
A66: Cherokee Roland | B66: Silver | C66: 1000 | D66: 1000 | E66: LH-N | F66: 9.22.25 | I66: 9/22/25 GB | J66: 45932 | K66: 1000 | L66: Allie Ornelas | N66: allison.ornelas@cnent.com
A67: Meridian Investment Advisors | B67: Silver | C67: 1000 | D67: 1000 | E67: LH-N | F67: 9.22.25 | I67: 9/22/25 GB | J67: 45946 | K67: 1000 | L67: Pat Moon | N67: pmoon@meridiania.com
A68: HCJ CPAs and Advisors | B68: Silver | C68: 1000 | D68: 1000 | E68: LH-N | F68: 9.23.25 | I68: 9/23/25 GB | J68: 45936 | K68: 1000 | L68: Karen Garrett | N68: KGarrett@hcjcpa.com>
A69: La Pista, Los 3 Potrillos, Don Pepes | B69: Silver | C69: 1000 | D69: 1000 | E69: LH-N | F69: 9.22.25 | G69: When invoice is ready, email to Lindsay. | I69: 9/23/25 GB | J69: 45938 | K69: 1000 | L69: Ernesto Castro, Jose Castro | M69: Ernesto: 501-733-0217; Jose: 501-472.7615
A70: Crews & Associates | B70: Silver | C70: 1000 | D70: 1000 | E70: BL-N | F70: 9.23.25 | I70: 9/25/25 GB | J70: 45930 | K70: 1000 | L70: Paul Phillips | N70: pphillips@crewsfs.com
A71: Stoby's | B71: Silver | C71: 1000 | D71: 1000 | E71: LH-N | F71: 9.24.25 | I71: 9/25/25 GB | L71: Patti Stobaugh | N71: patti@stobys.com
A72: Pafford Medical Services | B72: Silver | C72: 1000 | D72: 1000 | E72: BL-N | F72: 9.30.25 | I72: 10/2/25 GB | L72: Suzie Gresham | N72: suzie@paffordems.com; jamie@paffordems.com
A73: Conway Wealth Management | B73: Silver | C73: 1000 | D73: 1000 | E73: BL-N | F73: 9.30.25 | I73: 10/2/25 GB | J73: 45950 | K73: 1000 | L73: Rita Stapleton | N73: rita@conwaywm.com
K76: =SUM(K9:K73) -> 95750
E300: BL-O
